parte3/contador_bin/contador_bin.vhd
library IEEE;
use IEEE.STD_LOGIC_1164.ALL;
use IEEE.NUMERIC_STD.ALL;

entity contador_bin is
    Port (
        clk   : in  STD_LOGIC; -- Clock
        reset : in  STD_LOGIC; -- Reset assíncrono
        count : out STD_LOGIC_VECTOR (3 downto 0) -- Saída do contador
    );
end contador_bin;

architecture Behavioral of contador_bin is
    signal temp_count : UNSIGNED (3 downto 0) := (others => '0'); -- Use UNSIGNED para operações aritméticas
begin
    process (clk, reset)
    begin
        if reset = '1' then
            temp_count <= (others => '0'); -- Reseta o contador
        elsif rising_edge(clk) then
            temp_count <= temp_count + 1; -- Incrementa o contador
        end if;
    end process;

    count <= STD_LOGIC_VECTOR(temp_count); -- Converte para STD_LOGIC_VECTOR para a saída
end architecture;

parte3/contador_16bits/contador_16bits.vhd
library IEEE;
use IEEE.STD_LOGIC_1164.ALL;
use IEEE.NUMERIC_STD.ALL;

entity contador_16bits is
    Port (
        clk   : in  STD_LOGIC; -- Clock global
        reset : in  STD_LOGIC; -- Reset global
        count : out STD_LOGIC_VECTOR (15 downto 0) -- Saída do contador de 16 bits
    );
end contador_16bits;

architecture Structural of contador_16bits is
    -- Sinais internos para as saídas de cada contador de 4 bits e os carries
    signal count0, count1, count2, count3 : STD_LOGIC_VECTOR (3 downto 0);
    signal carry1, carry2, carry3 : STD_LOGIC; -- Carry entre os contadores

    -- Componente do contador binário de 4 bits
    component contador_bin is
        Port (
            clk   : in  STD_LOGIC;
            reset : in  STD_LOGIC;
            count : out STD_LOGIC_VECTOR (3 downto 0)
        );
    end component;
begin
    -- Instância do primeiro contador (LSB)
    contador0: contador_bin
        Port map (
            clk => clk,
            reset => reset,
            count => count0
        );

    -- Carry do primeiro contador
    carry1 <= '1' when count0 = "1111" else '0';

    -- Instância do segundo contador
    contador1: contador_bin
        Port map (
            clk => carry1, -- Clock do segundo contador é o carry do primeiro
            reset => reset,
            count => count1
        );

    -- Carry do segundo contador
    carry2 <= '1' when count1 = "1111" else '0';

    -- Instância do terceiro contador
    contador2: contador_bin
        Port map (
            clk => carry2, -- Clock do terceiro contador é o carry do segundo
            reset => reset,
            count => count2
        );

    -- Carry do terceiro contador
    carry3 <= '1' when count2 = "1111" else '0';

    -- Instância do quarto contador (MSB)
    contador3: contador_bin
        Port map (
            clk => carry3, -- Clock do quarto contador é o carry do terceiro
            reset => reset,
            count => count3
        );

    -- Concatenação das saídas
    count <= count3 & count2 & count1 & count0;
end Structural;

parte3/contador_16bits/contador_16bits_tb.vhd
library IEEE;
use IEEE.STD_LOGIC_1164.ALL;

entity contador_16bits_tb is
end contador_16bits_tb;

architecture Behavioral of contador_16bits_tb is
    signal clk   : STD_LOGIC := '0';
    signal reset : STD_LOGIC := '0';
    signal count : STD_LOGIC_VECTOR (15 downto 0);

    component contador_16bits
        Port (
            clk   : in  STD_LOGIC;
            reset : in  STD_LOGIC;
            count : out STD_LOGIC_VECTOR (15 downto 0)
        );
    end component;
begin
    uut: contador_16bits
        Port map (
            clk => clk,
            reset => reset,
            count => count
        );

    -- Clock Generation
    clk_process: process
    begin
        for i in 0 to 100 loop -- Gera 100 ciclos de clock
            clk <= '0';
            wait for 10 ns;
            clk <= '1';
            wait for 10 ns;
        end loop;
        wait; -- Para o processo após 100 ciclos
    end process;

    -- Stimulus Process
    stimulus_process: process
    begin
        -- Reset
        reset <= '1';
        wait for 20 ns;
        reset <= '0';

        -- Deixe o contador funcionar por algum tempo
        wait for 2000 ns;

        -- Encerrar a simulação
        wait;
    end process;
end Behavioral;

parte3/contador_16bits/work/wave.vcd
$date
  Mon Dec 02 19:01:57 2024
$end
$version
  GHDL v0
$end
$timescale
  1 fs
$end
$scope module standard $end
$upscope $end
$scope module std_logic_1164 $end
$upscope $end
$scope module numeric_std $end
$upscope $end
$scope module contador_16bits_tb $end
$var reg 1 ! clk $end
$var reg 1 " reset $end
$var reg 16 # count[15:0] $end
$scope module uut $end
$var reg 1 $ clk $end
$var reg 1 % reset $end
$var reg 16 & count[15:0] $end
$var reg 4 ' count0[3:0] $end
$var reg 4 ( count1[3:0] $end
$var reg 4 ) count2[3:0] $end
$var reg 4 * count3[3:0] $end
$var reg 1 + carry1 $end
$var reg 1 , carry2 $end
$var reg 1 - carry3 $end
$scope module contador0 $end
$var reg 1 . clk $end
$var reg 1 / reset $end
$var reg 4 0 count[3:0] $end
$var reg 4 1 temp_count[3:0] $end
$upscope $end
$scope module contador1 $end
$var reg 1 2 clk $end
$var reg 1 3 reset $end
$var reg 4 4 count[3:0] $end
$var reg 4 5 temp_count[3:0] $end
$upscope $end
$scope module contador2 $end
$var reg 1 6 clk $end
$var reg 1 7 reset $end
$var reg 4 8 count[3:0] $end
$var reg 4 9 temp_count[3:0] $end
$upscope $end
$scope module contador3 $end
$var reg 1 : clk $end
$var reg 1 ; reset $end
$var reg 4 < count[3:0] $end
$var reg 4 = temp_count[3:0] $end
$upscope $end
$upscope $end
$upscope $end
$enddefinitions $end
#0
0!
1"
b0000000000000000 #
0$
1%
b0000000000000000 &
b0000 '
b0000 (
b0000 )
b0000 *
0+
0,
0-
0.
1/
b0000 0
b0000 1
02
13
b0000 4
b0000 5
06
17
b0000 8
b0000 9
0:
1;
b0000 <
b0000 =
#10000000
1!
1$
1.
#20000000
0!
0"
0$
0%
0.
0/
03
07
0;
#30000000
1!
b0000000000000001 #
1$
b0000000000000001 &
b0001 '
1.
b0001 0
b0001 1
#40000000
0!
0$
0.
#50000000
1!
b0000000000000010 #
1$
b0000000000000010 &
b0010 '
1.
b0010 0
b0010 1
#60000000
0!
0$
0.
#70000000
1!
b0000000000000011 #
1$
b0000000000000011 &
b0011 '
1.
b0011 0
b0011 1
#80000000
0!
0$
0.
#90000000
1!
b0000000000000100 #
1$
b0000000000000100 &
b0100 '
1.
b0100 0
b0100 1
#100000000
0!
0$
0.
#110000000
1!
b0000000000000101 #
1$
b0000000000000101 &
b0101 '
1.
b0101 0
b0101 1
#120000000
0!
0$
0.
#130000000
1!
b0000000000000110 #
1$
b0000000000000110 &
b0110 '
1.
b0110 0
b0110 1
#140000000
0!
0$
0.
#150000000
1!
b0000000000000111 #
1$
b0000000000000111 &
b0111 '
1.
b0111 0
b0111 1
#160000000
0!
0$
0.
#170000000
1!
b0000000000001000 #
1$
b0000000000001000 &
b1000 '
1.
b1000 0
b1000 1
#180000000
0!
0$
0.
#190000000
1!
b0000000000001001 #
1$
b0000000000001001 &
b1001 '
1.
b1001 0
b1001 1
#200000000
0!
0$
0.
#210000000
1!
b0000000000001010 #
1$
b0000000000001010 &
b1010 '
1.
b1010 0
b1010 1
#220000000
0!
0$
0.
#230000000
1!
b0000000000001011 #
1$
b0000000000001011 &
b1011 '
1.
b1011 0
b1011 1
#240000000
0!
0$
0.
#250000000
1!
b0000000000001100 #
1$
b0000000000001100 &
b1100 '
1.
b1100 0
b1100 1
#260000000
0!
0$
0.
#270000000
1!
b0000000000001101 #
1$
b0000000000001101 &
b1101 '
1.
b1101 0
b1101 1
#280000000
0!
0$
0.
#290000000
1!
b0000000000001110 #
1$
b0000000000001110 &
b1110 '
1.
b1110 0
b1110 1
#300000000
0!
0$
0.
#310000000
1!
b0000000000011111 #
1$
b0000000000011111 &
b1111 '
b0001 (
1+
1.
b1111 0
b1111 1
12
b0001 4
b0001 5
#320000000
0!
0$
0.
#330000000
1!
b0000000000010000 #
1$
b0000000000010000 &
b0000 '
0+
1.
b0000 0
b0000 1
02
#340000000
0!
0$
0.
#350000000
1!
b0000000000010001 #
1$
b0000000000010001 &
b0001 '
1.
b0001 0
b0001 1
#360000000
0!
0$
0.
#370000000
1!
b0000000000010010 #
1$
b0000000000010010 &
b0010 '
1.
b0010 0
b0010 1
#380000000
0!
0$
0.
#390000000
1!
b0000000000010011 #
1$
b0000000000010011 &
b0011 '
1.
b0011 0
b0011 1
#400000000
0!
0$
0.
#410000000
1!
b0000000000010100 #
1$
b0000000000010100 &
b0100 '
1.
b0100 0
b0100 1
#420000000
0!
0$
0.
#430000000
1!
b0000000000010101 #
1$
b0000000000010101 &
b0101 '
1.
b0101 0
b0101 1
#440000000
0!
0$
0.
#450000000
1!
b0000000000010110 #
1$
b0000000000010110 &
b0110 '
1.
b0110 0
b0110 1
#460000000
0!
0$
0.
#470000000
1!
b0000000000010111 #
1$
b0000000000010111 &
b0111 '
1.
b0111 0
b0111 1
#480000000
0!
0$
0.
#490000000
1!
b0000000000011000 #
1$
b0000000000011000 &
b1000 '
1.
b1000 0
b1000 1
#500000000
0!
0$
0.
#510000000
1!
b0000000000011001 #
1$
b0000000000011001 &
b1001 '
1.
b1001 0
b1001 1
#520000000
0!
0$
0.
#530000000
1!
b0000000000011010 #
1$
b0000000000011010 &
b1010 '
1.
b1010 0
b1010 1
#540000000
0!
0$
0.
#550000000
1!
b0000000000011011 #
1$
b0000000000011011 &
b1011 '
1.
b1011 0
b1011 1
#560000000
0!
0$
0.
#570000000
1!
b0000000000011100 #
1$
b0000000000011100 &
b1100 '
1.
b1100 0
b1100 1
#580000000
0!
0$
0.
#590000000
1!
b0000000000011101 #
1$
b0000000000011101 &
b1101 '
1.
b1101 0
b1101 1
#600000000
0!
0$
0.
#610000000
1!
b0000000000011110 #
1$
b0000000000011110 &
b1110 '
1.
b1110 0
b1110 1
#620000000
0!
0$
0.
#630000000
1!
b0000000000101111 #
1$
b0000000000101111 &
b1111 '
b0010 (
1+
1.
b1111 0
b1111 1
12
b0010 4
b0010 5
#640000000
0!
0$
0.
#650000000
1!
b0000000000100000 #
1$
b0000000000100000 &
b0000 '
0+
1.
b0000 0
b0000 1
02
#660000000
0!
0$
0.
#670000000
1!
b0000000000100001 #
1$
b0000000000100001 &
b0001 '
1.
b0001 0
b0001 1
#680000000
0!
0$
0.
#690000000
1!
b0000000000100010 #
1$
b0000000000100010 &
b0010 '
1.
b0010 0
b0010 1
#700000000
0!
0$
0.
#710000000
1!
b0000000000100011 #
1$
b0000000000100011 &
b0011 '
1.
b0011 0
b0011 1
#720000000
0!
0$
0.
#730000000
1!
b0000000000100100 #
1$
b0000000000100100 &
b0100 '
1.
b0100 0
b0100 1
#740000000
0!
0$
0.
#750000000
1!
b0000000000100101 #
1$
b0000000000100101 &
b0101 '
1.
b0101 0
b0101 1
#760000000
0!
0$
0.
#770000000
1!
b0000000000100110 #
1$
b0000000000100110 &
b0110 '
1.
b0110 0
b0110 1
#780000000
0!
0$
0.
#790000000
1!
b0000000000100111 #
1$
b0000000000100111 &
b0111 '
1.
b0111 0
b0111 1
#800000000
0!
0$
0.
#810000000
1!
b0000000000101000 #
1$
b0000000000101000 &
b1000 '
1.
b1000 0
b1000 1
#820000000
0!
0$
0.
#830000000
1!
b0000000000101001 #
1$
b0000000000101001 &
b1001 '
1.
b1001 0
b1001 1
#840000000
0!
0$
0.
#850000000
1!
b0000000000101010 #
1$
b0000000000101010 &
b1010 '
1.
b1010 0
b1010 1
#860000000
0!
0$
0.
#870000000
1!
b0000000000101011 #
1$
b0000000000101011 &
b1011 '
1.
b1011 0
b1011 1
#880000000
0!
0$
0.
#890000000
1!
b0000000000101100 #
1$
b0000000000101100 &
b1100 '
1.
b1100 0
b1100 1
#900000000
0!
0$
0.
#910000000
1!
b0000000000101101 #
1$
b0000000000101101 &
b1101 '
1.
b1101 0
b1101 1
#920000000
0!
0$
0.
#930000000
1!
b0000000000101110 #
1$
b0000000000101110 &
b1110 '
1.
b1110 0
b1110 1
#940000000
0!
0$
0.
#950000000
1!
b0000000000111111 #
1$
b0000000000111111 &
b1111 '
b0011 (
1+
1.
b1111 0
b1111 1
12
b0011 4
b0011 5
#960000000
0!
0$
0.
#970000000
1!
b0000000000110000 #
1$
b0000000000110000 &
b0000 '
0+
1.
b0000 0
b0000 1
02
#980000000
0!
0$
0.
#990000000
1!
b0000000000110001 #
1$
b0000000000110001 &
b0001 '
1.
b0001 0
b0001 1
#1000000000
0!
0$
0.
#1010000000
1!
b0000000000110010 #
1$
b0000000000110010 &
b0010 '
1.
b0010 0
b0010 1
#1020000000
0!
0$
0.
#1030000000
1!
b0000000000110011 #
1$
b0000000000110011 &
b0011 '
1.
b0011 0
b0011 1
#1040000000
0!
0$
0.
#1050000000
1!
b0000000000110100 #
1$
b0000000000110100 &
b0100 '
1.
b0100 0
b0100 1
#1060000000
0!
0$
0.
#1070000000
1!
b0000000000110101 #
1$
b0000000000110101 &
b0101 '
1.
b0101 0
b0101 1
#1080000000
0!
0$
0.
#1090000000
1!
b0000000000110110 #
1$
b0000000000110110 &
b0110 '
1.
b0110 0
b0110 1
#1100000000
0!
0$
0.
#1110000000
1!
b0000000000110111 #
1$
b0000000000110111 &
b0111 '
1.
b0111 0
b0111 1
#1120000000
0!
0$
0.
#1130000000
1!
b0000000000111000 #
1$
b0000000000111000 &
b1000 '
1.
b1000 0
b1000 1
#1140000000
0!
0$
0.
#1150000000
1!
b0000000000111001 #
1$
b0000000000111001 &
b1001 '
1.
b1001 0
b1001 1
#1160000000
0!
0$
0.
#1170000000
1!
b0000000000111010 #
1$
b0000000000111010 &
b1010 '
1.
b1010 0
b1010 1
#1180000000
0!
0$
0.
#1190000000
1!
b0000000000111011 #
1$
b0000000000111011 &
b1011 '
1.
b1011 0
b1011 1
#1200000000
0!
0$
0.
#1210000000
1!
b0000000000111100 #
1$
b0000000000111100 &
b1100 '
1.
b1100 0
b1100 1
#1220000000
0!
0$
0.
#1230000000
1!
b0000000000111101 #
1$
b0000000000111101 &
b1101 '
1.
b1101 0
b1101 1
#1240000000
0!
0$
0.
#1250000000
1!
b0000000000111110 #
1$
b0000000000111110 &
b1110 '
1.
b1110 0
b1110 1
#1260000000
0!
0$
0.
#1270000000
1!
b0000000001001111 #
1$
b0000000001001111 &
b1111 '
b0100 (
1+
1.
b1111 0
b1111 1
12
b0100 4
b0100 5
#1280000000
0!
0$
0.
#1290000000
1!
b0000000001000000 #
1$
b0000000001000000 &
b0000 '
0+
1.
b0000 0
b0000 1
02
#1300000000
0!
0$
0.
#1310000000
1!
b0000000001000001 #
1$
b0000000001000001 &
b0001 '
1.
b0001 0
b0001 1
#1320000000
0!
0$
0.
#1330000000
1!
b0000000001000010 #
1$
b0000000001000010 &
b0010 '
1.
b0010 0
b0010 1
#1340000000
0!
0$
0.
#1350000000
1!
b0000000001000011 #
1$
b0000000001000011 &
b0011 '
1.
b0011 0
b0011 1
#1360000000
0!
0$
0.
#1370000000
1!
b0000000001000100 #
1$
b0000000001000100 &
b0100 '
1.
b0100 0
b0100 1
#1380000000
0!
0$
0.
#1390000000
1!
b0000000001000101 #
1$
b0000000001000101 &
b0101 '
1.
b0101 0
b0101 1
#1400000000
0!
0$
0.
#1410000000
1!
b0000000001000110 #
1$
b0000000001000110 &
b0110 '
1.
b0110 0
b0110 1
#1420000000
0!
0$
0.
#1430000000
1!
b0000000001000111 #
1$
b0000000001000111 &
b0111 '
1.
b0111 0
b0111 1
#1440000000
0!
0$
0.
#1450000000
1!
b0000000001001000 #
1$
b0000000001001000 &
b1000 '
1.
b1000 0
b1000 1
#1460000000
0!
0$
0.
#1470000000
1!
b0000000001001001 #
1$
b0000000001001001 &
b1001 '
1.
b1001 0
b1001 1
#1480000000
0!
0$
0.
#1490000000
1!
b0000000001001010 #
1$
b0000000001001010 &
b1010 '
1.
b1010 0
b1010 1
#1500000000
0!
0$
0.
#1510000000
1!
b0000000001001011 #
1$
b0000000001001011 &
b1011 '
1.
b1011 0
b1011 1
#1520000000
0!
0$
0.
#1530000000
1!
b0000000001001100 #
1$
b0000000001001100 &
b1100 '
1.
b1100 0
b1100 1
#1540000000
0!
0$
0.
#1550000000
1!
b0000000001001101 #
1$
b0000000001001101 &
b1101 '
1.
b1101 0
b1101 1
#1560000000
0!
0$
0.
#1570000000
1!
b0000000001001110 #
1$
b0000000001001110 &
b1110 '
1.
b1110 0
b1110 1
#1580000000
0!
0$
0.
#1590000000
1!
b0000000001011111 #
1$
b0000000001011111 &
b1111 '
b0101 (
1+
1.
b1111 0
b1111 1
12
b0101 4
b0101 5
#1600000000
0!
0$
0.
#1610000000
1!
b0000000001010000 #
1$
b0000000001010000 &
b0000 '
0+
1.
b0000 0
b0000 1
02
#1620000000
0!
0$
0.
#1630000000
1!
b0000000001010001 #
1$
b0000000001010001 &
b0001 '
1.
b0001 0
b0001 1
#1640000000
0!
0$
0.
#1650000000
1!
b0000000001010010 #
1$
b0000000001010010 &
b0010 '
1.
b0010 0
b0010 1
#1660000000
0!
0$
0.
#1670000000
1!
b0000000001010011 #
1$
b0000000001010011 &
b0011 '
1.
b0011 0
b0011 1
#1680000000
0!
0$
0.
#1690000000
1!
b0000000001010100 #
1$
b0000000001010100 &
b0100 '
1.
b0100 0
b0100 1
#1700000000
0!
0$
0.
#1710000000
1!
b0000000001010101 #
1$
b0000000001010101 &
b0101 '
1.
b0101 0
b0101 1
#1720000000
0!
0$
0.
#1730000000
1!
b0000000001010110 #
1$
b0000000001010110 &
b0110 '
1.
b0110 0
b0110 1
#1740000000
0!
0$
0.
#1750000000
1!
b0000000001010111 #
1$
b0000000001010111 &
b0111 '
1.
b0111 0
b0111 1
#1760000000
0!
0$
0.
#1770000000
1!
b0000000001011000 #
1$
b0000000001011000 &
b1000 '
1.
b1000 0
b1000 1
#1780000000
0!
0$
0.
#1790000000
1!
b0000000001011001 #
1$
b0000000001011001 &
b1001 '
1.
b1001 0
b1001 1
#1800000000
0!
0$
0.
#1810000000
1!
b0000000001011010 #
1$
b0000000001011010 &
b1010 '
1.
b1010 0
b1010 1
#1820000000
0!
0$
0.
#1830000000
1!
b0000000001011011 #
1$
b0000000001011011 &
b1011 '
1.
b1011 0
b1011 1
#1840000000
0!
0$
0.
#1850000000
1!
b0000000001011100 #
1$
b0000000001011100 &
b1100 '
1.
b1100 0
b1100 1
#1860000000
0!
0$
0.
#1870000000
1!
b0000000001011101 #
1$
b0000000001011101 &
b1101 '
1.
b1101 0
b1101 1
#1880000000
0!
0$
0.
#1890000000
1!
b0000000001011110 #
1$
b0000000001011110 &
b1110 '
1.
b1110 0
b1110 1
#1900000000
0!
0$
0.
#1910000000
1!
b0000000001101111 #
1$
b0000000001101111 &
b1111 '
b0110 (
1+
1.
b1111 0
b1111 1
12
b0110 4
b0110 5
#1920000000
0!
0$
0.
#1930000000
1!
b0000000001100000 #
1$
b0000000001100000 &
b0000 '
0+
1.
b0000 0
b0000 1
02
#1940000000
0!
0$
0.
#1950000000
1!
b0000000001100001 #
1$
b0000000001100001 &
b0001 '
1.
b0001 0
b0001 1
#1960000000
0!
0$
0.
#1970000000
1!
b0000000001100010 #
1$
b0000000001100010 &
b0010 '
1.
b0010 0
b0010 1
#1980000000
0!
0$
0.
#1990000000
1!
b0000000001100011 #
1$
b0000000001100011 &
b0011 '
1.
b0011 0
b0011 1
#2000000000
0!
0$
0.
#2010000000
1!
b0000000001100100 #
1$
b0000000001100100 &
b0100 '
1.
b0100 0
b0100 1
