prova2/exame-2022_1/q3/q3.vhd
library ieee;
use ieee.std_logic_1164.all;
use ieee.numeric_std.all;

entity q3 is
  port (
    clk   : in std_logic;
    reset : in std_logic;
    ch    : in std_logic;

    z0 : out std_logic;
    z1 : out std_logic
  );
end entity;

architecture simple of q3 is
  signal Q : std_logic_vector(2 downto 0);
begin

  process (clk, reset)
  begin
    if reset = '1' then
      Q <= (others => '0');
    elsif rising_edge(clk) then
      Q(2) <= Q(1);
      Q(1) <= Q(0);
      Q(0) <= ch;
    end if;
  end process;
  z1 <= not Q(2);
  z0 <= not Q(2) nand Q(0);
end architecture;

prova2/exame-2022_1/q3/q3_tb.vhd
library ieee;
use ieee.std_logic_1164.all;
use ieee.numeric_std.all;

entity q3_tb is
end entity;

architecture testbench of q3_tb is
  component q3 is
    port (
      clk   : in std_logic;
      reset : in std_logic;
      ch    : in std_logic;

      z0 : out std_logic;
      z1 : out std_logic
    );
  end component;

  signal clk   : std_logic := '0';
  signal reset : std_logic := '0';
  signal ch    : std_logic := '0';
  signal z0    : std_logic := '0';
  signal z1    : std_logic := '0';
begin

  clk   <= not clk after 5 ns; -- gerar clock
  reset <= '0', '1' after 10 ns, '0' after 20 ns; --gerar reset

  process_ch : q3
  port map
  (
    clk   => clk,
    reset => reset,
    ch    => ch,
    z0    => z0,
    z1    => z1
  );
  process
    variable count : time := 1 ns;
  begin
    while true loop
      ch <= not ch;
      wait for count;
      count := count + 1 ns;
    end loop;
    wait;
  end process;
end architecture;

prova2/exame-2022_1/q3/work/wave.vcd
$date
  Thu Dec 12 22:44:25 2024
$end
$version
  GHDL v0
$end
$timescale
  1 fs
$end
$scope module standard $end
$upscope $end
$scope module std_logic_1164 $end
$upscope $end
$scope module numeric_std $end
$upscope $end
$scope module q3_tb $end
$var reg 1 ! clk $end
$var reg 1 " reset $end
$var reg 1 # ch $end
$var reg 1 $ z0 $end
$var reg 1 % z1 $end
$scope module process_ch $end
$var reg 1 & clk $end
$var reg 1 ' reset $end
$var reg 1 ( ch $end
$var reg 1 ) z0 $end
$var reg 1 * z1 $end
$var reg 3 + q[2:0] $end
$upscope $end
$upscope $end
$enddefinitions $end
#0
0!
0"
1#
U$
U%
0&
0'
1(
U)
U*
bUUU +
#1000000
0#
0(
#3000000
1#
1(
#5000000
1!
1&
bUU1 +
#6000000
0#
0(
#10000000
0!
1"
1#
1$
1%
0&
1'
1(
1)
1*
b000 +
#15000000
1!
0#
1&
0(
#20000000
0!
0"
0&
0'
#21000000
1#
1(
#25000000
1!
0$
1&
0)
b001 +
#28000000
0#
0(
#30000000
0!
0&
#35000000
1!
1$
1&
1)
b010 +
#36000000
1#
1(
#40000000
0!
0&
#45000000
1!
0#
0%
1&
0(
0*
b101 +
#50000000
0!
0&
#55000000
1!
1#
1%
1&
1(
1*
b010 +
#60000000
0!
0&
#65000000
1!
0%
1&
0*
b101 +
#66000000
0#
0(
#70000000
0!
0&
#75000000
1!
1%
1&
1*
b010 +
#78000000
1#
1(
#80000000
0!
0&
#85000000
1!
0%
1&
0*
b101 +
#90000000
0!
0&
#91000000
0#
0(
#95000000
1!
1%
1&
1*
b010 +
#100000000
0!
0&
#105000000
1!
1#
0%
1&
1(
0*
b100 +
#110000000
0!
0&
#115000000
1!
0$
1%
1&
0)
1*
b001 +
#120000000
0!
0#
0&
0(
#125000000
1!
1$
1&
1)
b010 +
#130000000
0!
0&
#135000000
1!
0%
1&
0*
b100 +
#136000000
1#
1(
#140000000
0!
0&
#145000000
1!
0$
1%
1&
0)
1*
b001 +
#150000000
0!
0&
#153000000
0#
0(
#155000000
1!
1$
1&
1)
b010 +
#160000000
0!
0&
#165000000
1!
0%
1&
0*
b100 +
#170000000
0!
0&
#171000000
1#
1(
#175000000
1!
0$
1%
1&
0)
1*
b001 +
#180000000
0!
0&
#185000000
1!
1&
b011 +
#190000000
0!
0#
0&
0(
#195000000
1!
1$
0%
1&
1)
0*
b110 +
#200000000
0!
0&
#205000000
1!
1&
b100 +
#210000000
0!
1#
0&
1(
#215000000
1!
0$
1%
1&
0)
1*
b001 +
#220000000
0!
0&
#225000000
1!
1&
b011 +
#230000000
0!
0&
#231000000
0#
0(
#235000000
1!
1$
0%
1&
1)
0*
b110 +
#240000000
0!
0&
#245000000
1!
1&
b100 +
#250000000
0!
0&
#253000000
1#
1(
#255000000
1!
0$
1%
1&
0)
1*
b001 +
#260000000
0!
0&
#265000000
1!
1&
b011 +
#270000000
0!
0&
#275000000
1!
1$
0%
1&
1)
0*
b111 +
#276000000
0#
0(
#280000000
0!
0&
#285000000
1!
1&
b110 +
#290000000
0!
0&
#295000000
1!
1&
b100 +
#300000000
0!
1#
0&
1(
#305000000
1!
0$
1%
1&
0)
1*
b001 +
#310000000
0!
0&
#315000000
1!
1&
b011 +
#320000000
0!
0&
#325000000
1!
0#
1$
0%
1&
0(
1)
0*
b111 +
#330000000
0!
0&
#335000000
1!
1&
b110 +
#340000000
0!
0&
#345000000
1!
1&
b100 +
#350000000
0!
0&
#351000000
1#
1(
#355000000
1!
0$
1%
1&
0)
1*
b001 +
#360000000
0!
0&
#365000000
1!
1&
b011 +
#370000000
0!
0&
#375000000
1!
1$
0%
1&
1)
0*
b111 +
#378000000
0#
0(
#380000000
0!
0&
#385000000
1!
1&
b110 +
#390000000
0!
0&
#395000000
1!
1&
b100 +
#400000000
0!
0&
#405000000
1!
1%
1&
1*
b000 +
#406000000
1#
1(
#410000000
0!
0&
#415000000
1!
0$
1&
0)
b001 +
#420000000
0!
0&
#425000000
1!
1&
b011 +
#430000000
0!
0&
#435000000
1!
0#
1$
0%
1&
0(
1)
0*
b111 +
#440000000
0!
0&
#445000000
1!
1&
b110 +
#450000000
0!
0&
#455000000
1!
1&
b100 +
#460000000
0!
0&
#465000000
1!
1#
1%
1&
1(
1*
b000 +
#470000000
0!
0&
#475000000
1!
0$
1&
0)
b001 +
#480000000
0!
0&
#485000000
1!
1&
b011 +
#490000000
0!
0&
#495000000
1!
1$
0%
1&
1)
0*
b111 +
#496000000
0#
0(
#500000000
0!
0&
#505000000
1!
1&
b110 +
#510000000
0!
0&
#515000000
1!
1&
b100 +
#520000000
0!
0&
#525000000
1!
1%
1&
1*
b000 +
#528000000
1#
1(
#530000000
0!
0&
#535000000
1!
0$
1&
0)
b001 +
#540000000
0!
0&
#545000000
1!
1&
b011 +
#550000000
0!
0&
#555000000
1!
1$
0%
1&
1)
0*
b111 +
#560000000
0!
0&
#561000000
0#
0(
#565000000
1!
1&
b110 +
#570000000
0!
0&
#575000000
1!
1&
b100 +
#580000000
0!
0&
#585000000
1!
1%
1&
1*
b000 +
#590000000
0!
0&
#595000000
1!
1#
1&
1(
#600000000
0!
0&
#605000000
1!
0$
1&
0)
b001 +
#610000000
0!
0&
#615000000
1!
1&
b011 +
#620000000
0!
0&
#625000000
1!
1$
0%
1&
1)
0*
b111 +
#630000000
0!
0#
0&
0(
#635000000
1!
1&
b110 +
#640000000
0!
0&
#645000000
1!
1&
b100 +
#650000000
0!
0&
#655000000
1!
1%
1&
1*
b000 +
#660000000
0!
0&
#665000000
1!
1&
#666000000
1#
1(
#670000000
0!
0&
#675000000
1!
0$
1&
0)
b001 +
#680000000
0!
0&
#685000000
1!
1&
b011 +
#690000000
0!
0&
#695000000
1!
1$
0%
1&
1)
0*
b111 +
#700000000
0!
0&
#703000000
0#
0(
#705000000
1!
1&
b110 +
#710000000
0!
0&
#715000000
1!
1&
b100 +
#720000000
0!
0&
#725000000
1!
1%
1&
1*
b000 +
#730000000
0!
0&
#735000000
1!
1&
#740000000
0!
0&
#741000000
1#
1(
#745000000
1!
0$
1&
0)
b001 +
#750000000
0!
0&
#755000000
1!
1&
b011 +
#760000000
0!
0&
#765000000
1!
1$
0%
1&
1)
0*
b111 +
#770000000
0!
0&
#775000000
1!
1&
#780000000
0!
0#
0&
0(
#785000000
1!
1&
b110 +
#790000000
0!
0&
#795000000
1!
1&
b100 +
#800000000
0!
0&
#805000000
1!
1%
1&
1*
b000 +
#810000000
0!
0&
#815000000
1!
1&
#820000000
0!
1#
0&
1(
#825000000
1!
0$
1&
0)
b001 +
#830000000
0!
0&
#835000000
1!
1&
b011 +
#840000000
0!
0&
#845000000
1!
1$
0%
1&
1)
0*
b111 +
#850000000
0!
0&
#855000000
1!
1&
#860000000
0!
0&
#861000000
0#
0(
#865000000
1!
1&
b110 +
#870000000
0!
0&
#875000000
1!
1&
b100 +
#880000000
0!
0&
#885000000
1!
1%
1&
1*
b000 +
#890000000
0!
0&
#895000000
1!
1&
#900000000
0!
0&
#903000000
1#
1(
#905000000
1!
0$
1&
0)
b001 +
#910000000
0!
0&
#915000000
1!
1&
b011 +
#920000000
0!
0&
#925000000
1!
1$
0%
1&
1)
0*
b111 +
#930000000
0!
0&
#935000000
1!
1&
#940000000
0!
0&
#945000000
1!
1&
#946000000
0#
0(
#950000000
0!
0&
#955000000
1!
1&
b110 +
#960000000
0!
0&
#965000000
1!
1&
b100 +
#970000000
0!
0&
#975000000
1!
1%
1&
1*
b000 +
#980000000
0!
0&
#985000000
1!
1&
#990000000
0!
1#
0&
1(
#995000000
1!
0$
1&
0)
b001 +
#1000000000
0!
0&
#1005000000
1!
1&
b011 +
#1010000000
0!
0&
#1015000000
1!
1$
0%
1&
1)
0*
b111 +
#1020000000
0!
0&
#1025000000
1!
1&
#1030000000
0!
0&
#1035000000
1!
0#
1&
0(
#1040000000
0!
0&
#1045000000
1!
1&
b110 +
#1050000000
0!
0&
#1055000000
1!
1&
b100 +
#1060000000
0!
0&
#1065000000
1!
1%
1&
1*
b000 +
#1070000000
0!
0&
#1075000000
1!
1&
#1080000000
0!
0&
#1081000000
1#
1(
#1085000000
1!
0$
1&
0)
b001 +
#1090000000
0!
0&
#1095000000
1!
1&
b011 +
#1100000000
0!
0&
#1105000000
1!
1$
0%
1&
1)
0*
b111 +
#1110000000
0!
0&
#1115000000
1!
1&
#1120000000
0!
0&
#1125000000
1!
1&
#1128000000
0#
0(
#1130000000
0!
0&
#1135000000
1!
1&
b110 +
#1140000000
0!
0&
#1145000000
1!
1&
b100 +
#1150000000
0!
0&
#1155000000
1!
1%
1&
1*
b000 +
#1160000000
0!
0&
#1165000000
1!
1&
#1170000000
0!
0&
#1175000000
1!
1&
#1176000000
1#
1(
#1180000000
0!
0&
#1185000000
1!
0$
1&
0)
b001 +
#1190000000
0!
0&
#1195000000
1!
1&
b011 +
#1200000000
0!
0&
#1205000000
1!
1$
0%
1&
1)
0*
b111 +
#1210000000
0!
0&
#1215000000
1!
1&
#1220000000
0!
0&
#1225000000
1!
0#
1&
0(
#1230000000
0!
0&
#1235000000
1!
1&
b110 +
#1240000000
0!
0&
#1245000000
1!
1&
b100 +
#1250000000
0!
0&
#1255000000
1!
1%
1&
1*
b000 +
#1260000000
0!
0&
#1265000000
1!
1&
#1270000000
0!
0&
#1275000000
1!
1#
1&
1(
#1280000000
0!
0&
#1285000000
1!
0$
1&
0)
b001 +
#1290000000
0!
0&
#1295000000
1!
1&
b011 +
#1300000000
0!
0&
#1305000000
1!
1$
0%
1&
1)
0*
b111 +
#1310000000
0!
0&
#1315000000
1!
1&
#1320000000
0!
0&
#1325000000
1!
1&
#1326000000
0#
0(
#1330000000
0!
0&
#1335000000
1!
1&
b110 +
#1340000000
0!
0&
#1345000000
1!
1&
b100 +
#1350000000
0!
0&
#1355000000
1!
1%
1&
1*
b000 +
#1360000000
0!
0&
#1365000000
1!
1&
#1370000000
0!
0&
#1375000000
1!
1&
#1378000000
1#
1(
#1380000000
0!
0&
#1385000000
1!
0$
1&
0)
b001 +
#1390000000
0!
0&
#1395000000
1!
1&
b011 +
#1400000000
0!
0&
#1405000000
1!
1$
0%
1&
1)
0*
b111 +
#1410000000
0!
0&
#1415000000
1!
1&
#1420000000
0!
0&
#1425000000
1!
1&
#1430000000
0!
0&
#1431000000
0#
0(
#1435000000
1!
1&
b110 +
#1440000000
0!
0&
#1445000000
1!
1&
b100 +
#1450000000
0!
0&
#1455000000
1!
1%
1&
1*
b000 +
#1460000000
0!
0&
#1465000000
1!
1&
#1470000000
0!
0&
#1475000000
1!
1&
#1480000000
0!
0&
#1485000000
1!
1#
1&
1(
#1490000000
0!
0&
#1495000000
1!
0$
1&
0)
b001 +
#1500000000
0!
0&
#1505000000
1!
1&
b011 +
#1510000000
0!
0&
#1515000000
1!
1$
0%
1&
1)
0*
b111 +
#1520000000
0!
0&
#1525000000
1!
1&
#1530000000
0!
0&
#1535000000
1!
1&
#1540000000
0!
0#
0&
0(
#1545000000
1!
1&
b110 +
#1550000000
0!
0&
#1555000000
1!
1&
b100 +
#1560000000
0!
0&
#1565000000
1!
1%
1&
1*
b000 +
#1570000000
0!
0&
#1575000000
1!
1&
#1580000000
0!
0&
#1585000000
1!
1&
#1590000000
0!
0&
#1595000000
1!
1&
#1596000000
1#
1(
#1600000000
0!
0&
#1605000000
1!
0$
1&
0)
b001 +
#1610000000
0!
0&
#1615000000
1!
1&
b011 +
#1620000000
0!
0&
#1625000000
1!
1$
0%
1&
1)
0*
b111 +
#1630000000
0!
0&
#1635000000
1!
1&
#1640000000
0!
0&
#1645000000
1!
1&
#1650000000
0!
0&
#1653000000
0#
0(
#1655000000
1!
1&
b110 +
#1660000000
0!
0&
#1665000000
1!
1&
b100 +
#1670000000
0!
0&
#1675000000
1!
1%
1&
1*
b000 +
#1680000000
0!
0&
#1685000000
1!
1&
#1690000000
0!
0&
#1695000000
1!
1&
#1700000000
0!
0&
#1705000000
1!
1&
#1710000000
0!
0&
#1711000000
1#
1(
#1715000000
1!
0$
1&
0)
b001 +
#1720000000
0!
0&
#1725000000
1!
1&
b011 +
#1730000000
0!
0&
#1735000000
1!
1$
0%
1&
1)
0*
b111 +
#1740000000
0!
0&
#1745000000
1!
1&
#1750000000
0!
0&
#1755000000
1!
1&
#1760000000
0!
0&
#1765000000
1!
1&
#1770000000
0!
0#
0&
0(
#1775000000
1!
1&
b110 +
#1780000000
0!
0&
#1785000000
1!
1&
b100 +
#1790000000
0!
0&
#1795000000
1!
1%
1&
1*
b000 +
#1800000000
0!
0&
#1805000000
1!
1&
#1810000000
0!
0&
#1815000000
1!
1&
#1820000000
0!
0&
#1825000000
1!
1&
#1830000000
0!
1#
0&
1(
#1835000000
1!
0$
1&
0)
b001 +
#1840000000
0!
0&
#1845000000
1!
1&
b011 +
#1850000000
0!
0&
#1855000000
1!
1$
0%
1&
1)
0*
b111 +
#1860000000
0!
0&
#1865000000
1!
1&
#1870000000
0!
0&
#1875000000
1!
1&
#1880000000
0!
0&
#1885000000
1!
1&
#1890000000
0!
0&
#1891000000
0#
0(
#1895000000
1!
1&
b110 +
#1900000000
0!
0&
#1905000000
1!
1&
b100 +
#1910000000
0!
0&
#1915000000
1!
1%
1&
1*
b000 +
#1920000000
0!
0&
#1925000000
1!
1&
#1930000000
0!
0&
#1935000000
1!
1&
#1940000000
0!
0&
#1945000000
1!
1&
#1950000000
0!
0&
#1953000000
1#
1(
#1955000000
1!
0$
1&
0)
b001 +
#1960000000
0!
0&
#1965000000
1!
1&
b011 +
#1970000000
0!
0&
#1975000000
1!
1$
0%
1&
1)
0*
b111 +
#1980000000
0!
0&
#1985000000
1!
1&
#1990000000
0!
0&
#1995000000
1!
1&
#2000000000
0!
0&
#2005000000
1!
1&
#2010000000
0!
0&
#2015000000
1!
1&
#2016000000
0#
0(
#2020000000
0!
0&
#2025000000
1!
1&
b110 +
#2030000000
0!
0&
#2035000000
1!
1&
b100 +
#2040000000
0!
0&
#2045000000
1!
1%
1&
1*
b000 +
#2050000000
0!
0&
#2055000000
1!
1&
#2060000000
0!
0&
#2065000000
1!
1&
#2070000000
0!
0&
#2075000000
1!
1&
#2080000000
0!
1#
0&
1(
#2085000000
1!
0$
1&
0)
b001 +
#2090000000
0!
0&
#2095000000
1!
1&
b011 +
#2100000000
0!
0&
#2105000000
1!
1$
0%
1&
1)
0*
b111 +
#2110000000
0!
0&
#2115000000
1!
1&
#2120000000
0!
0&
#2125000000
1!
1&
#2130000000
0!
0&
#2135000000
1!
1&
#2140000000
0!
0&
#2145000000
1!
0#
1&
0(
#2150000000
0!
0&
#2155000000
1!
1&
b110 +
#2160000000
0!
0&
#2165000000
1!
1&
b100 +
#2170000000
0!
0&
#2175000000
1!
1%
1&
1*
b000 +
#2180000000
0!
0&
#2185000000
1!
1&
#2190000000
0!
0&
#2195000000
1!
1&
#2200000000
0!
0&
#2205000000
1!
1&
#2210000000
0!
0&
#2211000000
1#
1(
#2215000000
1!
0$
1&
0)
b001 +
#2220000000
0!
0&
#2225000000
1!
1&
b011 +
#2230000000
0!
0&
#2235000000
1!
1$
0%
1&
1)
0*
b111 +
#2240000000
0!
0&
#2245000000
1!
1&
#2250000000
0!
0&
#2255000000
1!
1&
#2260000000
0!
0&
#2265000000
1!
1&
#2270000000
0!
0&
#2275000000
1!
1&
#2278000000
0#
0(
#2280000000
0!
0&
#2285000000
1!
1&
b110 +
#2290000000
0!
0&
#2295000000
1!
1&
b100 +
#2300000000
0!
0&
#2305000000
1!
1%
1&
1*
b000 +
#2310000000
0!
0&
#2315000000
1!
1&
#2320000000
0!
0&
#2325000000
1!
1&
#2330000000
0!
0&
#2335000000
1!
1&
#2340000000
0!
0&
#2345000000
1!
1&
#2346000000
1#
1(
#2350000000
0!
0&
#2355000000
1!
0$
1&
0)
b001 +
#2360000000
0!
0&
#2365000000
1!
1&
b011 +
#2370000000
0!
0&
#2375000000
1!
1$
0%
1&
1)
0*
b111 +
#2380000000
0!
0&
#2385000000
1!
1&
#2390000000
0!
0&
#2395000000
1!
1&
#2400000000
0!
0&
#2405000000
1!
1&
#2410000000
0!
0&
#2415000000
1!
0#
1&
0(
#2420000000
0!
0&
#2425000000
1!
1&
b110 +
#2430000000
0!
0&
#2435000000
1!
1&
b100 +
#2440000000
0!
0&
#2445000000
1!
1%
1&
1*
b000 +
#2450000000
0!
0&
#2455000000
1!
1&
#2460000000
0!
0&
#2465000000
1!
1&
#2470000000
0!
0&
#2475000000
1!
1&
#2480000000
0!
0&
#2485000000
1!
1#
1&
1(
#2490000000
0!
0&
#2495000000
1!
0$
1&
0)
b001 +
#2500000000
0!
0&
#2505000000
1!
1&
b011 +
#2510000000
0!
0&
#2515000000
1!
1$
0%
1&
1)
0*
b111 +
#2520000000
0!
0&
#2525000000
1!
1&
#2530000000
0!
0&
#2535000000
1!
1&
#2540000000
0!
0&
#2545000000
1!
1&
#2550000000
0!
0&
#2555000000
1!
1&
#2556000000
0#
0(
#2560000000
0!
0&
#2565000000
1!
1&
b110 +
#2570000000
0!
0&
#2575000000
1!
1&
b100 +
#2580000000
0!
0&
#2585000000
1!
1%
1&
1*
b000 +
#2590000000
0!
0&
#2595000000
1!
1&
#2600000000
0!
0&
#2605000000
1!
1&
#2610000000
0!
0&
#2615000000
1!
1&
#2620000000
0!
0&
#2625000000
1!
1&
#2628000000
1#
1(
#2630000000
0!
0&
#2635000000
1!
0$
1&
0)
b001 +
#2640000000
0!
0&
#2645000000
1!
1&
b011 +
#2650000000
0!
0&
#2655000000
1!
1$
0%
1&
1)
0*
b111 +
#2660000000
0!
0&
#2665000000
1!
1&
#2670000000
0!
0&
#2675000000
1!
1&
#2680000000
0!
0&
#2685000000
1!
1&
#2690000000
0!
0&
#2695000000
1!
1&
#2700000000
0!
0&
#2701000000
0#
0(
#2705000000
1!
1&
b110 +
#2710000000
0!
0&
#2715000000
1!
1&
b100 +
#2720000000
0!
0&
#2725000000
1!
1%
1&
1*
b000 +
#2730000000
0!
0&
#2735000000
1!
1&
#2740000000
0!
0&
#2745000000
1!
1&
#2750000000
0!
0&
#2755000000
1!
1&
#2760000000
0!
0&
#2765000000
1!
1&
#2770000000
0!
0&
#2775000000
1!
1#
1&
1(
#2780000000
0!
0&
#2785000000
1!
0$
1&
0)
b001 +
#2790000000
0!
0&
#2795000000
1!
1&
b011 +
#2800000000
0!
0&
#2805000000
1!
1$
0%
1&
1)
0*
b111 +
#2810000000
0!
0&
#2815000000
1!
1&
#2820000000
0!
0&
#2825000000
1!
1&
#2830000000
0!
0&
#2835000000
1!
1&
#2840000000
0!
0&
#2845000000
1!
1&
#2850000000
0!
0#
0&
0(
#2855000000
1!
1&
b110 +
#2860000000
0!
0&
#2865000000
1!
1&
b100 +
#2870000000
0!
0&
#2875000000
1!
1%
1&
1*
b000 +
#2880000000
0!
0&
#2885000000
1!
1&
#2890000000
0!
0&
#2895000000
1!
1&
#2900000000
0!
0&
#2905000000
1!
1&
#2910000000
0!
0&
#2915000000
1!
1&
#2920000000
0!
0&
#2925000000
1!
1&
#2926000000
1#
1(
#2930000000
0!
0&
#2935000000
1!
0$
1&
0)
b001 +
#2940000000
0!
0&
#2945000000
1!
1&
b011 +
#2950000000
0!
0&
#2955000000
1!
1$
0%
1&
1)
0*
b111 +
#2960000000
0!
0&
#2965000000
1!
1&
#2970000000
0!
0&
#2975000000
1!
1&
#2980000000
0!
0&
#2985000000
1!
1&
#2990000000
0!
0&
#2995000000
1!
1&
#3000000000
0!
0&
#3003000000
0#
0(
#3005000000
1!
1&
b110 +
#3010000000
0!
0&
#3015000000
1!
1&
b100 +
#3020000000
0!
0&
#3025000000
1!
1%
1&
1*
b000 +
#3030000000
0!
0&
#3035000000
1!
1&
#3040000000
0!
0&
#3045000000
1!
1&
#3050000000
0!
0&
#3055000000
1!
1&
#3060000000
0!
0&
#3065000000
1!
1&
#3070000000
0!
0&
#3075000000
1!
1&
#3080000000
0!
0&
#3081000000
1#
1(
#3085000000
1!
0$
1&
0)
b001 +
#3090000000
0!
0&
#3095000000
1!
1&
b011 +
#3100000000
0!
0&
#3105000000
1!
1$
0%
1&
1)
0*
b111 +
#3110000000
0!
0&
#3115000000
1!
1&
#3120000000
0!
0&
#3125000000
1!
1&
#3130000000
0!
0&
#3135000000
1!
1&
#3140000000
0!
0&
#3145000000
1!
1&
#3150000000
0!
0&
#3155000000
1!
1&
#3160000000
0!
0#
0&
0(
#3165000000
1!
1&
b110 +
#3170000000
0!
0&
#3175000000
1!
1&
b100 +
#3180000000
0!
0&
#3185000000
1!
1%
1&
1*
b000 +
#3190000000
0!
0&
#3195000000
1!
1&
#3200000000
0!
0&
#3205000000
1!
1&
#3210000000
0!
0&
#3215000000
1!
1&
#3220000000
0!
0&
#3225000000
1!
1&
#3230000000
0!
0&
#3235000000
1!
1&
#3240000000
0!
1#
0&
1(
#3245000000
1!
0$
1&
0)
b001 +
#3250000000
0!
0&
#3255000000
1!
1&
b011 +
#3260000000
0!
0&
#3265000000
1!
1$
0%
1&
1)
0*
b111 +
#3270000000
0!
0&
#3275000000
1!
1&
#3280000000
0!
0&
#3285000000
1!
1&
#3290000000
0!
0&
#3295000000
1!
1&
#3300000000
0!
0&
#3305000000
1!
1&
#3310000000
0!
0&
#3315000000
1!
1&
#3320000000
0!
0&
#3321000000
0#
0(
#3325000000
1!
1&
b110 +
#3330000000
0!
0&
#3335000000
1!
1&
b100 +
#3340000000
0!
0&
#3345000000
1!
1%
1&
1*
b000 +
#3350000000
0!
0&
#3355000000
1!
1&
#3360000000
0!
0&
#3365000000
1!
1&
#3370000000
0!
0&
#3375000000
1!
1&
#3380000000
0!
0&
#3385000000
1!
1&
#3390000000
0!
0&
#3395000000
1!
1&
#3400000000
0!
0&
#3403000000
1#
1(
#3405000000
1!
0$
1&
0)
b001 +
#3410000000
0!
0&
#3415000000
1!
1&
b011 +
#3420000000
0!
0&
#3425000000
1!
1$
0%
1&
1)
0*
b111 +
#3430000000
0!
0&
#3435000000
1!
1&
#3440000000
0!
0&
#3445000000
1!
1&
#3450000000
0!
0&
#3455000000
1!
1&
#3460000000
0!
0&
#3465000000
1!
1&
#3470000000
0!
0&
#3475000000
1!
1&
#3480000000
0!
0&
#3485000000
1!
1&
#3486000000
0#
0(
#3490000000
0!
0&
#3495000000
1!
1&
b110 +
#3500000000
0!
0&
#3505000000
1!
1&
b100 +
#3510000000
0!
0&
#3515000000
1!
1%
1&
1*
b000 +
#3520000000
0!
0&
#3525000000
1!
1&
#3530000000
0!
0&
#3535000000
1!
1&
#3540000000
0!
0&
#3545000000
1!
1&
#3550000000
0!
0&
#3555000000
1!
1&
#3560000000
0!
0&
#3565000000
1!
1&
#3570000000
0!
1#
0&
1(
#3575000000
1!
0$
1&
0)
b001 +
#3580000000
0!
0&
#3585000000
1!
1&
b011 +
#3590000000
0!
0&
#3595000000
1!
1$
0%
1&
1)
0*
b111 +
#3600000000
0!
0&
#3605000000
1!
1&
#3610000000
0!
0&
#3615000000
1!
1&
#3620000000
0!
0&
#3625000000
1!
1&
#3630000000
0!
0&
#3635000000
1!
1&
#3640000000
0!
0&
#3645000000
1!
1&
#3650000000
0!
0&
#3655000000
1!
0#
1&
0(
#3660000000
0!
0&
#3665000000
1!
1&
b110 +
#3670000000
0!
0&
#3675000000
1!
1&
b100 +
#3680000000
0!
0&
#3685000000
1!
1%
1&
1*
b000 +
#3690000000
0!
0&
#3695000000
1!
1&
#3700000000
0!
0&
#3705000000
1!
1&
#3710000000
0!
0&
#3715000000
1!
1&
#3720000000
0!
0&
#3725000000
1!
1&
#3730000000
0!
0&
#3735000000
1!
1&
#3740000000
0!
0&
#3741000000
1#
1(
#3745000000
1!
0$
1&
0)
b001 +
#3750000000
0!
0&
#3755000000
1!
1&
b011 +
#3760000000
0!
0&
#3765000000
1!
1$
0%
1&
1)
0*
b111 +
#3770000000
0!
0&
#3775000000
1!
1&
#3780000000
0!
0&
#3785000000
1!
1&
#3790000000
0!
0&
#3795000000
1!
1&
#3800000000
0!
0&
#3805000000
1!
1&
#3810000000
0!
0&
#3815000000
1!
1&
#3820000000
0!
0&
#3825000000
1!
1&
#3828000000
0#
0(
#3830000000
0!
0&
#3835000000
1!
1&
b110 +
#3840000000
0!
0&
#3845000000
1!
1&
b100 +
#3850000000
0!
0&
#3855000000
1!
1%
1&
1*
b000 +
#3860000000
0!
0&
#3865000000
1!
1&
#3870000000
0!
0&
#3875000000
1!
1&
#3880000000
0!
0&
#3885000000
1!
1&
#3890000000
0!
0&
#3895000000
1!
1&
#3900000000
0!
0&
#3905000000
1!
1&
#3910000000
0!
0&
#3915000000
1!
1&
#3916000000
1#
1(
#3920000000
0!
0&
#3925000000
1!
0$
1&
0)
b001 +
#3930000000
0!
0&
#3935000000
1!
1&
b011 +
#3940000000
0!
0&
#3945000000
1!
1$
0%
1&
1)
0*
b111 +
#3950000000
0!
0&
#3955000000
1!
1&
#3960000000
0!
0&
#3965000000
1!
1&
#3970000000
0!
0&
#3975000000
1!
1&
#3980000000
0!
0&
#3985000000
1!
1&
#3990000000
0!
0&
#3995000000
1!
1&
#4000000000
0!
0&
#4005000000
1!
0#
1&
0(
#4010000000
0!
0&
#4015000000
1!
1&
b110 +
#4020000000
0!
0&
#4025000000
1!
1&
b100 +
#4030000000
0!
0&
#4035000000
1!
1%
1&
1*
b000 +
#4040000000
0!
0&
#4045000000
1!
1&
#4050000000
0!
0&
#4055000000
1!
1&
#4060000000
0!
0&
#4065000000
1!
1&
#4070000000
0!
0&
#4075000000
1!
1&
#4080000000
0!
0&
#4085000000
1!
1&
#4090000000
0!
0&
#4095000000
1!
1#
1&
1(
#4100000000
0!
0&
#4105000000
1!
0$
1&
0)
b001 +
#4110000000
0!
0&
#4115000000
1!
1&
b011 +
#4120000000
0!
0&
#4125000000
1!
1$
0%
1&
1)
0*
b111 +
#4130000000
0!
0&
#4135000000
1!
1&
#4140000000
0!
0&
#4145000000
1!
1&
#4150000000
0!
0&
#4155000000
1!
1&
#4160000000
0!
0&
#4165000000
1!
1&
#4170000000
0!
0&
#4175000000
1!
1&
#4180000000
0!
0&
#4185000000
1!
1&
#4186000000
0#
0(
#4190000000
0!
0&
#4195000000
1!
1&
b110 +
#4200000000
0!
0&
#4205000000
1!
1&
b100 +
#4210000000
0!
0&
#4215000000
1!
1%
1&
1*
b000 +
#4220000000
0!
0&
#4225000000
1!
1&
#4230000000
0!
0&
#4235000000
1!
1&
#4240000000
0!
0&
#4245000000
1!
1&
#4250000000
0!
0&
#4255000000
1!
1&
#4260000000
0!
0&
#4265000000
1!
1&
#4270000000
0!
0&
#4275000000
1!
1&
#4278000000
1#
1(
#4280000000
0!
0&
#4285000000
1!
0$
1&
0)
b001 +
#4290000000
0!
0&
#4295000000
1!
1&
b011 +
#4300000000
0!
0&
#4305000000
1!
1$
0%
1&
1)
0*
b111 +
#4310000000
0!
0&
#4315000000
1!
1&
#4320000000
0!
0&
#4325000000
1!
1&
#4330000000
0!
0&
#4335000000
1!
1&
#4340000000
0!
0&
#4345000000
1!
1&
#4350000000
0!
0&
#4355000000
1!
1&
#4360000000
0!
0&
#4365000000
1!
1&
#4370000000
0!
0&
#4371000000
0#
0(
#4375000000
1!
1&
b110 +
#4380000000
0!
0&
#4385000000
1!
1&
b100 +
#4390000000
0!
0&
#4395000000
1!
1%
1&
1*
b000 +
#4400000000
0!
0&
#4405000000
1!
1&
#4410000000
0!
0&
#4415000000
1!
1&
#4420000000
0!
0&
#4425000000
1!
1&
#4430000000
0!
0&
#4435000000
1!
1&
#4440000000
0!
0&
#4445000000
1!
1&
#4450000000
0!
0&
#4455000000
1!
1&
#4460000000
0!
0&
#4465000000
1!
1#
1&
1(
#4470000000
0!
0&
#4475000000
1!
0$
1&
0)
b001 +
#4480000000
0!
0&
#4485000000
1!
1&
b011 +
#4490000000
0!
0&
#4495000000
1!
1$
0%
1&
1)
0*
b111 +
#4500000000
0!
0&
#4505000000
1!
1&
#4510000000
0!
0&
#4515000000
1!
1&
#4520000000
0!
0&
#4525000000
1!
1&
#4530000000
0!
0&
#4535000000
1!
1&
#4540000000
0!
0&
#4545000000
1!
1&
