prova2/2024-1/q1/q1.vhd
library ieee;
use ieee.std_logic_1164.all;
use ieee.numeric_std.all;

entity q1 is
  port (
    clk    : in std_logic; -- clock 
    rst    : in std_logic; -- reset
    hold_n : in std_logic; -- para o incremento se for '1'

    QD : out std_logic_vector (3 downto 0); -- dezenas
    QU : out std_logic_vector (3 downto 0); -- unidades
    S  : out std_logic -- saída '1' quando Q igual a 12 ou 56
  );
end entity;

architecture simlpe of q1 is
  signal qu_s : unsigned(3 downto 0) := (others => '0');
  signal qd_s : unsigned(3 downto 0) := (others => '0');
begin
  process (clk)
  begin
    if rising_edge(clk) then
      if rst = '1' then
        qu_s <= (others => '0');
        qd_s <= (others => '0');
      elsif hold_n = '0' then
        if qd_s = 7 and qu_s = 3 then
          null;
        elsif qu_s = 9 then
          qu_s <= (others => '0');
          if qd_s = 7 then
            qd_s <= (others => '0');
          else
            qd_s <= qd_s + 1;
          end if;
        else
          qu_s <= qu_s + 1;
        end if;
      end if;
    end if;
  end process;

  process (qd_s, qu_s)
  begin
    if (to_integer(qd_s) = 1 and to_integer(qu_s) = 2) or
      (to_integer(qd_s) = 5 and to_integer(qu_s) = 6) then
      S <= '1';
    else
      S <= '0';
    end if;
  end process;
  QU <= std_logic_vector(qu_s);
  QD <= std_logic_vector(qd_s);
end architecture;

prova2/2024-1/q1/q1_tb.vhd
library ieee;
use ieee.std_logic_1164.all;
use ieee.numeric_std.all;

entity q1_tb is
end entity;

architecture simlpe of q1_tb is
  component q1 is
    port (
      clk    : in std_logic;
      rst    : in std_logic;
      hold_n : in std_logic;
      QD     : out std_logic_vector(3 downto 0);
      QU     : out std_logic_vector(3 downto 0);
      S      : out std_logic
    );
  end component;

  constant CLK_PERIOD : time := 10 ns;
  constant RST_PERIOD : time := 800 ns;

  signal clk    : std_logic                    := '0';
  signal reset  : std_logic                    := '0';
  signal hold_n : std_logic                    := '0';
  signal QD     : std_logic_vector(3 downto 0) := (others => '0');
  signal QU     : std_logic_vector(3 downto 0) := (others => '0');
  signal S      : std_logic                    := '0';

begin
  DUT : q1
  port map
  (
    clk    => clk,
    rst    => reset,
    hold_n => hold_n,
    QD     => QD,
    QU     => QU,
    S      => S
  );

  clk   <= not clk after CLK_PERIOD/2;
  reset <= '0', '1' after 30 ns, '0' after 107 ns;
end architecture;

prova2/2024-1/q1/work/wave.vcd
$date
  Thu Dec 12 16:44:35 2024
$end
$version
  GHDL v0
$end
$timescale
  1 fs
$end
$scope module standard $end
$upscope $end
$scope module std_logic_1164 $end
$upscope $end
$scope module numeric_std $end
$upscope $end
$scope module q1_tb $end
$var reg 1 ! clk $end
$var reg 1 " reset $end
$var reg 1 # hold_n $end
$var reg 4 $ qd[3:0] $end
$var reg 4 % qu[3:0] $end
$var reg 1 & s $end
$scope module dut $end
$var reg 1 ' clk $end
$var reg 1 ( rst $end
$var reg 1 ) hold_n $end
$var reg 4 * qd[3:0] $end
$var reg 4 + qu[3:0] $end
$var reg 1 , s $end
$var reg 4 - qu_s[3:0] $end
$var reg 4 . qd_s[3:0] $end
$upscope $end
$upscope $end
$enddefinitions $end
#0
0!
0"
0#
b0000 $
b0000 %
0&
0'
0(
0)
b0000 *
b0000 +
0,
b0000 -
b0000 .
#5000000
1!
b0001 %
1'
b0001 +
b0001 -
#10000000
0!
0'
#15000000
1!
b0010 %
1'
b0010 +
b0010 -
#20000000
0!
0'
#25000000
1!
b0011 %
1'
b0011 +
b0011 -
#30000000
0!
1"
0'
1(
#35000000
1!
b0000 %
1'
b0000 +
b0000 -
#40000000
0!
0'
#45000000
1!
1'
#50000000
0!
0'
#55000000
1!
1'
#60000000
0!
0'
#65000000
1!
1'
#70000000
0!
0'
#75000000
1!
1'
#80000000
0!
0'
#85000000
1!
1'
#90000000
0!
0'
#95000000
1!
1'
#100000000
0!
0'
#105000000
1!
1'
#107000000
0"
0(
#110000000
0!
0'
#115000000
1!
b0001 %
1'
b0001 +
b0001 -
#120000000
0!
0'
#125000000
1!
b0010 %
1'
b0010 +
b0010 -
#130000000
0!
0'
#135000000
1!
b0011 %
1'
b0011 +
b0011 -
#140000000
0!
0'
#145000000
1!
b0100 %
1'
b0100 +
b0100 -
#150000000
0!
0'
#155000000
1!
b0101 %
1'
b0101 +
b0101 -
#160000000
0!
0'
#165000000
1!
b0110 %
1'
b0110 +
b0110 -
#170000000
0!
0'
#175000000
1!
b0111 %
1'
b0111 +
b0111 -
#180000000
0!
0'
#185000000
1!
b1000 %
1'
b1000 +
b1000 -
#190000000
0!
0'
#195000000
1!
b1001 %
1'
b1001 +
b1001 -
#200000000
0!
0'
#205000000
1!
b0001 $
b0000 %
1'
b0001 *
b0000 +
b0000 -
b0001 .
#210000000
0!
0'
#215000000
1!
b0001 %
1'
b0001 +
b0001 -
#220000000
0!
0'
#225000000
1!
b0010 %
1&
1'
b0010 +
1,
b0010 -
#230000000
0!
0'
#235000000
1!
b0011 %
0&
1'
b0011 +
0,
b0011 -
#240000000
0!
0'
#245000000
1!
b0100 %
1'
b0100 +
b0100 -
#250000000
0!
0'
#255000000
1!
b0101 %
1'
b0101 +
b0101 -
#260000000
0!
0'
#265000000
1!
b0110 %
1'
b0110 +
b0110 -
#270000000
0!
0'
#275000000
1!
b0111 %
1'
b0111 +
b0111 -
#280000000
0!
0'
#285000000
1!
b1000 %
1'
b1000 +
b1000 -
#290000000
0!
0'
#295000000
1!
b1001 %
1'
b1001 +
b1001 -
#300000000
0!
0'
#305000000
1!
b0010 $
b0000 %
1'
b0010 *
b0000 +
b0000 -
b0010 .
#310000000
0!
0'
#315000000
1!
b0001 %
1'
b0001 +
b0001 -
#320000000
0!
0'
#325000000
1!
b0010 %
1'
b0010 +
b0010 -
#330000000
0!
0'
#335000000
1!
b0011 %
1'
b0011 +
b0011 -
#340000000
0!
0'
#345000000
1!
b0100 %
1'
b0100 +
b0100 -
#350000000
0!
0'
#355000000
1!
b0101 %
1'
b0101 +
b0101 -
#360000000
0!
0'
#365000000
1!
b0110 %
1'
b0110 +
b0110 -
#370000000
0!
0'
#375000000
1!
b0111 %
1'
b0111 +
b0111 -
#380000000
0!
0'
#385000000
1!
b1000 %
1'
b1000 +
b1000 -
#390000000
0!
0'
#395000000
1!
b1001 %
1'
b1001 +
b1001 -
#400000000
0!
0'
#405000000
1!
b0011 $
b0000 %
1'
b0011 *
b0000 +
b0000 -
b0011 .
#410000000
0!
0'
#415000000
1!
b0001 %
1'
b0001 +
b0001 -
#420000000
0!
0'
#425000000
1!
b0010 %
1'
b0010 +
b0010 -
#430000000
0!
0'
#435000000
1!
b0011 %
1'
b0011 +
b0011 -
#440000000
0!
0'
#445000000
1!
b0100 %
1'
b0100 +
b0100 -
#450000000
0!
0'
#455000000
1!
b0101 %
1'
b0101 +
b0101 -
#460000000
0!
0'
#465000000
1!
b0110 %
1'
b0110 +
b0110 -
#470000000
0!
0'
#475000000
1!
b0111 %
1'
b0111 +
b0111 -
#480000000
0!
0'
#485000000
1!
b1000 %
1'
b1000 +
b1000 -
#490000000
0!
0'
#495000000
1!
b1001 %
1'
b1001 +
b1001 -
#500000000
0!
0'
#505000000
1!
b0100 $
b0000 %
1'
b0100 *
b0000 +
b0000 -
b0100 .
#510000000
0!
0'
#515000000
1!
b0001 %
1'
b0001 +
b0001 -
#520000000
0!
0'
#525000000
1!
b0010 %
1'
b0010 +
b0010 -
#530000000
0!
0'
#535000000
1!
b0011 %
1'
b0011 +
b0011 -
#540000000
0!
0'
#545000000
1!
b0100 %
1'
b0100 +
b0100 -
#550000000
0!
0'
#555000000
1!
b0101 %
1'
b0101 +
b0101 -
#560000000
0!
0'
#565000000
1!
b0110 %
1'
b0110 +
b0110 -
#570000000
0!
0'
#575000000
1!
b0111 %
1'
b0111 +
b0111 -
#580000000
0!
0'
#585000000
1!
b1000 %
1'
b1000 +
b1000 -
#590000000
0!
0'
#595000000
1!
b1001 %
1'
b1001 +
b1001 -
#600000000
0!
0'
#605000000
1!
b0101 $
b0000 %
1'
b0101 *
b0000 +
b0000 -
b0101 .
#610000000
0!
0'
#615000000
1!
b0001 %
1'
b0001 +
b0001 -
#620000000
0!
0'
#625000000
1!
b0010 %
1'
b0010 +
b0010 -
#630000000
0!
0'
#635000000
1!
b0011 %
1'
b0011 +
b0011 -
#640000000
0!
0'
#645000000
1!
b0100 %
1'
b0100 +
b0100 -
#650000000
0!
0'
#655000000
1!
b0101 %
1'
b0101 +
b0101 -
#660000000
0!
0'
#665000000
1!
b0110 %
1&
1'
b0110 +
1,
b0110 -
#670000000
0!
0'
#675000000
1!
b0111 %
0&
1'
b0111 +
0,
b0111 -
#680000000
0!
0'
#685000000
1!
b1000 %
1'
b1000 +
b1000 -
#690000000
0!
0'
#695000000
1!
b1001 %
1'
b1001 +
b1001 -
#700000000
0!
0'
#705000000
1!
b0110 $
b0000 %
1'
b0110 *
b0000 +
b0000 -
b0110 .
#710000000
0!
0'
#715000000
1!
b0001 %
1'
b0001 +
b0001 -
#720000000
0!
0'
#725000000
1!
b0010 %
1'
b0010 +
b0010 -
#730000000
0!
0'
#735000000
1!
b0011 %
1'
b0011 +
b0011 -
#740000000
0!
0'
#745000000
1!
b0100 %
1'
b0100 +
b0100 -
#750000000
0!
0'
#755000000
1!
b0101 %
1'
b0101 +
b0101 -
#760000000
0!
0'
#765000000
1!
b0110 %
1'
b0110 +
b0110 -
#770000000
0!
0'
#775000000
1!
b0111 %
1'
b0111 +
b0111 -
#780000000
0!
0'
#785000000
1!
b1000 %
1'
b1000 +
b1000 -
#790000000
0!
0'
#795000000
1!
b1001 %
1'
b1001 +
b1001 -
#800000000
0!
0'
#805000000
1!
b0111 $
b0000 %
1'
b0111 *
b0000 +
b0000 -
b0111 .
#810000000
0!
0'
#815000000
1!
b0001 %
1'
b0001 +
b0001 -
#820000000
0!
0'
#825000000
1!
b0010 %
1'
b0010 +
b0010 -
#830000000
0!
0'
#835000000
1!
b0011 %
1'
b0011 +
b0011 -
