prova2/2023-2/q2/contador.vhd
library ieee;
use ieee.std_logic_1164.all;
use ieee.numeric_std.all;

entity contador is
  port (
    clk   : in std_logic;
    reset : in std_logic;
    x     : out std_logic_vector (2 downto 0);
    S     : out std_logic
  );
end entity;

architecture simple of contador is
  signal Q  : std_logic_vector (2 downto 0) := "111";
  signal x3 : std_logic                     := '0';

begin
  x3 <= (Q(0) xor Q(1)) xor (Q(2) nor Q(1));
  x  <= Q;
  S  <= '1' when Q = "000" else
    '0';

  process (clk, reset)
  begin
    if rising_edge(clk) then
      if reset = '1' then
        Q <= "000";
      else
        Q(0) <= x3;
        Q(1) <= Q(0);
        Q(2) <= Q(1);
      end if;
    end if;
  end process;
end architecture;

prova2/2023-2/q2/contador_tb.vhd
library ieee;
use ieee.std_logic_1164.all;
use ieee.numeric_std.all;

entity contador_tb is
end entity;

architecture simple of contador_tb is
  component contador is
    port (
      clk   : in std_logic;
      reset : in std_logic;
      x     : out std_logic_vector (2 downto 0);
      S     : out std_logic
    );
  end component;

  signal clk   : std_logic                     := '0';
  signal reset : std_logic                     := '0';
  signal x     : std_logic_vector (2 downto 0) := "000";
  signal S     : std_logic                     := '0';

begin

  reset <= '0', '1' after 30 ns, '0' after 50 ns;

  uut : contador
  port map
  (
    clk   => clk,
    reset => reset,
    x     => x,
    S     => S
  );
  process
  begin
    while true loop
      clk <= '1';
      wait for 10 ns;
      clk <= '0';
      wait for 10 ns;
    end loop;
    wait;
  end process;
end architecture;

prova2/2023-2/q2/work/wave.vcd
$date
  Thu Dec 12 22:23:31 2024
$end
$version
  GHDL v0
$end
$timescale
  1 fs
$end
$scope module standard $end
$upscope $end
$scope module std_logic_1164 $end
$upscope $end
$scope module numeric_std $end
$upscope $end
$scope module contador_tb $end
$var reg 1 ! clk $end
$var reg 1 " reset $end
$var reg 3 # x[2:0] $end
$var reg 1 $ s $end
$scope module uut $end
$var reg 1 % clk $end
$var reg 1 & reset $end
$var reg 3 ' x[2:0] $end
$var reg 1 ( s $end
$var reg 3 ) q[2:0] $end
$var reg 1 * x3 $end
$upscope $end
$upscope $end
$enddefinitions $end
#0
1!
0"
b110 #
0$
1%
0&
b110 '
0(
b110 )
1*
#10000000
0!
0%
#20000000
1!
b101 #
1%
b101 '
b101 )
#30000000
0!
1"
0%
1&
#40000000
1!
b000 #
1$
1%
b000 '
1(
b000 )
#50000000
0!
0"
0%
0&
#60000000
1!
b001 #
0$
1%
b001 '
0(
b001 )
0*
#70000000
0!
0%
#80000000
1!
b010 #
1%
b010 '
b010 )
1*
#90000000
0!
0%
#100000000
1!
b101 #
1%
b101 '
b101 )
#110000000
0!
0%
#120000000
1!
b011 #
1%
b011 '
b011 )
0*
#130000000
0!
0%
#140000000
1!
b110 #
1%
b110 '
b110 )
1*
#150000000
0!
0%
#160000000
1!
b101 #
1%
b101 '
b101 )
#170000000
0!
0%
#180000000
1!
b011 #
1%
b011 '
b011 )
0*
#190000000
0!
0%
#200000000
1!
b110 #
1%
b110 '
b110 )
1*
#210000000
0!
0%
#220000000
1!
b101 #
1%
b101 '
b101 )
#230000000
0!
0%
#240000000
1!
b011 #
1%
b011 '
b011 )
0*
#250000000
0!
0%
#260000000
1!
b110 #
1%
b110 '
b110 )
1*
#270000000
0!
0%
#280000000
1!
b101 #
1%
b101 '
b101 )
#290000000
0!
0%
#300000000
1!
b011 #
1%
b011 '
b011 )
0*
#310000000
0!
0%
#320000000
1!
b110 #
1%
b110 '
b110 )
1*
#330000000
0!
0%
#340000000
1!
b101 #
1%
b101 '
b101 )
#350000000
0!
0%
#360000000
1!
b011 #
1%
b011 '
b011 )
0*
#370000000
0!
0%
#380000000
1!
b110 #
1%
b110 '
b110 )
1*
#390000000
0!
0%
#400000000
1!
b101 #
1%
b101 '
b101 )
#410000000
0!
0%
#420000000
1!
b011 #
1%
b011 '
b011 )
0*
#430000000
0!
0%
#440000000
1!
b110 #
1%
b110 '
b110 )
1*
#450000000
0!
0%
#460000000
1!
b101 #
1%
b101 '
b101 )
#470000000
0!
0%
#480000000
1!
b011 #
1%
b011 '
b011 )
0*
#490000000
0!
0%
#500000000
1!
b110 #
1%
b110 '
b110 )
1*
#510000000
0!
0%
#520000000
1!
b101 #
1%
b101 '
b101 )
#530000000
0!
0%
#540000000
1!
b011 #
1%
b011 '
b011 )
0*
#550000000
0!
0%
#560000000
1!
b110 #
1%
b110 '
b110 )
1*
#570000000
0!
0%
#580000000
1!
b101 #
1%
b101 '
b101 )
#590000000
0!
0%
#600000000
1!
b011 #
1%
b011 '
b011 )
0*
#610000000
0!
0%
#620000000
1!
b110 #
1%
b110 '
b110 )
1*
#630000000
0!
0%
#640000000
1!
b101 #
1%
b101 '
b101 )
#650000000
0!
0%
#660000000
1!
b011 #
1%
b011 '
b011 )
0*
#670000000
0!
0%
#680000000
1!
b110 #
1%
b110 '
b110 )
1*
#690000000
0!
0%
#700000000
1!
b101 #
1%
b101 '
b101 )
#710000000
0!
0%
#720000000
1!
b011 #
1%
b011 '
b011 )
0*
#730000000
0!
0%
#740000000
1!
b110 #
1%
b110 '
b110 )
1*
#750000000
0!
0%
#760000000
1!
b101 #
1%
b101 '
b101 )
#770000000
0!
0%
#780000000
1!
b011 #
1%
b011 '
b011 )
0*
#790000000
0!
0%
#800000000
1!
b110 #
1%
b110 '
b110 )
1*
#810000000
0!
0%
#820000000
1!
b101 #
1%
b101 '
b101 )
#830000000
0!
0%
#840000000
1!
b011 #
1%
b011 '
b011 )
0*
#850000000
0!
0%
#860000000
1!
b110 #
1%
b110 '
b110 )
1*
#870000000
0!
0%
#880000000
1!
b101 #
1%
b101 '
b101 )
#890000000
0!
0%
#900000000
1!
b011 #
1%
b011 '
b011 )
0*
#910000000
0!
0%
#920000000
1!
b110 #
1%
b110 '
b110 )
1*
#930000000
0!
0%
#940000000
1!
b101 #
1%
b101 '
b101 )
#950000000
0!
0%
#960000000
1!
b011 #
1%
b011 '
b011 )
0*
#970000000
0!
0%
#980000000
1!
b110 #
1%
b110 '
b110 )
1*
#990000000
0!
0%
#1000000000
1!
b101 #
1%
b101 '
b101 )
#1010000000
0!
0%
#1020000000
1!
b011 #
1%
b011 '
b011 )
0*
#1030000000
0!
0%
#1040000000
1!
b110 #
1%
b110 '
b110 )
1*
#1050000000
0!
0%
#1060000000
1!
b101 #
1%
b101 '
b101 )
#1070000000
0!
0%
#1080000000
1!
b011 #
1%
b011 '
b011 )
0*
#1090000000
0!
0%
#1100000000
1!
b110 #
1%
b110 '
b110 )
1*
#1110000000
0!
0%
#1120000000
1!
b101 #
1%
b101 '
b101 )
#1130000000
0!
0%
#1140000000
1!
b011 #
1%
b011 '
b011 )
0*
#1150000000
0!
0%
#1160000000
1!
b110 #
1%
b110 '
b110 )
1*
#1170000000
0!
0%
#1180000000
1!
b101 #
1%
b101 '
b101 )
#1190000000
0!
0%
#1200000000
1!
b011 #
1%
b011 '
b011 )
0*
#1210000000
0!
0%
#1220000000
1!
b110 #
1%
b110 '
b110 )
1*
#1230000000
0!
0%
#1240000000
1!
b101 #
1%
b101 '
b101 )
#1250000000
0!
0%
#1260000000
1!
b011 #
1%
b011 '
b011 )
0*
#1270000000
0!
0%
#1280000000
1!
b110 #
1%
b110 '
b110 )
1*
#1290000000
0!
0%
#1300000000
1!
b101 #
1%
b101 '
b101 )
#1310000000
0!
0%
#1320000000
1!
b011 #
1%
b011 '
b011 )
0*
#1330000000
0!
0%
#1340000000
1!
b110 #
1%
b110 '
b110 )
1*
#1350000000
0!
0%
#1360000000
1!
b101 #
1%
b101 '
b101 )
#1370000000
0!
0%
#1380000000
1!
b011 #
1%
b011 '
b011 )
0*
#1390000000
0!
0%
#1400000000
1!
b110 #
1%
b110 '
b110 )
1*
#1410000000
0!
0%
#1420000000
1!
b101 #
1%
b101 '
b101 )
#1430000000
0!
0%
#1440000000
1!
b011 #
1%
b011 '
b011 )
0*
#1450000000
0!
0%
#1460000000
1!
b110 #
1%
b110 '
b110 )
1*
#1470000000
0!
0%
#1480000000
1!
b101 #
1%
b101 '
b101 )
#1490000000
0!
0%
#1500000000
1!
b011 #
1%
b011 '
b011 )
0*
#1510000000
0!
0%
#1520000000
1!
b110 #
1%
b110 '
b110 )
1*
#1530000000
0!
0%
#1540000000
1!
b101 #
1%
b101 '
b101 )
#1550000000
0!
0%
#1560000000
1!
b011 #
1%
b011 '
b011 )
0*
#1570000000
0!
0%
#1580000000
1!
b110 #
1%
b110 '
b110 )
1*
#1590000000
0!
0%
#1600000000
1!
b101 #
1%
b101 '
b101 )
#1610000000
0!
0%
#1620000000
1!
b011 #
1%
b011 '
b011 )
0*
#1630000000
0!
0%
#1640000000
1!
b110 #
1%
b110 '
b110 )
1*
#1650000000
0!
0%
#1660000000
1!
b101 #
1%
b101 '
b101 )
#1670000000
0!
0%
#1680000000
1!
b011 #
1%
b011 '
b011 )
0*
#1690000000
0!
0%
#1700000000
1!
b110 #
1%
b110 '
b110 )
1*
#1710000000
0!
0%
#1720000000
1!
b101 #
1%
b101 '
b101 )
#1730000000
0!
0%
#1740000000
1!
b011 #
1%
b011 '
b011 )
0*
#1750000000
0!
0%
#1760000000
1!
b110 #
1%
b110 '
b110 )
1*
#1770000000
0!
0%
#1780000000
1!
b101 #
1%
b101 '
b101 )
#1790000000
0!
0%
#1800000000
1!
b011 #
1%
b011 '
b011 )
0*
#1810000000
0!
0%
#1820000000
1!
b110 #
1%
b110 '
b110 )
1*
#1830000000
0!
0%
#1840000000
1!
b101 #
1%
b101 '
b101 )
#1850000000
0!
0%
#1860000000
1!
b011 #
1%
b011 '
b011 )
0*
#1870000000
0!
0%
#1880000000
1!
b110 #
1%
b110 '
b110 )
1*
#1890000000
0!
0%
#1900000000
1!
b101 #
1%
b101 '
b101 )
#1910000000
0!
0%
#1920000000
1!
b011 #
1%
b011 '
b011 )
0*
#1930000000
0!
0%
#1940000000
1!
b110 #
1%
b110 '
b110 )
1*
#1950000000
0!
0%
#1960000000
1!
b101 #
1%
b101 '
b101 )
#1970000000
0!
0%
#1980000000
1!
b011 #
1%
b011 '
b011 )
0*
#1990000000
0!
0%
#2000000000
1!
b110 #
1%
b110 '
b110 )
1*
#2010000000
0!
0%
#2020000000
1!
b101 #
1%
b101 '
b101 )
#2030000000
0!
0%
#2040000000
1!
b011 #
1%
b011 '
b011 )
0*
#2050000000
0!
0%
#2060000000
1!
b110 #
1%
b110 '
b110 )
1*
#2070000000
0!
0%
#2080000000
1!
b101 #
1%
b101 '
b101 )
#2090000000
0!
0%
#2100000000
1!
b011 #
1%
b011 '
b011 )
0*
#2110000000
0!
0%
#2120000000
1!
b110 #
1%
b110 '
b110 )
1*
#2130000000
0!
0%
#2140000000
1!
b101 #
1%
b101 '
b101 )
#2150000000
0!
0%
#2160000000
1!
b011 #
1%
b011 '
b011 )
0*
#2170000000
0!
0%
#2180000000
1!
b110 #
1%
b110 '
b110 )
1*
#2190000000
0!
0%
#2200000000
1!
b101 #
1%
b101 '
b101 )
#2210000000
0!
0%
#2220000000
1!
b011 #
1%
b011 '
b011 )
0*
#2230000000
0!
0%
#2240000000
1!
b110 #
1%
b110 '
b110 )
1*
#2250000000
0!
0%
#2260000000
1!
b101 #
1%
b101 '
b101 )
#2270000000
0!
0%
#2280000000
1!
b011 #
1%
b011 '
b011 )
0*
#2290000000
0!
0%
#2300000000
1!
b110 #
1%
b110 '
b110 )
1*
#2310000000
0!
0%
#2320000000
1!
b101 #
1%
b101 '
b101 )
#2330000000
0!
0%
#2340000000
1!
b011 #
1%
b011 '
b011 )
0*
#2350000000
0!
0%
#2360000000
1!
b110 #
1%
b110 '
b110 )
1*
#2370000000
0!
0%
#2380000000
1!
b101 #
1%
b101 '
b101 )
#2390000000
0!
0%
#2400000000
1!
b011 #
1%
b011 '
b011 )
0*
#2410000000
0!
0%
#2420000000
1!
b110 #
1%
b110 '
b110 )
1*
#2430000000
0!
0%
#2440000000
1!
b101 #
1%
b101 '
b101 )
#2450000000
0!
0%
#2460000000
1!
b011 #
1%
b011 '
b011 )
0*
#2470000000
0!
0%
#2480000000
1!
b110 #
1%
b110 '
b110 )
1*
#2490000000
0!
0%
#2500000000
1!
b101 #
1%
b101 '
b101 )
#2510000000
0!
0%
#2520000000
1!
b011 #
1%
b011 '
b011 )
0*
#2530000000
0!
0%
#2540000000
1!
b110 #
1%
b110 '
b110 )
1*
#2550000000
0!
0%
#2560000000
1!
b101 #
1%
b101 '
b101 )
#2570000000
0!
0%
#2580000000
1!
b011 #
1%
b011 '
b011 )
0*
#2590000000
0!
0%
#2600000000
1!
b110 #
1%
b110 '
b110 )
1*
#2610000000
0!
0%
#2620000000
1!
b101 #
1%
b101 '
b101 )
#2630000000
0!
0%
#2640000000
1!
b011 #
1%
b011 '
b011 )
0*
#2650000000
0!
0%
#2660000000
1!
b110 #
1%
b110 '
b110 )
1*
#2670000000
0!
0%
#2680000000
1!
b101 #
1%
b101 '
b101 )
#2690000000
0!
0%
#2700000000
1!
b011 #
1%
b011 '
b011 )
0*
#2710000000
0!
0%
#2720000000
1!
b110 #
1%
b110 '
b110 )
1*
#2730000000
0!
0%
#2740000000
1!
b101 #
1%
b101 '
b101 )
#2750000000
0!
0%
#2760000000
1!
b011 #
1%
b011 '
b011 )
0*
#2770000000
0!
0%
#2780000000
1!
b110 #
1%
b110 '
b110 )
1*
#2790000000
0!
0%
#2800000000
1!
b101 #
1%
b101 '
b101 )
#2810000000
0!
0%
#2820000000
1!
b011 #
1%
b011 '
b011 )
0*
#2830000000
0!
0%
#2840000000
1!
b110 #
1%
b110 '
b110 )
1*
#2850000000
0!
0%
#2860000000
1!
b101 #
1%
b101 '
b101 )
#2870000000
0!
0%
#2880000000
1!
b011 #
1%
b011 '
b011 )
0*
#2890000000
0!
0%
#2900000000
1!
b110 #
1%
b110 '
b110 )
1*
#2910000000
0!
0%
#2920000000
1!
b101 #
1%
b101 '
b101 )
#2930000000
0!
0%
#2940000000
1!
b011 #
1%
b011 '
b011 )
0*
#2950000000
0!
0%
#2960000000
1!
b110 #
1%
b110 '
b110 )
1*
#2970000000
0!
0%
#2980000000
1!
b101 #
1%
b101 '
b101 )
#2990000000
0!
0%
#3000000000
1!
b011 #
1%
b011 '
b011 )
0*
#3010000000
0!
0%
#3020000000
1!
b110 #
1%
b110 '
b110 )
1*
#3030000000
0!
0%
#3040000000
1!
b101 #
1%
b101 '
b101 )
#3050000000
0!
0%
#3060000000
1!
b011 #
1%
b011 '
b011 )
0*
#3070000000
0!
0%
#3080000000
1!
b110 #
1%
b110 '
b110 )
1*
#3090000000
0!
0%
#3100000000
1!
b101 #
1%
b101 '
b101 )
#3110000000
0!
0%
#3120000000
1!
b011 #
1%
b011 '
b011 )
0*
#3130000000
0!
0%
#3140000000
1!
b110 #
1%
b110 '
b110 )
1*
#3150000000
0!
0%
#3160000000
1!
b101 #
1%
b101 '
b101 )
#3170000000
0!
0%
#3180000000
1!
b011 #
1%
b011 '
b011 )
0*
#3190000000
0!
0%
#3200000000
1!
b110 #
1%
b110 '
b110 )
1*
#3210000000
0!
0%
#3220000000
1!
b101 #
1%
b101 '
b101 )
#3230000000
0!
0%
#3240000000
1!
b011 #
1%
b011 '
b011 )
0*
#3250000000
0!
0%
#3260000000
1!
b110 #
1%
b110 '
b110 )
1*
#3270000000
0!
0%
#3280000000
1!
b101 #
1%
b101 '
b101 )
#3290000000
0!
0%
#3300000000
1!
b011 #
1%
b011 '
b011 )
0*
#3310000000
0!
0%
#3320000000
1!
b110 #
1%
b110 '
b110 )
1*
#3330000000
0!
0%
#3340000000
1!
b101 #
1%
b101 '
b101 )
#3350000000
0!
0%
#3360000000
1!
b011 #
1%
b011 '
b011 )
0*
#3370000000
0!
0%
#3380000000
1!
b110 #
1%
b110 '
b110 )
1*
#3390000000
0!
0%
#3400000000
1!
b101 #
1%
b101 '
b101 )
#3410000000
0!
0%
#3420000000
1!
b011 #
1%
b011 '
b011 )
0*
#3430000000
0!
0%
#3440000000
1!
b110 #
1%
b110 '
b110 )
1*
#3450000000
0!
0%
#3460000000
1!
b101 #
1%
b101 '
b101 )
#3470000000
0!
0%
#3480000000
1!
b011 #
1%
b011 '
b011 )
0*
#3490000000
0!
0%
#3500000000
1!
b110 #
1%
b110 '
b110 )
1*
#3510000000
0!
0%
#3520000000
1!
b101 #
1%
b101 '
b101 )
#3530000000
0!
0%
#3540000000
1!
b011 #
1%
b011 '
b011 )
0*
#3550000000
0!
0%
#3560000000
1!
b110 #
1%
b110 '
b110 )
1*
#3570000000
0!
0%
#3580000000
1!
b101 #
1%
b101 '
b101 )
#3590000000
0!
0%
#3600000000
1!
b011 #
1%
b011 '
b011 )
0*
#3610000000
0!
0%
#3620000000
1!
b110 #
1%
b110 '
b110 )
1*
#3630000000
0!
0%
#3640000000
1!
b101 #
1%
b101 '
b101 )
#3650000000
0!
0%
#3660000000
1!
b011 #
1%
b011 '
b011 )
0*
#3670000000
0!
0%
#3680000000
1!
b110 #
1%
b110 '
b110 )
1*
#3690000000
0!
0%
#3700000000
1!
b101 #
1%
b101 '
b101 )
#3710000000
0!
0%
#3720000000
1!
b011 #
1%
b011 '
b011 )
0*
#3730000000
0!
0%
#3740000000
1!
b110 #
1%
b110 '
b110 )
1*
#3750000000
0!
0%
#3760000000
1!
b101 #
1%
b101 '
b101 )
#3770000000
0!
0%
#3780000000
1!
b011 #
1%
b011 '
b011 )
0*
#3790000000
0!
0%
#3800000000
1!
b110 #
1%
b110 '
b110 )
1*
#3810000000
0!
0%
#3820000000
1!
b101 #
1%
b101 '
b101 )
#3830000000
0!
0%
#3840000000
1!
b011 #
1%
b011 '
b011 )
0*
#3850000000
0!
0%
#3860000000
1!
b110 #
1%
b110 '
b110 )
1*
#3870000000
0!
0%
#3880000000
1!
b101 #
1%
b101 '
b101 )
#3890000000
0!
0%
#3900000000
1!
b011 #
1%
b011 '
b011 )
0*
#3910000000
0!
0%
#3920000000
1!
b110 #
1%
b110 '
b110 )
1*
#3930000000
0!
0%
#3940000000
1!
b101 #
1%
b101 '
b101 )
#3950000000
0!
0%
#3960000000
1!
b011 #
1%
b011 '
b011 )
0*
#3970000000
0!
0%
#3980000000
1!
b110 #
1%
b110 '
b110 )
1*
#3990000000
0!
0%
#4000000000
1!
b101 #
1%
b101 '
b101 )
#4010000000
0!
0%
#4020000000
1!
b011 #
1%
b011 '
b011 )
0*
#4030000000
0!
0%
#4040000000
1!
b110 #
1%
b110 '
b110 )
1*
#4050000000
0!
0%
#4060000000
1!
b101 #
1%
b101 '
b101 )
#4070000000
0!
0%
#4080000000
1!
b011 #
1%
b011 '
b011 )
0*
#4090000000
0!
0%
#4100000000
1!
b110 #
1%
b110 '
b110 )
1*
#4110000000
0!
0%
#4120000000
1!
b101 #
1%
b101 '
b101 )
#4130000000
0!
0%
#4140000000
1!
b011 #
1%
b011 '
b011 )
0*
#4150000000
0!
0%
#4160000000
1!
b110 #
1%
b110 '
b110 )
1*
#4170000000
0!
0%
#4180000000
1!
b101 #
1%
b101 '
b101 )
#4190000000
0!
0%
#4200000000
1!
b011 #
1%
b011 '
b011 )
0*
#4210000000
0!
0%
#4220000000
1!
b110 #
1%
b110 '
b110 )
1*
#4230000000
0!
0%
#4240000000
1!
b101 #
1%
b101 '
b101 )
#4250000000
0!
0%
#4260000000
1!
b011 #
1%
b011 '
b011 )
0*
#4270000000
0!
0%
#4280000000
1!
b110 #
1%
b110 '
b110 )
1*
#4290000000
0!
0%
#4300000000
1!
b101 #
1%
b101 '
b101 )
#4310000000
0!
0%
#4320000000
1!
b011 #
1%
b011 '
b011 )
0*
#4330000000
0!
0%
#4340000000
1!
b110 #
1%
b110 '
b110 )
1*
#4350000000
0!
0%
#4360000000
1!
b101 #
1%
b101 '
b101 )
#4370000000
0!
0%
#4380000000
1!
b011 #
1%
b011 '
b011 )
0*
#4390000000
0!
0%
#4400000000
1!
b110 #
1%
b110 '
b110 )
1*
#4410000000
0!
0%
#4420000000
1!
b101 #
1%
b101 '
b101 )
#4430000000
0!
0%
#4440000000
1!
b011 #
1%
b011 '
b011 )
0*
#4450000000
0!
0%
#4460000000
1!
b110 #
1%
b110 '
b110 )
1*
#4470000000
0!
0%
#4480000000
1!
b101 #
1%
b101 '
b101 )
#4490000000
0!
0%
#4500000000
1!
b011 #
1%
b011 '
b011 )
0*
#4510000000
0!
0%
#4520000000
1!
b110 #
1%
b110 '
b110 )
1*
#4530000000
0!
0%
#4540000000
1!
b101 #
1%
b101 '
b101 )
#4550000000
0!
0%
#4560000000
1!
b011 #
1%
b011 '
b011 )
0*
#4570000000
0!
0%
#4580000000
1!
b110 #
1%
b110 '
b110 )
1*
#4590000000
0!
0%
#4600000000
1!
b101 #
1%
b101 '
b101 )
#4610000000
0!
0%
#4620000000
1!
b011 #
1%
b011 '
b011 )
0*
#4630000000
0!
0%
#4640000000
1!
b110 #
1%
b110 '
b110 )
1*
#4650000000
0!
0%
#4660000000
1!
b101 #
1%
b101 '
b101 )
#4670000000
0!
0%
#4680000000
1!
b011 #
1%
b011 '
b011 )
0*
#4690000000
0!
0%
#4700000000
1!
b110 #
1%
b110 '
b110 )
1*
#4710000000
0!
0%
#4720000000
1!
b101 #
1%
b101 '
b101 )
#4730000000
0!
0%
#4740000000
1!
b011 #
1%
b011 '
b011 )
0*
#4750000000
0!
0%
#4760000000
1!
b110 #
1%
b110 '
b110 )
1*
#4770000000
0!
0%
#4780000000
1!
b101 #
1%
b101 '
b101 )
#4790000000
0!
0%
#4800000000
1!
b011 #
1%
b011 '
b011 )
0*
#4810000000
0!
0%
#4820000000
1!
b110 #
1%
b110 '
b110 )
1*
#4830000000
0!
0%
#4840000000
1!
b101 #
1%
b101 '
b101 )
#4850000000
0!
0%
#4860000000
1!
b011 #
1%
b011 '
b011 )
0*
#4870000000
0!
0%
#4880000000
1!
b110 #
1%
b110 '
b110 )
1*
#4890000000
0!
0%
#4900000000
1!
b101 #
1%
b101 '
b101 )
#4910000000
0!
0%
#4920000000
1!
b011 #
1%
b011 '
b011 )
0*
#4930000000
0!
0%
#4940000000
1!
b110 #
1%
b110 '
b110 )
1*
#4950000000
0!
0%
#4960000000
1!
b101 #
1%
b101 '
b101 )
#4970000000
0!
0%
#4980000000
1!
b011 #
1%
b011 '
b011 )
0*
#4990000000
0!
0%
#5000000000
1!
b110 #
1%
b110 '
b110 )
1*
#5010000000
0!
0%
#5020000000
1!
b101 #
1%
b101 '
b101 )
#5030000000
0!
0%
#5040000000
1!
b011 #
1%
b011 '
b011 )
0*
#5050000000
0!
0%
#5060000000
1!
b110 #
1%
b110 '
b110 )
1*
#5070000000
0!
0%
#5080000000
1!
b101 #
1%
b101 '
b101 )
#5090000000
0!
0%
#5100000000
1!
b011 #
1%
b011 '
b011 )
0*
#5110000000
0!
0%
#5120000000
1!
b110 #
1%
b110 '
b110 )
1*
#5130000000
0!
0%
#5140000000
1!
b101 #
1%
b101 '
b101 )
#5150000000
0!
0%
#5160000000
1!
b011 #
1%
b011 '
b011 )
0*
#5170000000
0!
0%
#5180000000
1!
b110 #
1%
b110 '
b110 )
1*
#5190000000
0!
0%
#5200000000
1!
b101 #
1%
b101 '
b101 )
#5210000000
0!
0%
#5220000000
1!
b011 #
1%
b011 '
b011 )
0*
#5230000000
0!
0%
#5240000000
1!
b110 #
1%
b110 '
b110 )
1*
#5250000000
0!
0%
#5260000000
1!
b101 #
1%
b101 '
b101 )
#5270000000
0!
0%
#5280000000
1!
b011 #
1%
b011 '
b011 )
0*
#5290000000
0!
0%
#5300000000
1!
b110 #
1%
b110 '
b110 )
1*
#5310000000
0!
0%
#5320000000
1!
b101 #
1%
b101 '
b101 )
#5330000000
0!
0%
#5340000000
1!
b011 #
1%
b011 '
b011 )
0*
#5350000000
0!
0%
#5360000000
1!
b110 #
1%
b110 '
b110 )
1*
#5370000000
0!
0%
#5380000000
1!
b101 #
1%
b101 '
b101 )
#5390000000
0!
0%
#5400000000
1!
b011 #
1%
b011 '
b011 )
0*
#5410000000
0!
0%
#5420000000
1!
b110 #
1%
b110 '
b110 )
1*
#5430000000
0!
0%
#5440000000
1!
b101 #
1%
b101 '
b101 )
#5450000000
0!
0%
#5460000000
1!
b011 #
1%
b011 '
b011 )
0*
#5470000000
0!
0%
#5480000000
1!
b110 #
1%
b110 '
b110 )
1*
#5490000000
0!
0%
#5500000000
1!
b101 #
1%
b101 '
b101 )
#5510000000
0!
0%
#5520000000
1!
b011 #
1%
b011 '
b011 )
0*
#5530000000
0!
0%
#5540000000
1!
b110 #
1%
b110 '
b110 )
1*
#5550000000
0!
0%
#5560000000
1!
b101 #
1%
b101 '
b101 )
#5570000000
0!
0%
#5580000000
1!
b011 #
1%
b011 '
b011 )
0*
#5590000000
0!
0%
#5600000000
1!
b110 #
1%
b110 '
b110 )
1*
#5610000000
0!
0%
#5620000000
1!
b101 #
1%
b101 '
b101 )
#5630000000
0!
0%
#5640000000
1!
b011 #
1%
b011 '
b011 )
0*
#5650000000
0!
0%
#5660000000
1!
b110 #
1%
b110 '
b110 )
1*
#5670000000
0!
0%
#5680000000
1!
b101 #
1%
b101 '
b101 )
#5690000000
0!
0%
#5700000000
1!
b011 #
1%
b011 '
b011 )
0*
#5710000000
0!
0%
#5720000000
1!
b110 #
1%
b110 '
b110 )
1*
#5730000000
0!
0%
#5740000000
1!
b101 #
1%
b101 '
b101 )
#5750000000
0!
0%
#5760000000
1!
b011 #
1%
b011 '
b011 )
0*
#5770000000
0!
0%
#5780000000
1!
b110 #
1%
b110 '
b110 )
1*
#5790000000
0!
0%
#5800000000
1!
b101 #
1%
b101 '
b101 )
#5810000000
0!
0%
#5820000000
1!
b011 #
1%
b011 '
b011 )
0*
#5830000000
0!
0%
#5840000000
1!
b110 #
1%
b110 '
b110 )
1*
#5850000000
0!
0%
#5860000000
1!
b101 #
1%
b101 '
b101 )
#5870000000
0!
0%
#5880000000
1!
b011 #
1%
b011 '
b011 )
0*
#5890000000
0!
0%
#5900000000
1!
b110 #
1%
b110 '
b110 )
1*
#5910000000
0!
0%
#5920000000
1!
b101 #
1%
b101 '
b101 )
#5930000000
0!
0%
#5940000000
1!
b011 #
1%
b011 '
b011 )
0*
#5950000000
0!
0%
#5960000000
1!
b110 #
1%
b110 '
b110 )
1*
#5970000000
0!
0%
#5980000000
1!
b101 #
1%
b101 '
b101 )
#5990000000
0!
0%
#6000000000
1!
b011 #
1%
b011 '
b011 )
0*
#6010000000
0!
0%
#6020000000
1!
b110 #
1%
b110 '
b110 )
1*
#6030000000
0!
0%
#6040000000
1!
b101 #
1%
b101 '
b101 )
#6050000000
0!
0%
#6060000000
1!
b011 #
1%
b011 '
b011 )
0*
#6070000000
0!
0%
#6080000000
1!
b110 #
1%
b110 '
b110 )
1*
#6090000000
0!
0%
#6100000000
1!
b101 #
1%
b101 '
b101 )
#6110000000
0!
0%
#6120000000
1!
b011 #
1%
b011 '
b011 )
0*
#6130000000
0!
0%
#6140000000
1!
b110 #
1%
b110 '
b110 )
1*
#6150000000
0!
0%
#6160000000
1!
b101 #
1%
b101 '
b101 )
#6170000000
0!
0%
#6180000000
1!
b011 #
1%
b011 '
b011 )
0*
#6190000000
0!
0%
#6200000000
1!
b110 #
1%
b110 '
b110 )
1*
#6210000000
0!
0%
#6220000000
1!
b101 #
1%
b101 '
b101 )
#6230000000
0!
0%
#6240000000
1!
b011 #
1%
b011 '
b011 )
0*
#6250000000
0!
0%
#6260000000
1!
b110 #
1%
b110 '
b110 )
1*
#6270000000
0!
0%
#6280000000
1!
b101 #
1%
b101 '
b101 )
#6290000000
0!
0%
#6300000000
1!
b011 #
1%
b011 '
b011 )
0*
#6310000000
0!
0%
#6320000000
1!
b110 #
1%
b110 '
b110 )
1*
#6330000000
0!
0%
#6340000000
1!
b101 #
1%
b101 '
b101 )
#6350000000
0!
0%
#6360000000
1!
b011 #
1%
b011 '
b011 )
0*
#6370000000
0!
0%
#6380000000
1!
b110 #
1%
b110 '
b110 )
1*
#6390000000
0!
0%
#6400000000
1!
b101 #
1%
b101 '
b101 )
#6410000000
0!
0%
#6420000000
1!
b011 #
1%
b011 '
b011 )
0*
#6430000000
0!
0%
#6440000000
1!
b110 #
1%
b110 '
b110 )
1*
#6450000000
0!
0%
#6460000000
1!
b101 #
1%
b101 '
b101 )
#6470000000
0!
0%
#6480000000
1!
b011 #
1%
b011 '
b011 )
0*
#6490000000
0!
0%
#6500000000
1!
b110 #
1%
b110 '
b110 )
1*
#6510000000
0!
0%
#6520000000
1!
b101 #
1%
b101 '
b101 )
#6530000000
0!
0%
#6540000000
1!
b011 #
1%
b011 '
b011 )
0*
#6550000000
0!
0%
#6560000000
1!
b110 #
1%
b110 '
b110 )
1*
#6570000000
0!
0%
#6580000000
1!
b101 #
1%
b101 '
b101 )
#6590000000
0!
0%
#6600000000
1!
b011 #
1%
b011 '
b011 )
0*
#6610000000
0!
0%
#6620000000
1!
b110 #
1%
b110 '
b110 )
1*
#6630000000
0!
0%
#6640000000
1!
b101 #
1%
b101 '
b101 )
#6650000000
0!
0%
#6660000000
1!
b011 #
1%
b011 '
b011 )
0*
#6670000000
0!
0%
#6680000000
1!
b110 #
1%
b110 '
b110 )
1*
#6690000000
0!
0%
#6700000000
1!
b101 #
1%
b101 '
b101 )
#6710000000
0!
0%
#6720000000
1!
b011 #
1%
b011 '
b011 )
0*
#6730000000
0!
0%
#6740000000
1!
b110 #
1%
b110 '
b110 )
1*
#6750000000
0!
0%
#6760000000
1!
b101 #
1%
b101 '
b101 )
#6770000000
0!
0%
#6780000000
1!
b011 #
1%
b011 '
b011 )
0*
#6790000000
0!
0%
#6800000000
1!
b110 #
1%
b110 '
b110 )
1*
#6810000000
0!
0%
