parte3/BCD/contador_BCD.vhd
library ieee;
use ieee.std_logic_1164.all;
use ieee.numeric_std.all;

entity contador_BCD is
    port
    (
        saida_BCD     : out std_logic_vector(3 downto 0); -- saída BCD do contador
        habilita      : in std_logic;                     -- habilita a contagem se ativo
        ultimo_estado : out std_logic;                    -- 1 se as saídas do contador é igual a 99
        clk           : in std_logic;                     -- sinal de relógio
        rst           : in std_logic                      -- sinal de reset assíncrono
    );
end entity;

architecture contador_BCD of contador_BCD is
    signal contador : unsigned(3 downto 0) := (others => '0');
begin

    saida_BCD <= std_logic_vector(contador);

    ultimo_estado <= '1' when (to_integer(contador) = 9) and (habilita = '1') else '0';

    process (clk, rst)
    begin
        if rst = '1' then
            contador <= (others => '0');
        elsif rising_edge(clk) then
            if habilita = '1' then
                if contador = 9 then
                    contador <= (others => '0');
                else
                    contador <= contador + 1;
                end if;
            end if;
        end if;
    end process;

end architecture;

parte3/BCD/contador_BCD_tb.vhd
library ieee;
use ieee.std_logic_1164.all;
use ieee.numeric_std.all;

entity contador_BCD_tb is
end entity;

architecture tb of contador_BCD_tb is
    component contador_BCD is
        port(
            saida_BCD     : out std_logic_vector(3 downto 0);
            habilita      : in std_logic;
            ultimo_estado : out std_logic;
            clk           : in std_logic;
            rst           : in std_logic
        );
    end component;

    signal saida_BCD     : std_logic_vector(3 downto 0);
    signal habilita      : std_logic := '0';
    signal ultimo_estado : std_logic;
    signal clk           : std_logic := '0';
    signal rst           : std_logic := '0';

    constant periodo : time := 20 ns;

begin
    DUT: contador_BCD port map(
        saida_BCD     => saida_BCD,
        habilita      => habilita,
        ultimo_estado => ultimo_estado,
        clk           => clk,
        rst           => rst
    );

    -- geramos o sinal de reset
    rst <= '0', '1' after 30 ns, '0' after 107 ns;
    -- geramos o sinal para habilitar a contagem
    habilita <= '1';

    -- geramos o sinal de relógio
    process
    begin
        clk <= '0';
        wait for 20 ns;
        loop
            clk <= '1';
            wait for periodo/2;
            clk <= '0';
            wait for PERIODO/2;
        end loop;
        wait;
    end process;

end architecture;

parte3/BCD/work/wave.vcd
$date
  Fri Dec 06 13:40:25 2024
$end
$version
  GHDL v0
$end
$timescale
  1 fs
$end
$scope module standard $end
$upscope $end
$scope module std_logic_1164 $end
$upscope $end
$scope module numeric_std $end
$upscope $end
$scope module contador_bcd_tb $end
$var reg 4 ! saida_bcd[3:0] $end
$var reg 1 " habilita $end
$var reg 1 # ultimo_estado $end
$var reg 1 $ clk $end
$var reg 1 % rst $end
$scope module dut $end
$var reg 4 & saida_bcd[3:0] $end
$var reg 1 ' habilita $end
$var reg 1 ( ultimo_estado $end
$var reg 1 ) clk $end
$var reg 1 * rst $end
$var reg 4 + contador[3:0] $end
$upscope $end
$upscope $end
$enddefinitions $end
#0
b0000 !
1"
0#
0$
0%
b0000 &
1'
0(
0)
0*
b0000 +
#20000000
b0001 !
1$
b0001 &
1)
b0001 +
#30000000
b0000 !
0$
1%
b0000 &
0)
1*
b0000 +
#40000000
1$
1)
#50000000
0$
0)
#60000000
1$
1)
#70000000
0$
0)
#80000000
1$
1)
#90000000
0$
0)
#100000000
1$
1)
#107000000
0%
0*
#110000000
0$
0)
#120000000
b0001 !
1$
b0001 &
1)
b0001 +
#130000000
0$
0)
#140000000
b0010 !
1$
b0010 &
1)
b0010 +
#150000000
0$
0)
#160000000
b0011 !
1$
b0011 &
1)
b0011 +
#170000000
0$
0)
#180000000
b0100 !
1$
b0100 &
1)
b0100 +
#190000000
0$
0)
#200000000
b0101 !
1$
b0101 &
1)
b0101 +
#210000000
0$
0)
#220000000
b0110 !
1$
b0110 &
1)
b0110 +
#230000000
0$
0)
#240000000
b0111 !
1$
b0111 &
1)
b0111 +
#250000000
0$
0)
#260000000
b1000 !
1$
b1000 &
1)
b1000 +
#270000000
0$
0)
#280000000
b1001 !
1#
1$
b1001 &
1(
1)
b1001 +
#290000000
0$
0)
#300000000
b0000 !
0#
1$
b0000 &
0(
1)
b0000 +
#310000000
0$
0)
#320000000
b0001 !
1$
b0001 &
1)
b0001 +
#330000000
0$
0)
#340000000
b0010 !
1$
b0010 &
1)
b0010 +
#350000000
0$
0)
#360000000
b0011 !
1$
b0011 &
1)
b0011 +
#370000000
0$
0)
#380000000
b0100 !
1$
b0100 &
1)
b0100 +
#390000000
0$
0)
#400000000
b0101 !
1$
b0101 &
1)
b0101 +
#410000000
0$
0)
#420000000
b0110 !
1$
b0110 &
1)
b0110 +
#430000000
0$
0)
#440000000
b0111 !
1$
b0111 &
1)
b0111 +
#450000000
0$
0)
#460000000
b1000 !
1$
b1000 &
1)
b1000 +
#470000000
0$
0)
#480000000
b1001 !
1#
1$
b1001 &
1(
1)
b1001 +
#490000000
0$
0)
#500000000
b0000 !
0#
1$
b0000 &
0(
1)
b0000 +
#510000000
0$
0)
#520000000
b0001 !
1$
b0001 &
1)
b0001 +
#530000000
0$
0)
#540000000
b0010 !
1$
b0010 &
1)
b0010 +
#550000000
0$
0)
#560000000
b0011 !
1$
b0011 &
1)
b0011 +
#570000000
0$
0)
#580000000
b0100 !
1$
b0100 &
1)
b0100 +
#590000000
0$
0)
#600000000
b0101 !
1$
b0101 &
1)
b0101 +
#610000000
0$
0)
#620000000
b0110 !
1$
b0110 &
1)
b0110 +
#630000000
0$
0)
#640000000
b0111 !
1$
b0111 &
1)
b0111 +
#650000000
0$
0)
#660000000
b1000 !
1$
b1000 &
1)
b1000 +
#670000000
0$
0)
#680000000
b1001 !
1#
1$
b1001 &
1(
1)
b1001 +
#690000000
0$
0)
#700000000
b0000 !
0#
1$
b0000 &
0(
1)
b0000 +
#710000000
0$
0)
#720000000
b0001 !
1$
b0001 &
1)
b0001 +
#730000000
0$
0)
#740000000
b0010 !
1$
b0010 &
1)
b0010 +
#750000000
0$
0)
#760000000
b0011 !
1$
b0011 &
1)
b0011 +
#770000000
0$
0)
#780000000
b0100 !
1$
b0100 &
1)
b0100 +
#790000000
0$
0)
#800000000
b0101 !
1$
b0101 &
1)
b0101 +
#810000000
0$
0)
#820000000
b0110 !
1$
b0110 &
1)
b0110 +
#830000000
0$
0)
#840000000
b0111 !
1$
b0111 &
1)
b0111 +
#850000000
0$
0)
#860000000
b1000 !
1$
b1000 &
1)
b1000 +
#870000000
0$
0)
#880000000
b1001 !
1#
1$
b1001 &
1(
1)
b1001 +
#890000000
0$
0)
#900000000
b0000 !
0#
1$
b0000 &
0(
1)
b0000 +
#910000000
0$
0)
#920000000
b0001 !
1$
b0001 &
1)
b0001 +
#930000000
0$
0)
#940000000
b0010 !
1$
b0010 &
1)
b0010 +
#950000000
0$
0)
#960000000
b0011 !
1$
b0011 &
1)
b0011 +
#970000000
0$
0)
#980000000
b0100 !
1$
b0100 &
1)
b0100 +
#990000000
0$
0)
#1000000000
b0101 !
1$
b0101 &
1)
b0101 +
#1010000000
0$
0)
#1020000000
b0110 !
1$
b0110 &
1)
b0110 +
#1030000000
0$
0)
#1040000000
b0111 !
1$
b0111 &
1)
b0111 +
#1050000000
0$
0)
#1060000000
b1000 !
1$
b1000 &
1)
b1000 +
#1070000000
0$
0)
#1080000000
b1001 !
1#
1$
b1001 &
1(
1)
b1001 +
#1090000000
0$
0)
#1100000000
b0000 !
0#
1$
b0000 &
0(
1)
b0000 +
#1110000000
0$
0)
#1120000000
b0001 !
1$
b0001 &
1)
b0001 +
#1130000000
0$
0)
#1140000000
b0010 !
1$
b0010 &
1)
b0010 +
#1150000000
0$
0)
#1160000000
b0011 !
1$
b0011 &
1)
b0011 +
#1170000000
0$
0)
#1180000000
b0100 !
1$
b0100 &
1)
b0100 +
#1190000000
0$
0)
#1200000000
b0101 !
1$
b0101 &
1)
b0101 +
#1210000000
0$
0)
#1220000000
b0110 !
1$
b0110 &
1)
b0110 +
#1230000000
0$
0)
#1240000000
b0111 !
1$
b0111 &
1)
b0111 +
#1250000000
0$
0)
#1260000000
b1000 !
1$
b1000 &
1)
b1000 +
#1270000000
0$
0)
#1280000000
b1001 !
1#
1$
b1001 &
1(
1)
b1001 +
#1290000000
0$
0)
#1300000000
b0000 !
0#
1$
b0000 &
0(
1)
b0000 +
#1310000000
0$
0)
#1320000000
b0001 !
1$
b0001 &
1)
b0001 +
#1330000000
0$
0)
#1340000000
b0010 !
1$
b0010 &
1)
b0010 +
#1350000000
0$
0)
#1360000000
b0011 !
1$
b0011 &
1)
b0011 +
#1370000000
0$
0)
#1380000000
b0100 !
1$
b0100 &
1)
b0100 +
#1390000000
0$
0)
#1400000000
b0101 !
1$
b0101 &
1)
b0101 +
#1410000000
0$
0)
#1420000000
b0110 !
1$
b0110 &
1)
b0110 +
#1430000000
0$
0)
#1440000000
b0111 !
1$
b0111 &
1)
b0111 +
#1450000000
0$
0)
#1460000000
b1000 !
1$
b1000 &
1)
b1000 +
#1470000000
0$
0)
#1480000000
b1001 !
1#
1$
b1001 &
1(
1)
b1001 +
#1490000000
0$
0)
#1500000000
b0000 !
0#
1$
b0000 &
0(
1)
b0000 +
#1510000000
0$
0)
#1520000000
b0001 !
1$
b0001 &
1)
b0001 +
#1530000000
0$
0)
#1540000000
b0010 !
1$
b0010 &
1)
b0010 +
#1550000000
0$
0)
#1560000000
b0011 !
1$
b0011 &
1)
b0011 +
#1570000000
0$
0)
#1580000000
b0100 !
1$
b0100 &
1)
b0100 +
#1590000000
0$
0)
#1600000000
b0101 !
1$
b0101 &
1)
b0101 +
#1610000000
0$
0)
#1620000000
b0110 !
1$
b0110 &
1)
b0110 +
#1630000000
0$
0)
#1640000000
b0111 !
1$
b0111 &
1)
b0111 +
#1650000000
0$
0)
#1660000000
b1000 !
1$
b1000 &
1)
b1000 +
#1670000000
0$
0)
#1680000000
b1001 !
1#
1$
b1001 &
1(
1)
b1001 +
#1690000000
0$
0)
#1700000000
b0000 !
0#
1$
b0000 &
0(
1)
b0000 +
#1710000000
0$
0)
#1720000000
b0001 !
1$
b0001 &
1)
b0001 +
#1730000000
0$
0)
#1740000000
b0010 !
1$
b0010 &
1)
b0010 +
#1750000000
0$
0)
#1760000000
b0011 !
1$
b0011 &
1)
b0011 +
#1770000000
0$
0)
#1780000000
b0100 !
1$
b0100 &
1)
b0100 +
#1790000000
0$
0)
#1800000000
b0101 !
1$
b0101 &
1)
b0101 +
#1810000000
0$
0)
#1820000000
b0110 !
1$
b0110 &
1)
b0110 +
#1830000000
0$
0)
#1840000000
b0111 !
1$
b0111 &
1)
b0111 +
#1850000000
0$
0)
#1860000000
b1000 !
1$
b1000 &
1)
b1000 +
#1870000000
0$
0)
#1880000000
b1001 !
1#
1$
b1001 &
1(
1)
b1001 +
#1890000000
0$
0)
#1900000000
b0000 !
0#
1$
b0000 &
0(
1)
b0000 +
#1910000000
0$
0)
#1920000000
b0001 !
1$
b0001 &
1)
b0001 +
#1930000000
0$
0)
#1940000000
b0010 !
1$
b0010 &
1)
b0010 +
#1950000000
0$
0)
#1960000000
b0011 !
1$
b0011 &
1)
b0011 +
#1970000000
0$
0)
#1980000000
b0100 !
1$
b0100 &
1)
b0100 +
#1990000000
0$
0)
#2000000000
b0101 !
1$
b0101 &
1)
b0101 +
#2010000000
0$
0)
#2020000000
b0110 !
1$
b0110 &
1)
b0110 +
#2030000000
0$
0)
#2040000000
b0111 !
1$
b0111 &
1)
b0111 +
#2050000000
0$
0)
#2060000000
b1000 !
1$
b1000 &
1)
b1000 +
#2070000000
0$
0)
#2080000000
b1001 !
1#
1$
b1001 &
1(
1)
b1001 +
#2090000000
0$
0)
#2100000000
b0000 !
0#
1$
b0000 &
0(
1)
b0000 +
#2110000000
0$
0)
#2120000000
b0001 !
1$
b0001 &
1)
b0001 +
#2130000000
0$
0)
#2140000000
b0010 !
1$
b0010 &
1)
b0010 +
#2150000000
0$
0)
#2160000000
b0011 !
1$
b0011 &
1)
b0011 +
#2170000000
0$
0)
#2180000000
b0100 !
1$
b0100 &
1)
b0100 +
#2190000000
0$
0)
#2200000000
b0101 !
1$
b0101 &
1)
b0101 +
#2210000000
0$
0)
#2220000000
b0110 !
1$
b0110 &
1)
b0110 +
#2230000000
0$
0)
#2240000000
b0111 !
1$
b0111 &
1)
b0111 +
#2250000000
0$
0)
#2260000000
b1000 !
1$
b1000 &
1)
b1000 +
#2270000000
0$
0)
#2280000000
b1001 !
1#
1$
b1001 &
1(
1)
b1001 +
#2290000000
0$
0)
#2300000000
b0000 !
0#
1$
b0000 &
0(
1)
b0000 +
#2310000000
0$
0)
#2320000000
b0001 !
1$
b0001 &
1)
b0001 +
#2330000000
0$
0)
#2340000000
b0010 !
1$
b0010 &
1)
b0010 +
#2350000000
0$
0)
#2360000000
b0011 !
1$
b0011 &
1)
b0011 +
#2370000000
0$
0)
#2380000000
b0100 !
1$
b0100 &
1)
b0100 +
#2390000000
0$
0)
#2400000000
b0101 !
1$
b0101 &
1)
b0101 +
#2410000000
0$
0)
#2420000000
b0110 !
1$
b0110 &
1)
b0110 +
#2430000000
0$
0)
#2440000000
b0111 !
1$
b0111 &
1)
b0111 +
#2450000000
0$
0)
#2460000000
b1000 !
1$
b1000 &
1)
b1000 +
#2470000000
0$
0)
#2480000000
b1001 !
1#
1$
b1001 &
1(
1)
b1001 +
#2490000000
0$
0)
#2500000000
b0000 !
0#
1$
b0000 &
0(
1)
b0000 +
#2510000000
0$
0)
#2520000000
b0001 !
1$
b0001 &
1)
b0001 +
#2530000000
0$
0)
#2540000000
b0010 !
1$
b0010 &
1)
b0010 +
#2550000000
0$
0)
#2560000000
b0011 !
1$
b0011 &
1)
b0011 +
#2570000000
0$
0)
#2580000000
b0100 !
1$
b0100 &
1)
b0100 +
#2590000000
0$
0)
#2600000000
b0101 !
1$
b0101 &
1)
b0101 +
#2610000000
0$
0)
#2620000000
b0110 !
1$
b0110 &
1)
b0110 +
#2630000000
0$
0)
#2640000000
b0111 !
1$
b0111 &
1)
b0111 +
#2650000000
0$
0)
#2660000000
b1000 !
1$
b1000 &
1)
b1000 +
#2670000000
0$
0)
#2680000000
b1001 !
1#
1$
b1001 &
1(
1)
b1001 +
#2690000000
0$
0)
#2700000000
b0000 !
0#
1$
b0000 &
0(
1)
b0000 +
#2710000000
0$
0)
#2720000000
b0001 !
1$
b0001 &
1)
b0001 +
#2730000000
0$
0)
#2740000000
b0010 !
1$
b0010 &
1)
b0010 +
#2750000000
0$
0)
#2760000000
b0011 !
1$
b0011 &
1)
b0011 +
#2770000000
0$
0)
#2780000000
b0100 !
1$
b0100 &
1)
b0100 +
#2790000000
0$
0)
#2800000000
b0101 !
1$
b0101 &
1)
b0101 +
#2810000000
0$
0)
#2820000000
b0110 !
1$
b0110 &
1)
b0110 +
#2830000000
0$
0)
#2840000000
b0111 !
1$
b0111 &
1)
b0111 +
#2850000000
0$
0)
#2860000000
b1000 !
1$
b1000 &
1)
b1000 +
#2870000000
0$
0)
#2880000000
b1001 !
1#
1$
b1001 &
1(
1)
b1001 +
#2890000000
0$
0)
#2900000000
b0000 !
0#
1$
b0000 &
0(
1)
b0000 +
#2910000000
0$
0)
#2920000000
b0001 !
1$
b0001 &
1)
b0001 +
#2930000000
0$
0)
#2940000000
b0010 !
1$
b0010 &
1)
b0010 +
#2950000000
0$
0)
#2960000000
b0011 !
1$
b0011 &
1)
b0011 +
#2970000000
0$
0)
#2980000000
b0100 !
1$
b0100 &
1)
b0100 +
#2990000000
0$
0)
#3000000000
b0101 !
1$
b0101 &
1)
b0101 +
#3010000000
0$
0)
#3020000000
b0110 !
1$
b0110 &
1)
b0110 +
#3030000000
0$
0)
#3040000000
b0111 !
1$
b0111 &
1)
b0111 +
#3050000000
0$
0)
#3060000000
b1000 !
1$
b1000 &
1)
b1000 +
#3070000000
0$
0)
#3080000000
b1001 !
1#
1$
b1001 &
1(
1)
b1001 +
#3090000000
0$
0)
#3100000000
b0000 !
0#
1$
b0000 &
0(
1)
b0000 +
#3110000000
0$
0)
#3120000000
b0001 !
1$
b0001 &
1)
b0001 +
#3130000000
0$
0)
#3140000000
b0010 !
1$
b0010 &
1)
b0010 +
#3150000000
0$
0)
#3160000000
b0011 !
1$
b0011 &
1)
b0011 +
#3170000000
0$
0)
#3180000000
b0100 !
1$
b0100 &
1)
b0100 +
#3190000000
0$
0)
#3200000000
b0101 !
1$
b0101 &
1)
b0101 +
#3210000000
0$
0)
#3220000000
b0110 !
1$
b0110 &
1)
b0110 +
#3230000000
0$
0)
#3240000000
b0111 !
1$
b0111 &
1)
b0111 +
#3250000000
0$
0)
#3260000000
b1000 !
1$
b1000 &
1)
b1000 +
#3270000000
0$
0)
#3280000000
b1001 !
1#
1$
b1001 &
1(
1)
b1001 +
#3290000000
0$
0)
#3300000000
b0000 !
0#
1$
b0000 &
0(
1)
b0000 +
#3310000000
0$
0)
#3320000000
b0001 !
1$
b0001 &
1)
b0001 +
#3330000000
0$
0)
#3340000000
b0010 !
1$
b0010 &
1)
b0010 +
#3350000000
0$
0)
#3360000000
b0011 !
1$
b0011 &
1)
b0011 +
#3370000000
0$
0)
#3380000000
b0100 !
1$
b0100 &
1)
b0100 +
#3390000000
0$
0)
#3400000000
b0101 !
1$
b0101 &
1)
b0101 +
#3410000000
0$
0)
#3420000000
b0110 !
1$
b0110 &
1)
b0110 +
#3430000000
0$
0)
#3440000000
b0111 !
1$
b0111 &
1)
b0111 +
#3450000000
0$
0)
#3460000000
b1000 !
1$
b1000 &
1)
b1000 +
#3470000000
0$
0)
#3480000000
b1001 !
1#
1$
b1001 &
1(
1)
b1001 +
#3490000000
0$
0)
#3500000000
b0000 !
0#
1$
b0000 &
0(
1)
b0000 +
#3510000000
0$
0)
#3520000000
b0001 !
1$
b0001 &
1)
b0001 +
#3530000000
0$
0)
#3540000000
b0010 !
1$
b0010 &
1)
b0010 +
#3550000000
0$
0)
#3560000000
b0011 !
1$
b0011 &
1)
b0011 +
#3570000000
0$
0)
#3580000000
b0100 !
1$
b0100 &
1)
b0100 +
#3590000000
0$
0)
#3600000000
b0101 !
1$
b0101 &
1)
b0101 +
#3610000000
0$
0)
#3620000000
b0110 !
1$
b0110 &
1)
b0110 +
#3630000000
0$
0)
#3640000000
b0111 !
1$
b0111 &
1)
b0111 +
#3650000000
0$
0)
#3660000000
b1000 !
1$
b1000 &
1)
b1000 +
#3670000000
0$
0)
#3680000000
b1001 !
1#
1$
b1001 &
1(
1)
b1001 +
#3690000000
0$
0)
#3700000000
b0000 !
0#
1$
b0000 &
0(
1)
b0000 +
#3710000000
0$
0)
#3720000000
b0001 !
1$
b0001 &
1)
b0001 +
#3730000000
0$
0)
#3740000000
b0010 !
1$
b0010 &
1)
b0010 +
#3750000000
0$
0)
#3760000000
b0011 !
1$
b0011 &
1)
b0011 +
#3770000000
0$
0)
#3780000000
b0100 !
1$
b0100 &
1)
b0100 +
#3790000000
0$
0)
#3800000000
b0101 !
1$
b0101 &
1)
b0101 +
#3810000000
0$
0)
#3820000000
b0110 !
1$
b0110 &
1)
b0110 +
#3830000000
0$
0)
#3840000000
b0111 !
1$
b0111 &
1)
b0111 +
#3850000000
0$
0)
#3860000000
b1000 !
1$
b1000 &
1)
b1000 +
#3870000000
0$
0)
#3880000000
b1001 !
1#
1$
b1001 &
1(
1)
b1001 +
#3890000000
0$
0)
#3900000000
b0000 !
0#
1$
b0000 &
0(
1)
b0000 +
#3910000000
0$
0)
#3920000000
b0001 !
1$
b0001 &
1)
b0001 +
#3930000000
0$
0)
#3940000000
b0010 !
1$
b0010 &
1)
b0010 +
#3950000000
0$
0)
#3960000000
b0011 !
1$
b0011 &
1)
b0011 +
#3970000000
0$
0)
#3980000000
b0100 !
1$
b0100 &
1)
b0100 +
#3990000000
0$
0)
#4000000000
b0101 !
1$
b0101 &
1)
b0101 +
#4010000000
0$
0)
#4020000000
b0110 !
1$
b0110 &
1)
b0110 +
#4030000000
0$
0)
#4040000000
b0111 !
1$
b0111 &
1)
b0111 +
#4050000000
0$
0)
#4060000000
b1000 !
1$
b1000 &
1)
b1000 +
#4070000000
0$
0)
#4080000000
b1001 !
1#
1$
b1001 &
1(
1)
b1001 +
#4090000000
0$
0)
#4100000000
b0000 !
0#
1$
b0000 &
0(
1)
b0000 +
#4110000000
0$
0)
#4120000000
b0001 !
1$
b0001 &
1)
b0001 +
#4130000000
0$
0)
#4140000000
b0010 !
1$
b0010 &
1)
b0010 +
#4150000000
0$
0)
#4160000000
b0011 !
1$
b0011 &
1)
b0011 +
#4170000000
0$
0)
#4180000000
b0100 !
1$
b0100 &
1)
b0100 +
#4190000000
0$
0)
#4200000000
b0101 !
1$
b0101 &
1)
b0101 +
#4210000000
0$
0)
#4220000000
b0110 !
1$
b0110 &
1)
b0110 +
#4230000000
0$
0)
#4240000000
b0111 !
1$
b0111 &
1)
b0111 +
#4250000000
0$
0)
#4260000000
b1000 !
1$
b1000 &
1)
b1000 +
#4270000000
0$
0)
#4280000000
b1001 !
1#
1$
b1001 &
1(
1)
b1001 +
#4290000000
0$
0)
#4300000000
b0000 !
0#
1$
b0000 &
0(
1)
b0000 +
#4310000000
0$
0)
#4320000000
b0001 !
1$
b0001 &
1)
b0001 +
#4330000000
0$
0)
#4340000000
b0010 !
1$
b0010 &
1)
b0010 +
#4350000000
0$
0)
#4360000000
b0011 !
1$
b0011 &
1)
b0011 +
#4370000000
0$
0)
#4380000000
b0100 !
1$
b0100 &
1)
b0100 +
#4390000000
0$
0)
#4400000000
b0101 !
1$
b0101 &
1)
b0101 +
#4410000000
0$
0)
#4420000000
b0110 !
1$
b0110 &
1)
b0110 +
#4430000000
0$
0)
#4440000000
b0111 !
1$
b0111 &
1)
b0111 +
#4450000000
0$
0)
#4460000000
b1000 !
1$
b1000 &
1)
b1000 +
#4470000000
0$
0)
#4480000000
b1001 !
1#
1$
b1001 &
1(
1)
b1001 +
#4490000000
0$
0)
#4500000000
b0000 !
0#
1$
b0000 &
0(
1)
b0000 +
#4510000000
0$
0)
#4520000000
b0001 !
1$
b0001 &
1)
b0001 +
#4530000000
0$
0)
#4540000000
b0010 !
1$
b0010 &
1)
b0010 +
#4550000000
0$
0)
#4560000000
b0011 !
1$
b0011 &
1)
b0011 +
#4570000000
0$
0)
#4580000000
b0100 !
1$
b0100 &
1)
b0100 +
#4590000000
0$
0)
#4600000000
b0101 !
1$
b0101 &
1)
b0101 +
#4610000000
0$
0)
#4620000000
b0110 !
1$
b0110 &
1)
b0110 +
#4630000000
0$
0)
#4640000000
b0111 !
1$
b0111 &
1)
b0111 +
#4650000000
0$
0)
#4660000000
b1000 !
1$
b1000 &
1)
b1000 +
#4670000000
0$
0)
#4680000000
b1001 !
1#
1$
b1001 &
1(
1)
b1001 +
#4690000000
0$
0)
#4700000000
b0000 !
0#
1$
b0000 &
0(
1)
b0000 +
#4710000000
0$
0)
#4720000000
b0001 !
1$
b0001 &
1)
b0001 +
#4730000000
0$
0)
#4740000000
b0010 !
1$
b0010 &
1)
b0010 +
#4750000000
0$
0)
#4760000000
b0011 !
1$
b0011 &
1)
b0011 +
#4770000000
0$
0)
#4780000000
b0100 !
1$
b0100 &
1)
b0100 +
#4790000000
0$
0)
#4800000000
b0101 !
1$
b0101 &
1)
b0101 +
#4810000000
0$
0)
#4820000000
b0110 !
1$
b0110 &
1)
b0110 +
#4830000000
0$
0)
#4840000000
b0111 !
1$
b0111 &
1)
b0111 +
#4850000000
0$
0)
#4860000000
b1000 !
1$
b1000 &
1)
b1000 +
#4870000000
0$
0)
#4880000000
b1001 !
1#
1$
b1001 &
1(
1)
b1001 +
#4890000000
0$
0)
#4900000000
b0000 !
0#
1$
b0000 &
0(
1)
b0000 +
#4910000000
0$
0)
#4920000000
b0001 !
1$
b0001 &
1)
b0001 +
#4930000000
0$
0)
#4940000000
b0010 !
1$
b0010 &
1)
b0010 +
#4950000000
0$
0)
#4960000000
b0011 !
1$
b0011 &
1)
b0011 +
#4970000000
0$
0)
#4980000000
b0100 !
1$
b0100 &
1)
b0100 +
#4990000000
0$
0)
#5000000000
b0101 !
1$
b0101 &
1)
b0101 +
#5010000000
0$
0)
#5020000000
b0110 !
1$
b0110 &
1)
b0110 +
#5030000000
0$
0)
#5040000000
b0111 !
1$
b0111 &
1)
b0111 +
#5050000000
0$
0)
#5060000000
b1000 !
1$
b1000 &
1)
b1000 +
#5070000000
0$
0)
#5080000000
b1001 !
1#
1$
b1001 &
1(
1)
b1001 +
#5090000000
0$
0)
#5100000000
b0000 !
0#
1$
b0000 &
0(
1)
b0000 +
#5110000000
0$
0)
#5120000000
b0001 !
1$
b0001 &
1)
b0001 +
#5130000000
0$
0)
#5140000000
b0010 !
1$
b0010 &
1)
b0010 +
#5150000000
0$
0)
#5160000000
b0011 !
1$
b0011 &
1)
b0011 +
#5170000000
0$
0)
#5180000000
b0100 !
1$
b0100 &
1)
b0100 +
#5190000000
0$
0)
#5200000000
b0101 !
1$
b0101 &
1)
b0101 +
#5210000000
0$
0)
#5220000000
b0110 !
1$
b0110 &
1)
b0110 +
#5230000000
0$
0)
#5240000000
b0111 !
1$
b0111 &
1)
b0111 +
#5250000000
0$
0)
#5260000000
b1000 !
1$
b1000 &
1)
b1000 +
#5270000000
0$
0)
#5280000000
b1001 !
1#
1$
b1001 &
1(
1)
b1001 +
#5290000000
0$
0)
#5300000000
b0000 !
0#
1$
b0000 &
0(
1)
b0000 +
#5310000000
0$
0)
#5320000000
b0001 !
1$
b0001 &
1)
b0001 +
#5330000000
0$
0)
#5340000000
b0010 !
1$
b0010 &
1)
b0010 +
#5350000000
0$
0)
#5360000000
b0011 !
1$
b0011 &
1)
b0011 +
#5370000000
0$
0)
#5380000000
b0100 !
1$
b0100 &
1)
b0100 +
#5390000000
0$
0)
#5400000000
b0101 !
1$
b0101 &
1)
b0101 +
#5410000000
0$
0)
#5420000000
b0110 !
1$
b0110 &
1)
b0110 +
#5430000000
0$
0)
#5440000000
b0111 !
1$
b0111 &
1)
b0111 +
#5450000000
0$
0)
#5460000000
b1000 !
1$
b1000 &
1)
b1000 +
#5470000000
0$
0)
#5480000000
b1001 !
1#
1$
b1001 &
1(
1)
b1001 +
#5490000000
0$
0)
#5500000000
b0000 !
0#
1$
b0000 &
0(
1)
b0000 +
#5510000000
0$
0)
#5520000000
b0001 !
1$
b0001 &
1)
b0001 +
#5530000000
0$
0)
#5540000000
b0010 !
1$
b0010 &
1)
b0010 +
#5550000000
0$
0)
#5560000000
b0011 !
1$
b0011 &
1)
b0011 +
#5570000000
0$
0)
#5580000000
b0100 !
1$
b0100 &
1)
b0100 +
#5590000000
0$
0)
#5600000000
b0101 !
1$
b0101 &
1)
b0101 +
#5610000000
0$
0)
#5620000000
b0110 !
1$
b0110 &
1)
b0110 +
#5630000000
0$
0)
#5640000000
b0111 !
1$
b0111 &
1)
b0111 +
#5650000000
0$
0)
#5660000000
b1000 !
1$
b1000 &
1)
b1000 +
#5670000000
0$
0)
#5680000000
b1001 !
1#
1$
b1001 &
1(
1)
b1001 +
#5690000000
0$
0)
#5700000000
b0000 !
0#
1$
b0000 &
0(
1)
b0000 +
#5710000000
0$
0)
#5720000000
b0001 !
1$
b0001 &
1)
b0001 +
#5730000000
0$
0)
#5740000000
b0010 !
1$
b0010 &
1)
b0010 +
#5750000000
0$
0)
#5760000000
b0011 !
1$
b0011 &
1)
b0011 +
#5770000000
0$
0)
#5780000000
b0100 !
1$
b0100 &
1)
b0100 +
#5790000000
0$
0)
#5800000000
b0101 !
1$
b0101 &
1)
b0101 +
#5810000000
0$
0)
#5820000000
b0110 !
1$
b0110 &
1)
b0110 +
#5830000000
0$
0)
#5840000000
b0111 !
1$
b0111 &
1)
b0111 +
#5850000000
0$
0)
#5860000000
b1000 !
1$
b1000 &
1)
b1000 +
#5870000000
0$
0)
#5880000000
b1001 !
1#
1$
b1001 &
1(
1)
b1001 +
#5890000000
0$
0)
#5900000000
b0000 !
0#
1$
b0000 &
0(
1)
b0000 +
#5910000000
0$
0)
#5920000000
b0001 !
1$
b0001 &
1)
b0001 +
#5930000000
0$
0)
#5940000000
b0010 !
1$
b0010 &
1)
b0010 +
#5950000000
0$
0)
#5960000000
b0011 !
1$
b0011 &
1)
b0011 +
#5970000000
0$
0)
#5980000000
b0100 !
1$
b0100 &
1)
b0100 +
#5990000000
0$
0)
#6000000000
b0101 !
1$
b0101 &
1)
b0101 +
#6010000000
0$
0)
#6020000000
b0110 !
1$
b0110 &
1)
b0110 +
#6030000000
0$
0)
#6040000000
b0111 !
1$
b0111 &
1)
b0111 +
#6050000000
0$
0)
#6060000000
b1000 !
1$
b1000 &
1)
b1000 +
#6070000000
0$
0)
#6080000000
b1001 !
1#
1$
b1001 &
1(
1)
b1001 +
#6090000000
0$
0)
#6100000000
b0000 !
0#
1$
b0000 &
0(
1)
b0000 +
#6110000000
0$
0)
#6120000000
b0001 !
1$
b0001 &
1)
b0001 +
#6130000000
0$
0)
#6140000000
b0010 !
1$
b0010 &
1)
b0010 +
#6150000000
0$
0)
#6160000000
b0011 !
1$
b0011 &
1)
b0011 +
#6170000000
0$
0)
#6180000000
b0100 !
1$
b0100 &
1)
b0100 +
#6190000000
0$
0)
#6200000000
b0101 !
1$
b0101 &
1)
b0101 +
#6210000000
0$
0)
#6220000000
b0110 !
1$
b0110 &
1)
b0110 +
#6230000000
0$
0)
#6240000000
b0111 !
1$
b0111 &
1)
b0111 +
#6250000000
0$
0)
#6260000000
b1000 !
1$
b1000 &
1)
b1000 +
#6270000000
0$
0)
#6280000000
b1001 !
1#
1$
b1001 &
1(
1)
b1001 +
#6290000000
0$
0)
#6300000000
b0000 !
0#
1$
b0000 &
0(
1)
b0000 +
#6310000000
0$
0)
#6320000000
b0001 !
1$
b0001 &
1)
b0001 +
#6330000000
0$
0)
#6340000000
b0010 !
1$
b0010 &
1)
b0010 +
#6350000000
0$
0)
