prova2/q1/primo.vhd
--  1. (5,0 pontos, 40 min.) Seja um circuito combinacional com 1 entrada x[3..0] com 4 bits, uma entrada enable e 
--  uma saída y. O sinal nas entradas x[3..0] representam um número binário sem sinal com 4 bits, com o valor de 0 
--  a 15. A saída y é igual a 1 quando o número x[3..0] é um número primo1 e o sinal habilita está ativo. A saída 
--  y permanece em 0 quando enable está inativo. Faça um testbench, verificando que o circuito reconhece os 
--  números primos e que o sinal enable está funcionado corretamente. Salve a tela com a simulação2

library ieee;
use ieee.std_logic_1164.all;
use ieee.numeric_std.all;

entity primo is
    port (
        x   : in std_logic_vector (3 downto 0);
        y   : out std_logic
    );
end entity;

architecture simple of primo is
    signal m1, m2, m3, m4 : std_logic;
begin
    m1 <= (not x(3) and not x(2) and x(0));
    m2 <= (not x(3) and     x(2) and x(0));
    m3 <= (    x(2) and not x(1) and x(0));
    m4 <= (not x(2) and     x(1) and x(0));
    
    y <= m1 or m2 or m3 or m4;

end architecture;

prova2/q1/primo_tb.vhd
library ieee;
use ieee.std_logic_1164.all;
use ieee.numeric_std.all;

entity primo_tb is
end entity;

architecture simple of primo_tb is
    component primo is
        port (
            x   : in std_logic_vector (3 downto 0);
            y   : out std_logic
        );
    end component;

    signal x : std_logic_vector (3 downto 0) := "0000";
    signal y : std_logic;
    
begin
    DUT: primo port map(
        x => x,
        y => y
    );

    process
    begin
        for p1 in 0 to 15 loop -- p1 variando de 0 a 15
            x <= std_logic_vector(to_unsigned(p1, 4)); -- Converte p1 para std_logic_vector de 4 bits
            wait for 10 ns; -- Aguarda 10 ns antes da próxima iteração
          end loop; 
          wait; -- Espera indefinidamente após o loop
    end process;
    

end architecture;

prova2/2023-2/q1/work/wave.vcd
$date
  Thu Dec 05 18:45:49 2024
$end
$version
  GHDL v0
$end
$timescale
  1 fs
$end
$scope module standard $end
$upscope $end
$scope module std_logic_1164 $end
$upscope $end
$scope module numeric_std $end
$upscope $end
$scope module primo_tb $end
$var reg 4 ! x[3:0] $end
$var reg 1 " y $end
$scope module dut $end
$var reg 4 # x[3:0] $end
$var reg 1 $ y $end
$var reg 1 % m1 $end
$var reg 1 & m2 $end
$var reg 1 ' m3 $end
$var reg 1 ( m4 $end
$upscope $end
$upscope $end
$enddefinitions $end
#0
b0000 !
0"
b0000 #
0$
0%
0&
0'
0(
#10000000
b0001 !
1"
b0001 #
1$
1%
#20000000
b0010 !
0"
b0010 #
0$
0%
#30000000
b0011 !
1"
b0011 #
1$
1%
1(
#40000000
b0100 !
0"
b0100 #
0$
0%
0(
#50000000
b0101 !
1"
b0101 #
1$
1&
1'
#60000000
b0110 !
0"
b0110 #
0$
0&
0'
#70000000
b0111 !
1"
b0111 #
1$
1&
#80000000
b1000 !
0"
b1000 #
0$
0&
#90000000
b1001 !
b1001 #
#100000000
b1010 !
b1010 #
#110000000
b1011 !
1"
b1011 #
1$
1(
#120000000
b1100 !
0"
b1100 #
0$
0(
#130000000
b1101 !
1"
b1101 #
1$
1'
#140000000
b1110 !
0"
b1110 #
0$
0'
#150000000
b1111 !
b1111 #
