parte3/contador_bin/contador_bin.vhd
library IEEE;
use IEEE.STD_LOGIC_1164.ALL;
use IEEE.NUMERIC_STD.ALL;

entity contador_bin is
    Port (
        clk   : in  STD_LOGIC; -- Clock
        reset : in  STD_LOGIC; -- Reset assíncrono
        count : out STD_LOGIC_VECTOR (3 downto 0) -- Saída do contador
    );
end contador_bin;

architecture Behavioral of contador_bin is
    signal temp_count : UNSIGNED (3 downto 0) := (others => '0'); -- Use UNSIGNED para operações aritméticas
begin
    process (clk, reset)
    begin
        if reset = '1' then
            temp_count <= (others => '0'); -- Reseta o contador
        elsif rising_edge(clk) then
            temp_count <= temp_count + 1; -- Incrementa o contador
        end if;
    end process;

    count <= STD_LOGIC_VECTOR(temp_count); -- Converte para STD_LOGIC_VECTOR para a saída
end architecture;

parte3/contador_bin/contador_bin_tb.vhd
library IEEE;
use IEEE.STD_LOGIC_1164.ALL;

entity contador_bin_tb is
end contador_bin_tb;

architecture Behavioral of contador_bin_tb is
    signal clk   : STD_LOGIC := '0';
    signal reset : STD_LOGIC := '0';
    signal count : STD_LOGIC_VECTOR (3 downto 0);

    component contador_bin
        Port (
            clk   : in  STD_LOGIC;
            reset : in  STD_LOGIC;
            count : out STD_LOGIC_VECTOR (3 downto 0)
        );
    end component;

begin
    uut: contador_bin
        Port map (
            clk => clk,
            reset => reset,
            count => count
        );

    -- Clock Generation
    clk_process: process
    begin
        for i in 0 to 50 loop -- Gera um número limitado de ciclos de clock
            clk <= '0';
            wait for 10 ns;
            clk <= '1';
            wait for 10 ns;
        end loop;
        wait; -- Para o processo após o número definido de ciclos
    end process;

    -- Stimulus Process
    stimulus_process: process
    begin
        -- Reset
        reset <= '1';
        wait for 20 ns;
        reset <= '0';

        -- Reset novamente
        wait for 100 ns;
        reset <= '1';
        wait for 20 ns;
        reset <= '0';

        -- Deixe o contador funcionar por algum tempo
        wait for 500 ns;

        -- Encerrar a simulação
        wait;
    end process;
end architecture;

parte3/contador_bin/work/wave.vcd
$date
  Mon Dec 02 18:55:32 2024
$end
$version
  GHDL v0
$end
$timescale
  1 fs
$end
$scope module standard $end
$upscope $end
$scope module std_logic_1164 $end
$upscope $end
$scope module numeric_std $end
$upscope $end
$scope module contador_bin_tb $end
$var reg 1 ! clk $end
$var reg 1 " reset $end
$var reg 4 # count[3:0] $end
$scope module uut $end
$var reg 1 $ clk $end
$var reg 1 % reset $end
$var reg 4 & count[3:0] $end
$var reg 4 ' temp_count[3:0] $end
$upscope $end
$upscope $end
$enddefinitions $end
#0
0!
1"
b0000 #
0$
1%
b0000 &
b0000 '
#10000000
1!
1$
#20000000
0!
0"
0$
0%
#30000000
1!
b0001 #
1$
b0001 &
b0001 '
#40000000
0!
0$
#50000000
1!
b0010 #
1$
b0010 &
b0010 '
#60000000
0!
0$
#70000000
1!
b0011 #
1$
b0011 &
b0011 '
#80000000
0!
0$
#90000000
1!
b0100 #
1$
b0100 &
b0100 '
#100000000
0!
0$
#110000000
1!
b0101 #
1$
b0101 &
b0101 '
#120000000
0!
1"
b0000 #
0$
1%
b0000 &
b0000 '
#130000000
1!
1$
#140000000
0!
0"
0$
0%
#150000000
1!
b0001 #
1$
b0001 &
b0001 '
#160000000
0!
0$
#170000000
1!
b0010 #
1$
b0010 &
b0010 '
#180000000
0!
0$
#190000000
1!
b0011 #
1$
b0011 &
b0011 '
#200000000
0!
0$
#210000000
1!
b0100 #
1$
b0100 &
b0100 '
#220000000
0!
0$
#230000000
1!
b0101 #
1$
b0101 &
b0101 '
#240000000
0!
0$
#250000000
1!
b0110 #
1$
b0110 &
b0110 '
#260000000
0!
0$
#270000000
1!
b0111 #
1$
b0111 &
b0111 '
#280000000
0!
0$
#290000000
1!
b1000 #
1$
b1000 &
b1000 '
#300000000
0!
0$
#310000000
1!
b1001 #
1$
b1001 &
b1001 '
#320000000
0!
0$
#330000000
1!
b1010 #
1$
b1010 &
b1010 '
#340000000
0!
0$
#350000000
1!
b1011 #
1$
b1011 &
b1011 '
#360000000
0!
0$
#370000000
1!
b1100 #
1$
b1100 &
b1100 '
#380000000
0!
0$
#390000000
1!
b1101 #
1$
b1101 &
b1101 '
#400000000
0!
0$
#410000000
1!
b1110 #
1$
b1110 &
b1110 '
#420000000
0!
0$
#430000000
1!
b1111 #
1$
b1111 &
b1111 '
#440000000
0!
0$
#450000000
1!
b0000 #
1$
b0000 &
b0000 '
#460000000
0!
0$
#470000000
1!
b0001 #
1$
b0001 &
b0001 '
#480000000
0!
0$
#490000000
1!
b0010 #
1$
b0010 &
b0010 '
#500000000
0!
0$
#510000000
1!
b0011 #
1$
b0011 &
b0011 '
#520000000
0!
0$
#530000000
1!
b0100 #
1$
b0100 &
b0100 '
#540000000
0!
0$
#550000000
1!
b0101 #
1$
b0101 &
b0101 '
#560000000
0!
0$
#570000000
1!
b0110 #
1$
b0110 &
b0110 '
#580000000
0!
0$
#590000000
1!
b0111 #
1$
b0111 &
b0111 '
#600000000
0!
0$
#610000000
1!
b1000 #
1$
b1000 &
b1000 '
#620000000
0!
0$
#630000000
1!
b1001 #
1$
b1001 &
b1001 '
#640000000
0!
0$
#650000000
1!
b1010 #
1$
b1010 &
b1010 '
#660000000
0!
0$
#670000000
1!
b1011 #
1$
b1011 &
b1011 '
#680000000
0!
0$
#690000000
1!
b1100 #
1$
b1100 &
b1100 '
#700000000
0!
0$
#710000000
1!
b1101 #
1$
b1101 &
b1101 '
#720000000
0!
0$
#730000000
1!
b1110 #
1$
b1110 &
b1110 '
#740000000
0!
0$
#750000000
1!
b1111 #
1$
b1111 &
b1111 '
#760000000
0!
0$
#770000000
1!
b0000 #
1$
b0000 &
b0000 '
#780000000
0!
0$
#790000000
1!
b0001 #
1$
b0001 &
b0001 '
#800000000
0!
0$
#810000000
1!
b0010 #
1$
b0010 &
b0010 '
#820000000
0!
0$
#830000000
1!
b0011 #
1$
b0011 &
b0011 '
#840000000
0!
0$
#850000000
1!
b0100 #
1$
b0100 &
b0100 '
#860000000
0!
0$
#870000000
1!
b0101 #
1$
b0101 &
b0101 '
#880000000
0!
0$
#890000000
1!
b0110 #
1$
b0110 &
b0110 '
#900000000
0!
0$
#910000000
1!
b0111 #
1$
b0111 &
b0111 '
#920000000
0!
0$
#930000000
1!
b1000 #
1$
b1000 &
b1000 '
#940000000
0!
0$
#950000000
1!
b1001 #
1$
b1001 &
b1001 '
#960000000
0!
0$
#970000000
1!
b1010 #
1$
b1010 &
b1010 '
#980000000
0!
0$
#990000000
1!
b1011 #
1$
b1011 &
b1011 '
#1000000000
0!
0$
#1010000000
1!
b1100 #
1$
b1100 &
b1100 '
