parte2/decoder8-for/decoder8.vhd
library IEEE;  
use IEEE.STD_LOGIC_1164.all;  
use ieee.numeric_std.all;  

entity decoder8 is  
  port (  
    y : out std_logic_vector(7 downto 0); -- vetor de saída de 8 bits  
    x : in std_logic_vector(2 downto 0); -- vetor de entrada de 3 bits  
    E : in std_logic -- sinal de habilitação  
  );  
end entity;  

architecture simple of decoder8 is  
begin  
  process (x, E)  
  begin  
    if E = '0' then  
      y <= std_logic_vector(to_unsigned(0, 7)); -- se E for '0', todas as saídas são '0'  
    else  
      y <= (others => '0'); -- inicializa todas as saídas como '0'  
      for i in 0 to 7 loop  
        if x = std_logic_vector(to_unsigned(i, 3)) then  
          y(i) <= '1'; -- ativa a saída correspondente ao valor de x  
        end if;  
      end loop;  
    end if;  
  end process;  
end architecture;

parte2/decoder8-for/decoder8_tb.vhd
library IEEE;
use IEEE.STD_LOGIC_1164.ALL;
use ieee.numeric_std.all; 

entity decoder8_tb is
end decoder8_tb;

architecture Behavioral of decoder8_tb is
    component decoder8
        Port ( 
            x : in STD_LOGIC_VECTOR(2 downto 0);
            E : in STD_LOGIC;
            y : out STD_LOGIC_VECTOR(7 downto 0)
        );
    end component;
    
    signal x : STD_LOGIC_VECTOR(2 downto 0);
    signal E : STD_LOGIC;
    signal y : STD_LOGIC_VECTOR(7 downto 0);

begin
    uut: decoder8 port map (
        x => x,
        E => E,
        y => y
    );

    stim_proc: process
    begin
        for p1 in 0 to 7 loop -- p1 variando de 0 a 7
            x <= std_logic_vector(to_unsigned(p1, 3));
            wait for 10 ns;
        end loop;
        wait;
    end process;  
end Behavioral;

parte2/decoder8-for/work/wave.vcd
$date
  Mon Dec 02 16:48:12 2024
$end
$version
  GHDL v0
$end
$timescale
  1 fs
$end
$scope module standard $end
$upscope $end
$scope module std_logic_1164 $end
$upscope $end
$scope module numeric_std $end
$upscope $end
$scope module decoder8_tb $end
$var reg 3 ! x[2:0] $end
$var reg 1 " e $end
$var reg 8 # y[7:0] $end
$scope module uut $end
$var reg 8 $ y[7:0] $end
$var reg 3 % x[2:0] $end
$var reg 1 & e $end
$upscope $end
$upscope $end
$enddefinitions $end
#0
b000 !
U"
b00000001 #
b00000001 $
b000 %
U&
#10000000
b001 !
b00000010 #
b00000010 $
b001 %
#20000000
b010 !
b00000100 #
b00000100 $
b010 %
#30000000
b011 !
b00001000 #
b00001000 $
b011 %
#40000000
b100 !
b00010000 #
b00010000 $
b100 %
#50000000
b101 !
b00100000 #
b00100000 $
b101 %
#60000000
b110 !
b01000000 #
b01000000 $
b110 %
#70000000
b111 !
b10000000 #
b10000000 $
b111 %
