parte2/decoder8-for/decoder8.vhd
library IEEE;  
use IEEE.STD_LOGIC_1164.all;  
use ieee.numeric_std.all;  

entity decoder8 is  
  port (  
    y : out std_logic_vector(7 downto 0); -- vetor de saída de 8 bits  
    x : in std_logic_vector(2 downto 0); -- vetor de entrada de 3 bits  
    E : in std_logic -- sinal de habilitação  
  );  
end entity;  

architecture simple of decoder8 is  
begin  
  process (x, E)  
  begin  
    if E = '0' then  
      y <= (others => '0'); -- se E for '0', todas as saídas são '0'  
    else  
      y <= (others => '0'); -- inicializa todas as saídas como '0'  
      if to_integer(unsigned(x)) < 8 then  
        y(to_integer(unsigned(x))) <= '1'; -- ativa a saída correspondente ao valor de x  
      end if;  
    end if;  
  end process;  
end architecture;

parte2/decoder8-for/decoder8_tb.vhd
library IEEE;
use IEEE.STD_LOGIC_1164.ALL;
use ieee.numeric_std.all; 

entity decoder8_tb is
end decoder8_tb;

architecture simple of decoder8_tb is
    component decoder8
        Port ( 
            x : in STD_LOGIC_VECTOR(2 downto 0);
            E : in STD_LOGIC;
            y : out STD_LOGIC_VECTOR(7 downto 0)
        );
    end component;
    
    signal x : STD_LOGIC_VECTOR(2 downto 0);
    signal E : STD_LOGIC;
    signal y : STD_LOGIC_VECTOR(7 downto 0);

begin
    uut: decoder8 port map (
        x => x,
        E => E,
        y => y
    );

    stim_proc: process
    begin
        E <= '0'; -- Desabilita o decoder
        wait for 10 ns; -- Aguarda um tempo após desabilitar
        
        E <= '1'; -- Habilita o decoder
        for p1 in 0 to 7 loop -- p1 variando de 0 a 7
            x <= std_logic_vector(to_unsigned(p1, 3));
            wait for 10 ns;
        end loop;
        
        E <= '0'; -- Desabilita o decoder
        wait for 10 ns; -- Aguarda um tempo após desabilitar
        wait;
    end process;  
end architecture;

parte2/decoder8-for/work/wave.vcd
$date
  Tue Dec 03 13:58:35 2024
$end
$version
  GHDL v0
$end
$timescale
  1 fs
$end
$scope module standard $end
$upscope $end
$scope module std_logic_1164 $end
$upscope $end
$scope module numeric_std $end
$upscope $end
$scope module decoder8_tb $end
$var reg 3 ! x[2:0] $end
$var reg 1 " e $end
$var reg 8 # y[7:0] $end
$scope module uut $end
$var reg 8 $ y[7:0] $end
$var reg 3 % x[2:0] $end
$var reg 1 & e $end
$upscope $end
$upscope $end
$enddefinitions $end
#0
bUUU !
0"
b00000000 #
b00000000 $
bUUU %
0&
#10000000
b000 !
1"
b00000001 #
b00000001 $
b000 %
1&
#20000000
b001 !
b00000010 #
b00000010 $
b001 %
#30000000
b010 !
b00000100 #
b00000100 $
b010 %
#40000000
b011 !
b00001000 #
b00001000 $
b011 %
#50000000
b100 !
b00010000 #
b00010000 $
b100 %
#60000000
b101 !
b00100000 #
b00100000 $
b101 %
#70000000
b110 !
b01000000 #
b01000000 $
b110 %
#80000000
b111 !
b10000000 #
b10000000 $
b111 %
#90000000
0"
b00000000 #
b00000000 $
0&
