parte2/majority_detector/majority4.vhd
library IEEE;
use IEEE.STD_LOGIC_1164.ALL;

entity majority4 is
    Port ( 
        x : in STD_LOGIC_VECTOR(3 downto 0);
        y : out STD_LOGIC
    );
end majority4;

architecture Behavioral of majority4 is
begin
    process(x)
        variable count : integer range 0 to 4;
    begin
        count := 0;
        
        for i in 0 to 3 loop
            if x(i) = '1' then
                count := count + 1;
            end if;
        end loop;
        
        if count > 2 then
            y <= '1';
        else
            y <= '0';
        end if;
    end process;
end Behavioral;

parte2/majority_detector/majority4_tb.vhd
library IEEE;
use IEEE.STD_LOGIC_1164.ALL;

entity majority4_tb is
end majority4_tb;

architecture Behavioral of majority4_tb is
    component majority4
        Port ( 
            x : in STD_LOGIC_VECTOR(3 downto 0);
            y : out STD_LOGIC
        );
    end component;
    
    signal x : STD_LOGIC_VECTOR(3 downto 0);
    signal y : STD_LOGIC;

begin
    uut: majority4 port map (
        x => x,
        y => y
    );

    stim_proc: process
    begin
        -- Test all possible combinations
        x <= "0000"; wait for 10 ns; -- Should output 0
        x <= "0001"; wait for 10 ns; -- Should output 0
        x <= "0011"; wait for 10 ns; -- Should output 0
        x <= "0111"; wait for 10 ns; -- Should output 1
        x <= "1111"; wait for 10 ns; -- Should output 1
        x <= "1110"; wait for 10 ns; -- Should output 1
        x <= "1100"; wait for 10 ns; -- Should output 0
        x <= "1010"; wait for 10 ns; -- Should output 0
        x <= "1011"; wait for 10 ns; -- Should output 1
        
        wait;
    end process;
end Behavioral;

parte2/majority_detector/work/wave.vcd
$date
  Thu Nov 28 01:27:10 2024
$end
$version
  GHDL v0
$end
$timescale
  1 fs
$end
$scope module standard $end
$upscope $end
$scope module std_logic_1164 $end
$upscope $end
$scope module majority4_tb $end
$var reg 4 ! x[3:0] $end
$var reg 1 " y $end
$scope module uut $end
$var reg 4 # x[3:0] $end
$var reg 1 $ y $end
$upscope $end
$upscope $end
$enddefinitions $end
#0
b0000 !
0"
b0000 #
0$
#10000000
b0001 !
b0001 #
#20000000
b0011 !
b0011 #
#30000000
b0111 !
1"
b0111 #
1$
#40000000
b1111 !
b1111 #
#50000000
b1110 !
b1110 #
#60000000
b1100 !
0"
b1100 #
0$
#70000000
b1010 !
b1010 #
#80000000
b1011 !
1"
b1011 #
1$
