parte2/detector-raw/detector.vhd
library IEEE;
use IEEE.STD_LOGIC_1164.all;

entity detector is
    port (
       x : in std_logic_vector (3 downto 0); -- vetor de entrada de 4 bits
       y : out std_logic -- saída de 1 bit
        
    );
end entity;

architecture simple of detector is

begin
    process (x)
        variable  count : integer range 0 to 4; -- variável para contar os bits '1'
    begin
        count := 0; -- inicializa o contador
---------------- incrementa o contador se o bit for '1' ----------------
        for i in 0 to 3 loop
            if x(i)= '1' then
                count := count + 1; -- incrementa o contador se o bit atual for '1'
            end if;
        end loop;
------------------------------------------------------------------------


----------- se houver mais de 2 bits '1', a saída é '1' ----------------
        if count > 2 then
            y <= '1'; -- se o contador for maior que 2, a saída é '1'
        else
            y <= '0'; -- caso contrário, a saída é '0'
        end if;
------------------------------------------------------------------------
    end process;

end architecture;

parte2/detector-raw/detector_tb.vhd
library IEEE;
use IEEE.STD_LOGIC_1164.all;

entity detector_tb is
end entity;

architecture simple of detector_tb is
  component detector
    port (
      x : in std_logic_vector(3 downto 0);
      y : out std_logic
    );
  end component;

  signal x : std_logic_vector(3 downto 0);
  signal y : std_logic;
  

begin

  uut : detector port map(
    x => x,
    y => y
  );

  stim_proc: process
  begin
    x <= "0000"; 
    wait for 10 ns;
    x <= "0001"; 
    wait for 10 ns;
    x <= "0010"; 
    wait for 10 ns;
    x <= "0011"; 
    wait for 10 ns;
    x <= "0100"; 
    wait for 10 ns;
    x <= "0101"; 
    wait for 10 ns;
    x <= "0110"; 
    wait for 10 ns;
    x <= "0111"; 
    wait for 10 ns;
    x <= "1000"; 
    wait for 10 ns;
    x <= "1001"; 
    wait for 10 ns;
    x <= "1010"; 
    wait for 10 ns;
    x <= "1011"; 
    wait for 10 ns;
    x <= "1100"; 
    wait for 10 ns;
    x <= "1101"; 
    wait for 10 ns;
    x <= "1110"; 
    wait for 10 ns;
    x <= "1111"; 
    wait for 10 ns;
    wait;
  end process;

end architecture;

parte2/detector-raw/work/wave.vcd
$date
  Mon Dec 02 16:52:21 2024
$end
$version
  GHDL v0
$end
$timescale
  1 fs
$end
$scope module standard $end
$upscope $end
$scope module std_logic_1164 $end
$upscope $end
$scope module detector_tb $end
$var reg 4 ! x[3:0] $end
$var reg 1 " y $end
$scope module uut $end
$var reg 4 # x[3:0] $end
$var reg 1 $ y $end
$upscope $end
$upscope $end
$enddefinitions $end
#0
b0000 !
0"
b0000 #
0$
#10000000
b0001 !
b0001 #
#20000000
b0010 !
b0010 #
#30000000
b0011 !
b0011 #
#40000000
b0100 !
b0100 #
#50000000
b0101 !
b0101 #
#60000000
b0110 !
b0110 #
#70000000
b0111 !
1"
b0111 #
1$
#80000000
b1000 !
0"
b1000 #
0$
#90000000
b1001 !
b1001 #
#100000000
b1010 !
b1010 #
#110000000
b1011 !
1"
b1011 #
1$
#120000000
b1100 !
0"
b1100 #
0$
#130000000
b1101 !
1"
b1101 #
1$
#140000000
b1110 !
b1110 #
#150000000
b1111 !
b1111 #
