parte1/q4_v1/q4_v1.vhd
library ieee;
use ieee.std_logic_1164.all;

entity q4_v1 is
  port (
    i0 : in std_logic;
    i1 : in std_logic;
    i2 : in std_logic;
    i3 : in std_logic;
    s  : out std_logic
  );
end q4_v1;

architecture simple of q4_v1 is
  signal m1, m2, m3, m4, m5, m6 : std_logic;
begin
  m1 <= (not i0 and not i1 and i2 and i3);
  m2 <= (not i0 and i1 and not i2 and i3);
  m3 <= (not i0 and i1 and i2 and not i3);
  m4 <= (i0 and i1 and not i2 and not i3);
  m5 <= (i0 and not i1 and not i2 and i3);
  m6 <= (i0 and not i1 and i2 and not i3);
  s  <= m1 or m2 or m3 or m4 or m5 or m6;

end architecture;

parte1/q4_v1/q4_v1_tb.vhd
library ieee;
use ieee.std_logic_1164.all;

entity q4_v1_tb is
end q4_v1_tb;

architecture simple of q4_v1_tb is
  -- Declaração do componente a ser testado
  component q4_v1
    port (
      i0, i1, i2, i3 : in std_logic;
      s              : out std_logic
    );
  end component;

  -- Declaração de sinais para interconexão
  signal i0, i1, i2, i3 : std_logic;
  signal s              : std_logic;
begin
    -- Instanciação do componente
    dut : q4_v1 port map (
      i0 => i0,
      i1 => i1,
      i2 => i2,
      i3 => i3,
      s  => s
    );

    process
    begin
      -- Caso de teste 1
      i0 <= '0';
      i1 <= '0';
      i2 <= '0';
      i3 <= '0';
      wait for 10 ns;

      -- Caso de teste 2
      i0 <= '0';
      i1 <= '0';
      i2 <= '0';
      i3 <= '1';
      wait for 10 ns;

      -- Caso de teste 3
      i0 <= '0';
      i1 <= '0';
      i2 <= '1';
      i3 <= '0';
      wait for 10 ns;

      -- Caso de teste 4
      i0 <= '0';
      i1 <= '0';
      i2 <= '1';
      i3 <= '1';
      wait for 10 ns;

      -- Caso de teste 5
      i0 <= '0';
      i1 <= '1';
      i2 <= '0';
      i3 <= '0';
      wait for 10 ns;

      -- Caso de teste 6
      i0 <= '0';
      i1 <= '1';
      i2 <= '0';
      i3 <= '1';
      wait for 10 ns;

      -- Caso de teste 7
      i0 <= '0';
      i1 <= '1';
      i2 <= '1';
      i3 <= '0';
      wait for 10 ns;

      -- Caso de teste 8
      i0 <= '0';
      i1 <= '1';
      i2 <= '1';
      i3 <= '1';
      wait for 10 ns;

      -- Caso de teste 9
      i0 <= '1';
      i1 <= '0';
      i2 <= '0';
      i3 <= '0';
      wait for 10 ns;

      -- Caso de teste 10
      i0 <= '1';
      i1 <= '0';
      i2 <= '0';
      i3 <= '1';
      wait for 10 ns;

      -- Caso de teste 11
      i0 <= '1';
      i1 <= '0';
      i2 <= '1';
      i3 <= '0';
      wait for 10 ns;

      -- Caso de teste 12
      i0 <= '1';
      i1 <= '0';
      i2 <= '1';
      i3 <= '1';
      wait for 10 ns;

      -- Caso de teste 13
      i0 <= '1';
      i1 <= '1';
      i2 <= '0';
      i3 <= '0';
      wait for 10 ns;

      -- Caso de teste 14
      i0 <= '1';
      i1 <= '1';
      i2 <= '0';
      i3 <= '1';
      wait for 10 ns;

      -- Caso de teste 15
      i0 <= '1';
      i1 <= '1';
      i2 <= '1';
      i3 <= '0';
      wait for 10 ns;

      -- Caso de teste 16
      i0 <= '1';
      i1 <= '1';
      i2 <= '1';
      i3 <= '1';
      wait for 10 ns;

      -- Finaliza o processo
      wait;
    end process;
end architecture;

parte1/q4_v1/work/wave.vcd
$date
  Thu Nov 28 15:21:39 2024
$end
$version
  GHDL v0
$end
$timescale
  1 fs
$end
$scope module standard $end
$upscope $end
$scope module std_logic_1164 $end
$upscope $end
$scope module q4_v1_tb $end
$var reg 1 ! i0 $end
$var reg 1 " i1 $end
$var reg 1 # i2 $end
$var reg 1 $ i3 $end
$var reg 1 % s $end
$scope module dut $end
$var reg 1 & i0 $end
$var reg 1 ' i1 $end
$var reg 1 ( i2 $end
$var reg 1 ) i3 $end
$var reg 1 * s $end
$var reg 1 + m1 $end
$var reg 1 , m2 $end
$var reg 1 - m3 $end
$var reg 1 . m4 $end
$var reg 1 / m5 $end
$var reg 1 0 m6 $end
$upscope $end
$upscope $end
$enddefinitions $end
#0
0!
0"
0#
0$
0%
0&
0'
0(
0)
0*
0+
0,
0-
0.
0/
00
#10000000
1$
1)
#20000000
1#
0$
1(
0)
#30000000
1$
1%
1)
1*
1+
#40000000
1"
0#
0$
0%
1'
0(
0)
0*
0+
#50000000
1$
1%
1)
1*
1,
#60000000
1#
0$
1(
0)
0,
1-
#70000000
1$
0%
1)
0*
0-
#80000000
1!
0"
0#
0$
1&
0'
0(
0)
#90000000
1$
1%
1)
1*
1/
#100000000
1#
0$
1(
0)
0/
10
#110000000
1$
0%
1)
0*
00
#120000000
1"
0#
0$
1%
1'
0(
0)
1*
1.
#130000000
1$
0%
1)
0*
0.
#140000000
1#
0$
1(
0)
#150000000
1$
1)
