parte3/reg_nbits/reg_nbits.vhd
library IEEE;
use IEEE.STD_LOGIC_1164.ALL;
use IEEE.NUMERIC_STD.ALL;

entity reg_nbits is
    generic (
        N : integer := 16
    );
    port (
        clk   : in std_logic;
        reset : in std_logic;
        clr   : in std_logic;
        inv   : in std_logic;
        d     : in std_logic;
        q     : out std_logic_vector(N-1 downto 0)
    );
end entity;

architecture simple of reg_nbits is
    signal reg : std_logic_vector(N-1 downto 0) := (others => '0');
begin
    process(clk, reset)
    begin
        if reset = '1' then
            reg <= (others => '0');
        elsif rising_edge(clk) then
            if clr = '1' then
                reg <= (others => '0');
            elsif inv = '1' then
                reg <= not reg;
            else
                reg <= reg(N-2 downto 0) & d;
            end if;
        end if;
    end process;
    
    q <= reg;
end architecture;

parte3/reg_nbits/reg_nbits_tb.vhd
library IEEE;
use IEEE.STD_LOGIC_1164.ALL;
use IEEE.NUMERIC_STD.ALL;

entity reg_nbits_tb is
end reg_nbits_tb;

architecture simple of reg_nbits_tb is
    constant N : integer := 16;

    component reg_nbits is
        generic (
            N : integer := 8
        );
        port (
            clk   : in std_logic;
            reset : in std_logic;
            clr   : in std_logic;
            inv   : in std_logic;
            d     : in std_logic;
            q     : out std_logic_vector(N-1 downto 0)
        );
    end component;

    constant CLK_PERIOD : time := 10 ns;
    signal clk   : std_logic := '0';
    signal reset : std_logic := '0';
    signal clr   : std_logic := '0';
    signal inv   : std_logic := '0';
    signal d     : std_logic := '0';
    signal q     : std_logic_vector(N-1 downto 0);

begin
    DUT: reg_nbits
        generic map (
            N => N
        )
        port map (
            clk   => clk,
            reset => reset,
            clr   => clr,
            inv   => inv,
            d     => d,
            q     => q
        );

    -- Clock generation
    clk <= not clk after CLK_PERIOD/2;

    process
    begin
        -- Test 1: Reset
        reset <= '1';
        wait for CLK_PERIOD*2;
        reset <= '0';

        -- Test 2: Data shifting
        for i in 0 to 7 loop
            d <= '1';
            wait for CLK_PERIOD;
            d <= '0';
            wait for CLK_PERIOD;
        end loop;
        -- End simulation
        wait for CLK_PERIOD*5;
        assert false report "End of simulation" severity failure;
    end process;

end architecture;

parte3/reg_nbits/work/wave.vcd
$date
  Fri Dec 06 16:53:51 2024
$end
$version
  GHDL v0
$end
$timescale
  1 fs
$end
$scope module standard $end
$upscope $end
$scope module std_logic_1164 $end
$upscope $end
$scope module numeric_std $end
$upscope $end
$scope module reg_nbits_tb $end
$var reg 1 ! clk $end
$var reg 1 " reset $end
$var reg 1 # clr $end
$var reg 1 $ inv $end
$var reg 1 % d $end
$var reg 16 & q[15:0] $end
$scope module dut $end
$var reg 1 ' clk $end
$var reg 1 ( reset $end
$var reg 1 ) clr $end
$var reg 1 * inv $end
$var reg 1 + d $end
$var reg 16 , q[15:0] $end
$var reg 16 - reg[15:0] $end
$upscope $end
$upscope $end
$enddefinitions $end
#0
0!
1"
0#
0$
0%
b0000000000000000 &
0'
1(
0)
0*
0+
b0000000000000000 ,
b0000000000000000 -
#5000000
1!
1'
#10000000
0!
0'
#15000000
1!
1'
#20000000
0!
0"
1%
0'
0(
1+
#25000000
1!
b0000000000000001 &
1'
b0000000000000001 ,
b0000000000000001 -
#30000000
0!
0%
0'
0+
#35000000
1!
b0000000000000010 &
1'
b0000000000000010 ,
b0000000000000010 -
#40000000
0!
1%
0'
1+
#45000000
1!
b0000000000000101 &
1'
b0000000000000101 ,
b0000000000000101 -
#50000000
0!
0%
0'
0+
#55000000
1!
b0000000000001010 &
1'
b0000000000001010 ,
b0000000000001010 -
#60000000
0!
1%
0'
1+
#65000000
1!
b0000000000010101 &
1'
b0000000000010101 ,
b0000000000010101 -
#70000000
0!
0%
0'
0+
#75000000
1!
b0000000000101010 &
1'
b0000000000101010 ,
b0000000000101010 -
#80000000
0!
1%
0'
1+
#85000000
1!
b0000000001010101 &
1'
b0000000001010101 ,
b0000000001010101 -
#90000000
0!
0%
0'
0+
#95000000
1!
b0000000010101010 &
1'
b0000000010101010 ,
b0000000010101010 -
#100000000
0!
1%
0'
1+
#105000000
1!
b0000000101010101 &
1'
b0000000101010101 ,
b0000000101010101 -
#110000000
0!
0%
0'
0+
#115000000
1!
b0000001010101010 &
1'
b0000001010101010 ,
b0000001010101010 -
#120000000
0!
1%
0'
1+
#125000000
1!
b0000010101010101 &
1'
b0000010101010101 ,
b0000010101010101 -
#130000000
0!
0%
0'
0+
#135000000
1!
b0000101010101010 &
1'
b0000101010101010 ,
b0000101010101010 -
#140000000
0!
1%
0'
1+
#145000000
1!
b0001010101010101 &
1'
b0001010101010101 ,
b0001010101010101 -
#150000000
0!
0%
0'
0+
#155000000
1!
b0010101010101010 &
1'
b0010101010101010 ,
b0010101010101010 -
#160000000
0!
1%
0'
1+
#165000000
1!
b0101010101010101 &
1'
b0101010101010101 ,
b0101010101010101 -
#170000000
0!
0%
0'
0+
#175000000
1!
b1010101010101010 &
1'
b1010101010101010 ,
b1010101010101010 -
#180000000
0!
0'
#185000000
1!
b0101010101010100 &
1'
b0101010101010100 ,
b0101010101010100 -
#190000000
0!
0'
#195000000
1!
b1010101010101000 &
1'
b1010101010101000 ,
b1010101010101000 -
#200000000
0!
0'
#205000000
1!
b0101010101010000 &
1'
b0101010101010000 ,
b0101010101010000 -
#210000000
0!
0'
#215000000
1!
b1010101010100000 &
1'
b1010101010100000 ,
b1010101010100000 -
#220000000
0!
0'
#225000000
1!
b0101010101000000 &
1'
b0101010101000000 ,
b0101010101000000 -
