parte2/decoder8/decoder8.vhd
library IEEE;
use IEEE.STD_LOGIC_1164.all;

entity decoder8 is
  port (
    y : out std_logic_vector(7 downto 0);
    x : in std_logic_vector(2 downto 0);
    E : in std_logic
  );
end entity;

architecture simple of decoder8 is
begin
  process (x, E)
  begin
    if E = '0' then
      y <= "00000000";
    else
      case x is
        when "000"  => y  <= "00000001";
        when "001"  => y  <= "00000010";
        when "010"  => y  <= "00000100";
        when "011"  => y  <= "00001000";
        when "100"  => y  <= "00010000";
        when "101"  => y  <= "00100000";
        when "110"  => y  <= "01000000";
        when "111"  => y  <= "10000000";
        when others => y <= "00000000";
      end case;
    end if;
  end process;
end architecture;

parte2/decoder8/decoder8_tb.vhd
library IEEE;
use IEEE.STD_LOGIC_1164.ALL;

entity decoder8_tb is
end decoder8_tb;

architecture Behavioral of decoder8_tb is
    component decoder8
        Port ( 
            x : in STD_LOGIC_VECTOR(2 downto 0);
            E : in STD_LOGIC;
            y : out STD_LOGIC_VECTOR(7 downto 0)
        );
    end component;
    
    signal x : STD_LOGIC_VECTOR(2 downto 0);
    signal E : STD_LOGIC;
    signal y : STD_LOGIC_VECTOR(7 downto 0);

begin
    uut: decoder8 port map (
        x => x,
        E => E,
        y => y
    );

    stim_proc: process
    begin
        -- Test with E = 0 (disabled)
        E <= '0';
        x <= "000";
        wait for 10 ns;
        
        -- Test with E = 1 (enabled)
        E <= '1';
        
        -- Test all input combinations
        x <= "000";
        wait for 10 ns;
        x <= "001";
        wait for 10 ns;
        x <= "010";
        wait for 10 ns;
        x <= "011";
        wait for 10 ns;
        x <= "100";
        wait for 10 ns;
        x <= "101";
        wait for 10 ns;
        x <= "110";
        wait for 10 ns;
        x <= "111";
        wait for 10 ns;
        
        wait;
    end process;
end Behavioral;

parte2/decoder8/work/wave.vcd
$date
  Mon Dec 02 16:14:33 2024
$end
$version
  GHDL v0
$end
$timescale
  1 fs
$end
$scope module standard $end
$upscope $end
$scope module std_logic_1164 $end
$upscope $end
$scope module decoder8_tb $end
$var reg 3 ! x[2:0] $end
$var reg 1 " e $end
$var reg 8 # y[7:0] $end
$scope module uut $end
$var reg 8 $ y[7:0] $end
$var reg 3 % x[2:0] $end
$var reg 1 & e $end
$upscope $end
$upscope $end
$enddefinitions $end
#0
b000 !
0"
b00000000 #
b00000000 $
b000 %
0&
#10000000
1"
b00000001 #
b00000001 $
1&
#20000000
b001 !
b00000010 #
b00000010 $
b001 %
#30000000
b010 !
b00000100 #
b00000100 $
b010 %
#40000000
b011 !
b00001000 #
b00001000 $
b011 %
#50000000
b100 !
b00010000 #
b00010000 $
b100 %
#60000000
b101 !
b00100000 #
b00100000 $
b101 %
#70000000
b110 !
b01000000 #
b01000000 $
b110 %
#80000000
b111 !
b10000000 #
b10000000 $
b111 %
