prova2/2024-1/q2/q2.vhd
library ieee;
use ieee.std_logic_1164.all;
use ieee.numeric_std.all;

entity q2 is
  port (
    clk   : in std_logic;
    reset : in std_logic;

    x : out std_logic_vector(2 downto 0)
  );
end entity;

architecture q2 of q2 is
  signal Q  : std_logic_vector(2 downto 0) := "000";
  signal x3 : std_logic;
begin
  x3 <= (Q(0) xor Q(1)) xor (Q(2) nor Q(1));
  x  <= Q;

  process (clk, reset)
  begin
    if reset = '1' then
      Q <= "000";
    elsif rising_edge(clk) then
      Q(2) <= x3;
      Q(1) <= Q(2);
      Q(0) <= Q(1);
    end if;
  end process;
end architecture;

prova2/2024-1/q2/q2_tb.vhd
library ieee;
use ieee.std_logic_1164.all;
use ieee.numeric_std.all;

entity q2_tb is
end entity;

architecture simple of q2_tb is
  component q2 is
    port (
      clk   : in std_logic;
      reset : in std_logic;
      x     : out std_logic_vector (2 downto 0)
    );
  end component;

  signal clk   : std_logic                     := '0';
  signal reset : std_logic                     := '0';
  signal x     : std_logic_vector (2 downto 0) := "000";

begin

  reset <= '0', '1' after 30 ns, '0' after 50 ns;
  clk   <= not clk after 10 ns;

  uut : q2
  port map
  (
    clk   => clk,
    reset => reset,
    x     => x
  );

end architecture;

prova2/2024-1/q2/work/wave.vcd
$date
  Fri Dec 13 09:10:04 2024
$end
$version
  GHDL v0
$end
$timescale
  1 fs
$end
$scope module standard $end
$upscope $end
$scope module std_logic_1164 $end
$upscope $end
$scope module numeric_std $end
$upscope $end
$scope module q2_tb $end
$var reg 1 ! clk $end
$var reg 1 " reset $end
$var reg 3 # x[2:0] $end
$scope module uut $end
$var reg 1 $ clk $end
$var reg 1 % reset $end
$var reg 3 & x[2:0] $end
$var reg 3 ' q[2:0] $end
$var reg 1 ( x3 $end
$upscope $end
$upscope $end
$enddefinitions $end
#0
0!
0"
b000 #
0$
0%
b000 &
b000 '
1(
#10000000
1!
b100 #
1$
b100 &
b100 '
0(
#20000000
0!
0$
#30000000
1!
1"
b000 #
1$
1%
b000 &
b000 '
1(
#40000000
0!
0$
#50000000
1!
0"
b100 #
1$
0%
b100 &
b100 '
0(
#60000000
0!
0$
#70000000
1!
b010 #
1$
b010 &
b010 '
1(
#80000000
0!
0$
#90000000
1!
b101 #
1$
b101 &
b101 '
#100000000
0!
0$
#110000000
1!
b110 #
1$
b110 &
b110 '
#120000000
0!
0$
#130000000
1!
b111 #
1$
b111 &
b111 '
0(
#140000000
0!
0$
#150000000
1!
b011 #
1$
b011 &
b011 '
#160000000
0!
0$
#170000000
1!
b001 #
1$
b001 &
b001 '
#180000000
0!
0$
#190000000
1!
b000 #
1$
b000 &
b000 '
1(
#200000000
0!
0$
#210000000
1!
b100 #
1$
b100 &
b100 '
0(
#220000000
0!
0$
#230000000
1!
b010 #
1$
b010 &
b010 '
1(
#240000000
0!
0$
#250000000
1!
b101 #
1$
b101 &
b101 '
#260000000
0!
0$
#270000000
1!
b110 #
1$
b110 &
b110 '
#280000000
0!
0$
#290000000
1!
b111 #
1$
b111 &
b111 '
0(
#300000000
0!
0$
#310000000
1!
b011 #
1$
b011 &
b011 '
#320000000
0!
0$
#330000000
1!
b001 #
1$
b001 &
b001 '
#340000000
0!
0$
#350000000
1!
b000 #
1$
b000 &
b000 '
1(
#360000000
0!
0$
#370000000
1!
b100 #
1$
b100 &
b100 '
0(
#380000000
0!
0$
#390000000
1!
b010 #
1$
b010 &
b010 '
1(
#400000000
0!
0$
#410000000
1!
b101 #
1$
b101 &
b101 '
#420000000
0!
0$
#430000000
1!
b110 #
1$
b110 &
b110 '
#440000000
0!
0$
#450000000
1!
b111 #
1$
b111 &
b111 '
0(
#460000000
0!
0$
#470000000
1!
b011 #
1$
b011 &
b011 '
#480000000
0!
0$
#490000000
1!
b001 #
1$
b001 &
b001 '
#500000000
0!
0$
#510000000
1!
b000 #
1$
b000 &
b000 '
1(
#520000000
0!
0$
#530000000
1!
b100 #
1$
b100 &
b100 '
0(
#540000000
0!
0$
#550000000
1!
b010 #
1$
b010 &
b010 '
1(
#560000000
0!
0$
#570000000
1!
b101 #
1$
b101 &
b101 '
#580000000
0!
0$
#590000000
1!
b110 #
1$
b110 &
b110 '
#600000000
0!
0$
#610000000
1!
b111 #
1$
b111 &
b111 '
0(
#620000000
0!
0$
#630000000
1!
b011 #
1$
b011 &
b011 '
#640000000
0!
0$
#650000000
1!
b001 #
1$
b001 &
b001 '
#660000000
0!
0$
#670000000
1!
b000 #
1$
b000 &
b000 '
1(
#680000000
0!
0$
#690000000
1!
b100 #
1$
b100 &
b100 '
0(
#700000000
0!
0$
#710000000
1!
b010 #
1$
b010 &
b010 '
1(
#720000000
0!
0$
#730000000
1!
b101 #
1$
b101 &
b101 '
#740000000
0!
0$
#750000000
1!
b110 #
1$
b110 &
b110 '
#760000000
0!
0$
#770000000
1!
b111 #
1$
b111 &
b111 '
0(
#780000000
0!
0$
#790000000
1!
b011 #
1$
b011 &
b011 '
#800000000
0!
0$
#810000000
1!
b001 #
1$
b001 &
b001 '
#820000000
0!
0$
#830000000
1!
b000 #
1$
b000 &
b000 '
1(
#840000000
0!
0$
#850000000
1!
b100 #
1$
b100 &
b100 '
0(
#860000000
0!
0$
#870000000
1!
b010 #
1$
b010 &
b010 '
1(
#880000000
0!
0$
#890000000
1!
b101 #
1$
b101 &
b101 '
#900000000
0!
0$
#910000000
1!
b110 #
1$
b110 &
b110 '
#920000000
0!
0$
#930000000
1!
b111 #
1$
b111 &
b111 '
0(
#940000000
0!
0$
#950000000
1!
b011 #
1$
b011 &
b011 '
#960000000
0!
0$
#970000000
1!
b001 #
1$
b001 &
b001 '
#980000000
0!
0$
#990000000
1!
b000 #
1$
b000 &
b000 '
1(
#1000000000
0!
0$
#1010000000
1!
b100 #
1$
b100 &
b100 '
0(
#1020000000
0!
0$
#1030000000
1!
b010 #
1$
b010 &
b010 '
1(
#1040000000
0!
0$
#1050000000
1!
b101 #
1$
b101 &
b101 '
#1060000000
0!
0$
#1070000000
1!
b110 #
1$
b110 &
b110 '
#1080000000
0!
0$
#1090000000
1!
b111 #
1$
b111 &
b111 '
0(
#1100000000
0!
0$
#1110000000
1!
b011 #
1$
b011 &
b011 '
#1120000000
0!
0$
#1130000000
1!
b001 #
1$
b001 &
b001 '
#1140000000
0!
0$
#1150000000
1!
b000 #
1$
b000 &
b000 '
1(
#1160000000
0!
0$
#1170000000
1!
b100 #
1$
b100 &
b100 '
0(
#1180000000
0!
0$
#1190000000
1!
b010 #
1$
b010 &
b010 '
1(
#1200000000
0!
0$
#1210000000
1!
b101 #
1$
b101 &
b101 '
#1220000000
0!
0$
#1230000000
1!
b110 #
1$
b110 &
b110 '
#1240000000
0!
0$
#1250000000
1!
b111 #
1$
b111 &
b111 '
0(
#1260000000
0!
0$
#1270000000
1!
b011 #
1$
b011 &
b011 '
#1280000000
0!
0$
#1290000000
1!
b001 #
1$
b001 &
b001 '
#1300000000
0!
0$
#1310000000
1!
b000 #
1$
b000 &
b000 '
1(
#1320000000
0!
0$
#1330000000
1!
b100 #
1$
b100 &
b100 '
0(
#1340000000
0!
0$
#1350000000
1!
b010 #
1$
b010 &
b010 '
1(
#1360000000
0!
0$
#1370000000
1!
b101 #
1$
b101 &
b101 '
#1380000000
0!
0$
#1390000000
1!
b110 #
1$
b110 &
b110 '
#1400000000
0!
0$
#1410000000
1!
b111 #
1$
b111 &
b111 '
0(
#1420000000
0!
0$
#1430000000
1!
b011 #
1$
b011 &
b011 '
#1440000000
0!
0$
#1450000000
1!
b001 #
1$
b001 &
b001 '
#1460000000
0!
0$
#1470000000
1!
b000 #
1$
b000 &
b000 '
1(
#1480000000
0!
0$
#1490000000
1!
b100 #
1$
b100 &
b100 '
0(
#1500000000
0!
0$
#1510000000
1!
b010 #
1$
b010 &
b010 '
1(
#1520000000
0!
0$
#1530000000
1!
b101 #
1$
b101 &
b101 '
#1540000000
0!
0$
#1550000000
1!
b110 #
1$
b110 &
b110 '
#1560000000
0!
0$
#1570000000
1!
b111 #
1$
b111 &
b111 '
0(
#1580000000
0!
0$
#1590000000
1!
b011 #
1$
b011 &
b011 '
#1600000000
0!
0$
#1610000000
1!
b001 #
1$
b001 &
b001 '
#1620000000
0!
0$
#1630000000
1!
b000 #
1$
b000 &
b000 '
1(
#1640000000
0!
0$
#1650000000
1!
b100 #
1$
b100 &
b100 '
0(
#1660000000
0!
0$
#1670000000
1!
b010 #
1$
b010 &
b010 '
1(
#1680000000
0!
0$
#1690000000
1!
b101 #
1$
b101 &
b101 '
#1700000000
0!
0$
#1710000000
1!
b110 #
1$
b110 &
b110 '
#1720000000
0!
0$
#1730000000
1!
b111 #
1$
b111 &
b111 '
0(
#1740000000
0!
0$
#1750000000
1!
b011 #
1$
b011 &
b011 '
#1760000000
0!
0$
#1770000000
1!
b001 #
1$
b001 &
b001 '
#1780000000
0!
0$
#1790000000
1!
b000 #
1$
b000 &
b000 '
1(
#1800000000
0!
0$
#1810000000
1!
b100 #
1$
b100 &
b100 '
0(
#1820000000
0!
0$
#1830000000
1!
b010 #
1$
b010 &
b010 '
1(
#1840000000
0!
0$
#1850000000
1!
b101 #
1$
b101 &
b101 '
#1860000000
0!
0$
#1870000000
1!
b110 #
1$
b110 &
b110 '
#1880000000
0!
0$
#1890000000
1!
b111 #
1$
b111 &
b111 '
0(
#1900000000
0!
0$
#1910000000
1!
b011 #
1$
b011 &
b011 '
#1920000000
0!
0$
#1930000000
1!
b001 #
1$
b001 &
b001 '
#1940000000
0!
0$
#1950000000
1!
b000 #
1$
b000 &
b000 '
1(
#1960000000
0!
0$
#1970000000
1!
b100 #
1$
b100 &
b100 '
0(
#1980000000
0!
0$
#1990000000
1!
b010 #
1$
b010 &
b010 '
1(
#2000000000
0!
0$
#2010000000
1!
b101 #
1$
b101 &
b101 '
#2020000000
0!
0$
#2030000000
1!
b110 #
1$
b110 &
b110 '
#2040000000
0!
0$
#2050000000
1!
b111 #
1$
b111 &
b111 '
0(
#2060000000
0!
0$
#2070000000
1!
b011 #
1$
b011 &
b011 '
#2080000000
0!
0$
#2090000000
1!
b001 #
1$
b001 &
b001 '
#2100000000
0!
0$
#2110000000
1!
b000 #
1$
b000 &
b000 '
1(
#2120000000
0!
0$
#2130000000
1!
b100 #
1$
b100 &
b100 '
0(
#2140000000
0!
0$
#2150000000
1!
b010 #
1$
b010 &
b010 '
1(
#2160000000
0!
0$
#2170000000
1!
b101 #
1$
b101 &
b101 '
#2180000000
0!
0$
#2190000000
1!
b110 #
1$
b110 &
b110 '
#2200000000
0!
0$
#2210000000
1!
b111 #
1$
b111 &
b111 '
0(
#2220000000
0!
0$
#2230000000
1!
b011 #
1$
b011 &
b011 '
#2240000000
0!
0$
#2250000000
1!
b001 #
1$
b001 &
b001 '
#2260000000
0!
0$
#2270000000
1!
b000 #
1$
b000 &
b000 '
1(
#2280000000
0!
0$
#2290000000
1!
b100 #
1$
b100 &
b100 '
0(
#2300000000
0!
0$
#2310000000
1!
b010 #
1$
b010 &
b010 '
1(
#2320000000
0!
0$
#2330000000
1!
b101 #
1$
b101 &
b101 '
#2340000000
0!
0$
#2350000000
1!
b110 #
1$
b110 &
b110 '
#2360000000
0!
0$
#2370000000
1!
b111 #
1$
b111 &
b111 '
0(
#2380000000
0!
0$
#2390000000
1!
b011 #
1$
b011 &
b011 '
#2400000000
0!
0$
#2410000000
1!
b001 #
1$
b001 &
b001 '
#2420000000
0!
0$
#2430000000
1!
b000 #
1$
b000 &
b000 '
1(
#2440000000
0!
0$
#2450000000
1!
b100 #
1$
b100 &
b100 '
0(
#2460000000
0!
0$
#2470000000
1!
b010 #
1$
b010 &
b010 '
1(
#2480000000
0!
0$
#2490000000
1!
b101 #
1$
b101 &
b101 '
#2500000000
0!
0$
#2510000000
1!
b110 #
1$
b110 &
b110 '
#2520000000
0!
0$
#2530000000
1!
b111 #
1$
b111 &
b111 '
0(
#2540000000
0!
0$
#2550000000
1!
b011 #
1$
b011 &
b011 '
#2560000000
0!
0$
#2570000000
1!
b001 #
1$
b001 &
b001 '
#2580000000
0!
0$
#2590000000
1!
b000 #
1$
b000 &
b000 '
1(
#2600000000
0!
0$
#2610000000
1!
b100 #
1$
b100 &
b100 '
0(
#2620000000
0!
0$
#2630000000
1!
b010 #
1$
b010 &
b010 '
1(
#2640000000
0!
0$
#2650000000
1!
b101 #
1$
b101 &
b101 '
#2660000000
0!
0$
#2670000000
1!
b110 #
1$
b110 &
b110 '
#2680000000
0!
0$
#2690000000
1!
b111 #
1$
b111 &
b111 '
0(
#2700000000
0!
0$
#2710000000
1!
b011 #
1$
b011 &
b011 '
#2720000000
0!
0$
#2730000000
1!
b001 #
1$
b001 &
b001 '
#2740000000
0!
0$
#2750000000
1!
b000 #
1$
b000 &
b000 '
1(
#2760000000
0!
0$
#2770000000
1!
b100 #
1$
b100 &
b100 '
0(
#2780000000
0!
0$
#2790000000
1!
b010 #
1$
b010 &
b010 '
1(
#2800000000
0!
0$
#2810000000
1!
b101 #
1$
b101 &
b101 '
#2820000000
0!
0$
#2830000000
1!
b110 #
1$
b110 &
b110 '
#2840000000
0!
0$
#2850000000
1!
b111 #
1$
b111 &
b111 '
0(
#2860000000
0!
0$
#2870000000
1!
b011 #
1$
b011 &
b011 '
#2880000000
0!
0$
#2890000000
1!
b001 #
1$
b001 &
b001 '
#2900000000
0!
0$
#2910000000
1!
b000 #
1$
b000 &
b000 '
1(
#2920000000
0!
0$
#2930000000
1!
b100 #
1$
b100 &
b100 '
0(
#2940000000
0!
0$
#2950000000
1!
b010 #
1$
b010 &
b010 '
1(
#2960000000
0!
0$
#2970000000
1!
b101 #
1$
b101 &
b101 '
#2980000000
0!
0$
#2990000000
1!
b110 #
1$
b110 &
b110 '
#3000000000
0!
0$
#3010000000
1!
b111 #
1$
b111 &
b111 '
0(
#3020000000
0!
0$
#3030000000
1!
b011 #
1$
b011 &
b011 '
#3040000000
0!
0$
#3050000000
1!
b001 #
1$
b001 &
b001 '
#3060000000
0!
0$
#3070000000
1!
b000 #
1$
b000 &
b000 '
1(
#3080000000
0!
0$
#3090000000
1!
b100 #
1$
b100 &
b100 '
0(
#3100000000
0!
0$
#3110000000
1!
b010 #
1$
b010 &
b010 '
1(
#3120000000
0!
0$
#3130000000
1!
b101 #
1$
b101 &
b101 '
#3140000000
0!
0$
#3150000000
1!
b110 #
1$
b110 &
b110 '
#3160000000
0!
0$
#3170000000
1!
b111 #
1$
b111 &
b111 '
0(
#3180000000
0!
0$
#3190000000
1!
b011 #
1$
b011 &
b011 '
#3200000000
0!
0$
#3210000000
1!
b001 #
1$
b001 &
b001 '
#3220000000
0!
0$
#3230000000
1!
b000 #
1$
b000 &
b000 '
1(
#3240000000
0!
0$
#3250000000
1!
b100 #
1$
b100 &
b100 '
0(
#3260000000
0!
0$
#3270000000
1!
b010 #
1$
b010 &
b010 '
1(
#3280000000
0!
0$
#3290000000
1!
b101 #
1$
b101 &
b101 '
#3300000000
0!
0$
#3310000000
1!
b110 #
1$
b110 &
b110 '
#3320000000
0!
0$
#3330000000
1!
b111 #
1$
b111 &
b111 '
0(
#3340000000
0!
0$
#3350000000
1!
b011 #
1$
b011 &
b011 '
#3360000000
0!
0$
#3370000000
1!
b001 #
1$
b001 &
b001 '
#3380000000
0!
0$
#3390000000
1!
b000 #
1$
b000 &
b000 '
1(
#3400000000
0!
0$
#3410000000
1!
b100 #
1$
b100 &
b100 '
0(
#3420000000
0!
0$
#3430000000
1!
b010 #
1$
b010 &
b010 '
1(
#3440000000
0!
0$
#3450000000
1!
b101 #
1$
b101 &
b101 '
#3460000000
0!
0$
#3470000000
1!
b110 #
1$
b110 &
b110 '
#3480000000
0!
0$
#3490000000
1!
b111 #
1$
b111 &
b111 '
0(
#3500000000
0!
0$
#3510000000
1!
b011 #
1$
b011 &
b011 '
#3520000000
0!
0$
#3530000000
1!
b001 #
1$
b001 &
b001 '
#3540000000
0!
0$
#3550000000
1!
b000 #
1$
b000 &
b000 '
1(
#3560000000
0!
0$
#3570000000
1!
b100 #
1$
b100 &
b100 '
0(
#3580000000
0!
0$
#3590000000
1!
b010 #
1$
b010 &
b010 '
1(
#3600000000
0!
0$
#3610000000
1!
b101 #
1$
b101 &
b101 '
#3620000000
0!
0$
#3630000000
1!
b110 #
1$
b110 &
b110 '
#3640000000
0!
0$
#3650000000
1!
b111 #
1$
b111 &
b111 '
0(
#3660000000
0!
0$
#3670000000
1!
b011 #
1$
b011 &
b011 '
#3680000000
0!
0$
#3690000000
1!
b001 #
1$
b001 &
b001 '
#3700000000
0!
0$
#3710000000
1!
b000 #
1$
b000 &
b000 '
1(
#3720000000
0!
0$
#3730000000
1!
b100 #
1$
b100 &
b100 '
0(
#3740000000
0!
0$
#3750000000
1!
b010 #
1$
b010 &
b010 '
1(
#3760000000
0!
0$
#3770000000
1!
b101 #
1$
b101 &
b101 '
#3780000000
0!
0$
#3790000000
1!
b110 #
1$
b110 &
b110 '
#3800000000
0!
0$
#3810000000
1!
b111 #
1$
b111 &
b111 '
0(
#3820000000
0!
0$
#3830000000
1!
b011 #
1$
b011 &
b011 '
#3840000000
0!
0$
#3850000000
1!
b001 #
1$
b001 &
b001 '
#3860000000
0!
0$
#3870000000
1!
b000 #
1$
b000 &
b000 '
1(
#3880000000
0!
0$
#3890000000
1!
b100 #
1$
b100 &
b100 '
0(
#3900000000
0!
0$
#3910000000
1!
b010 #
1$
b010 &
b010 '
1(
#3920000000
0!
0$
#3930000000
1!
b101 #
1$
b101 &
b101 '
#3940000000
0!
0$
#3950000000
1!
b110 #
1$
b110 &
b110 '
#3960000000
0!
0$
#3970000000
1!
b111 #
1$
b111 &
b111 '
0(
#3980000000
0!
0$
#3990000000
1!
b011 #
1$
b011 &
b011 '
#4000000000
0!
0$
#4010000000
1!
b001 #
1$
b001 &
b001 '
#4020000000
0!
0$
#4030000000
1!
b000 #
1$
b000 &
b000 '
1(
#4040000000
0!
0$
#4050000000
1!
b100 #
1$
b100 &
b100 '
0(
#4060000000
0!
0$
#4070000000
1!
b010 #
1$
b010 &
b010 '
1(
#4080000000
0!
0$
#4090000000
1!
b101 #
1$
b101 &
b101 '
#4100000000
0!
0$
#4110000000
1!
b110 #
1$
b110 &
b110 '
#4120000000
0!
0$
#4130000000
1!
b111 #
1$
b111 &
b111 '
0(
#4140000000
0!
0$
#4150000000
1!
b011 #
1$
b011 &
b011 '
#4160000000
0!
0$
#4170000000
1!
b001 #
1$
b001 &
b001 '
#4180000000
0!
0$
#4190000000
1!
b000 #
1$
b000 &
b000 '
1(
#4200000000
0!
0$
#4210000000
1!
b100 #
1$
b100 &
b100 '
0(
#4220000000
0!
0$
#4230000000
1!
b010 #
1$
b010 &
b010 '
1(
#4240000000
0!
0$
#4250000000
1!
b101 #
1$
b101 &
b101 '
#4260000000
0!
0$
#4270000000
1!
b110 #
1$
b110 &
b110 '
#4280000000
0!
0$
#4290000000
1!
b111 #
1$
b111 &
b111 '
0(
#4300000000
0!
0$
#4310000000
1!
b011 #
1$
b011 &
b011 '
#4320000000
0!
0$
#4330000000
1!
b001 #
1$
b001 &
b001 '
#4340000000
0!
0$
#4350000000
1!
b000 #
1$
b000 &
b000 '
1(
#4360000000
0!
0$
#4370000000
1!
b100 #
1$
b100 &
b100 '
0(
#4380000000
0!
0$
#4390000000
1!
b010 #
1$
b010 &
b010 '
1(
#4400000000
0!
0$
#4410000000
1!
b101 #
1$
b101 &
b101 '
#4420000000
0!
0$
#4430000000
1!
b110 #
1$
b110 &
b110 '
#4440000000
0!
0$
#4450000000
1!
b111 #
1$
b111 &
b111 '
0(
#4460000000
0!
0$
#4470000000
1!
b011 #
1$
b011 &
b011 '
#4480000000
0!
0$
#4490000000
1!
b001 #
1$
b001 &
b001 '
#4500000000
0!
0$
#4510000000
1!
b000 #
1$
b000 &
b000 '
1(
#4520000000
0!
0$
#4530000000
1!
b100 #
1$
b100 &
b100 '
0(
#4540000000
0!
0$
#4550000000
1!
b010 #
1$
b010 &
b010 '
1(
#4560000000
0!
0$
#4570000000
1!
b101 #
1$
b101 &
b101 '
#4580000000
0!
0$
#4590000000
1!
b110 #
1$
b110 &
b110 '
#4600000000
0!
0$
#4610000000
1!
b111 #
1$
b111 &
b111 '
0(
#4620000000
0!
0$
#4630000000
1!
b011 #
1$
b011 &
b011 '
#4640000000
0!
0$
#4650000000
1!
b001 #
1$
b001 &
b001 '
#4660000000
0!
0$
#4670000000
1!
b000 #
1$
b000 &
b000 '
1(
#4680000000
0!
0$
#4690000000
1!
b100 #
1$
b100 &
b100 '
0(
#4700000000
0!
0$
#4710000000
1!
b010 #
1$
b010 &
b010 '
1(
#4720000000
0!
0$
#4730000000
1!
b101 #
1$
b101 &
b101 '
#4740000000
0!
0$
#4750000000
1!
b110 #
1$
b110 &
b110 '
#4760000000
0!
0$
#4770000000
1!
b111 #
1$
b111 &
b111 '
0(
#4780000000
0!
0$
#4790000000
1!
b011 #
1$
b011 &
b011 '
#4800000000
0!
0$
#4810000000
1!
b001 #
1$
b001 &
b001 '
#4820000000
0!
0$
#4830000000
1!
b000 #
1$
b000 &
b000 '
1(
#4840000000
0!
0$
#4850000000
1!
b100 #
1$
b100 &
b100 '
0(
#4860000000
0!
0$
#4870000000
1!
b010 #
1$
b010 &
b010 '
1(
#4880000000
0!
0$
#4890000000
1!
b101 #
1$
b101 &
b101 '
#4900000000
0!
0$
#4910000000
1!
b110 #
1$
b110 &
b110 '
#4920000000
0!
0$
#4930000000
1!
b111 #
1$
b111 &
b111 '
0(
#4940000000
0!
0$
#4950000000
1!
b011 #
1$
b011 &
b011 '
#4960000000
0!
0$
#4970000000
1!
b001 #
1$
b001 &
b001 '
#4980000000
0!
0$
#4990000000
1!
b000 #
1$
b000 &
b000 '
1(
#5000000000
0!
0$
#5010000000
1!
b100 #
1$
b100 &
b100 '
0(
#5020000000
0!
0$
#5030000000
1!
b010 #
1$
b010 &
b010 '
1(
#5040000000
0!
0$
#5050000000
1!
b101 #
1$
b101 &
b101 '
#5060000000
0!
0$
#5070000000
1!
b110 #
1$
b110 &
b110 '
#5080000000
0!
0$
#5090000000
1!
b111 #
1$
b111 &
b111 '
0(
#5100000000
0!
0$
#5110000000
1!
b011 #
1$
b011 &
b011 '
#5120000000
0!
0$
#5130000000
1!
b001 #
1$
b001 &
b001 '
#5140000000
0!
0$
#5150000000
1!
b000 #
1$
b000 &
b000 '
1(
#5160000000
0!
0$
#5170000000
1!
b100 #
1$
b100 &
b100 '
0(
#5180000000
0!
0$
#5190000000
1!
b010 #
1$
b010 &
b010 '
1(
#5200000000
0!
0$
#5210000000
1!
b101 #
1$
b101 &
b101 '
#5220000000
0!
0$
#5230000000
1!
b110 #
1$
b110 &
b110 '
#5240000000
0!
0$
#5250000000
1!
b111 #
1$
b111 &
b111 '
0(
#5260000000
0!
0$
#5270000000
1!
b011 #
1$
b011 &
b011 '
#5280000000
0!
0$
#5290000000
1!
b001 #
1$
b001 &
b001 '
#5300000000
0!
0$
#5310000000
1!
b000 #
1$
b000 &
b000 '
1(
#5320000000
0!
0$
#5330000000
1!
b100 #
1$
b100 &
b100 '
0(
#5340000000
0!
0$
#5350000000
1!
b010 #
1$
b010 &
b010 '
1(
#5360000000
0!
0$
#5370000000
1!
b101 #
1$
b101 &
b101 '
#5380000000
0!
0$
#5390000000
1!
b110 #
1$
b110 &
b110 '
#5400000000
0!
0$
#5410000000
1!
b111 #
1$
b111 &
b111 '
0(
#5420000000
0!
0$
#5430000000
1!
b011 #
1$
b011 &
b011 '
#5440000000
0!
0$
#5450000000
1!
b001 #
1$
b001 &
b001 '
#5460000000
0!
0$
#5470000000
1!
b000 #
1$
b000 &
b000 '
1(
#5480000000
0!
0$
#5490000000
1!
b100 #
1$
b100 &
b100 '
0(
#5500000000
0!
0$
#5510000000
1!
b010 #
1$
b010 &
b010 '
1(
#5520000000
0!
0$
#5530000000
1!
b101 #
1$
b101 &
b101 '
#5540000000
0!
0$
#5550000000
1!
b110 #
1$
b110 &
b110 '
#5560000000
0!
0$
#5570000000
1!
b111 #
1$
b111 &
b111 '
0(
#5580000000
0!
0$
#5590000000
1!
b011 #
1$
b011 &
b011 '
#5600000000
0!
0$
#5610000000
1!
b001 #
1$
b001 &
b001 '
#5620000000
0!
0$
#5630000000
1!
b000 #
1$
b000 &
b000 '
1(
#5640000000
0!
0$
#5650000000
1!
b100 #
1$
b100 &
b100 '
0(
#5660000000
0!
0$
#5670000000
1!
b010 #
1$
b010 &
b010 '
1(
#5680000000
0!
0$
#5690000000
1!
b101 #
1$
b101 &
b101 '
#5700000000
0!
0$
#5710000000
1!
b110 #
1$
b110 &
b110 '
#5720000000
0!
0$
#5730000000
1!
b111 #
1$
b111 &
b111 '
0(
#5740000000
0!
0$
#5750000000
1!
b011 #
1$
b011 &
b011 '
#5760000000
0!
0$
#5770000000
1!
b001 #
1$
b001 &
b001 '
#5780000000
0!
0$
#5790000000
1!
b000 #
1$
b000 &
b000 '
1(
#5800000000
0!
0$
#5810000000
1!
b100 #
1$
b100 &
b100 '
0(
#5820000000
0!
0$
#5830000000
1!
b010 #
1$
b010 &
b010 '
1(
#5840000000
0!
0$
#5850000000
1!
b101 #
1$
b101 &
b101 '
#5860000000
0!
0$
#5870000000
1!
b110 #
1$
b110 &
b110 '
#5880000000
0!
0$
#5890000000
1!
b111 #
1$
b111 &
b111 '
0(
#5900000000
0!
0$
#5910000000
1!
b011 #
1$
b011 &
b011 '
#5920000000
0!
0$
#5930000000
1!
b001 #
1$
b001 &
b001 '
#5940000000
0!
0$
#5950000000
1!
b000 #
1$
b000 &
b000 '
1(
#5960000000
0!
0$
#5970000000
1!
b100 #
1$
b100 &
b100 '
0(
#5980000000
0!
0$
#5990000000
1!
b010 #
1$
b010 &
b010 '
1(
#6000000000
0!
0$
#6010000000
1!
b101 #
1$
b101 &
b101 '
#6020000000
0!
0$
#6030000000
1!
b110 #
1$
b110 &
b110 '
#6040000000
0!
0$
#6050000000
1!
b111 #
1$
b111 &
b111 '
0(
#6060000000
0!
0$
#6070000000
1!
b011 #
1$
b011 &
b011 '
#6080000000
0!
0$
#6090000000
1!
b001 #
1$
b001 &
b001 '
#6100000000
0!
0$
#6110000000
1!
b000 #
1$
b000 &
b000 '
1(
#6120000000
0!
0$
#6130000000
1!
b100 #
1$
b100 &
b100 '
0(
#6140000000
0!
0$
#6150000000
1!
b010 #
1$
b010 &
b010 '
1(
#6160000000
0!
0$
#6170000000
1!
b101 #
1$
b101 &
b101 '
#6180000000
0!
0$
#6190000000
1!
b110 #
1$
b110 &
b110 '
#6200000000
0!
0$
#6210000000
1!
b111 #
1$
b111 &
b111 '
0(
#6220000000
0!
0$
#6230000000
1!
b011 #
1$
b011 &
b011 '
#6240000000
0!
0$
#6250000000
1!
b001 #
1$
b001 &
b001 '
#6260000000
0!
0$
#6270000000
1!
b000 #
1$
b000 &
b000 '
1(
#6280000000
0!
0$
#6290000000
1!
b100 #
1$
b100 &
b100 '
0(
#6300000000
0!
0$
#6310000000
1!
b010 #
1$
b010 &
b010 '
1(
#6320000000
0!
0$
#6330000000
1!
b101 #
1$
b101 &
b101 '
#6340000000
0!
0$
#6350000000
1!
b110 #
1$
b110 &
b110 '
#6360000000
0!
0$
#6370000000
1!
b111 #
1$
b111 &
b111 '
0(
#6380000000
0!
0$
#6390000000
1!
b011 #
1$
b011 &
b011 '
#6400000000
0!
0$
#6410000000
1!
b001 #
1$
b001 &
b001 '
#6420000000
0!
0$
#6430000000
1!
b000 #
1$
b000 &
b000 '
1(
#6440000000
0!
0$
#6450000000
1!
b100 #
1$
b100 &
b100 '
0(
#6460000000
0!
0$
#6470000000
1!
b010 #
1$
b010 &
b010 '
1(
#6480000000
0!
0$
#6490000000
1!
b101 #
1$
b101 &
b101 '
#6500000000
0!
0$
#6510000000
1!
b110 #
1$
b110 &
b110 '
#6520000000
0!
0$
#6530000000
1!
b111 #
1$
b111 &
b111 '
0(
#6540000000
0!
0$
#6550000000
1!
b011 #
1$
b011 &
b011 '
#6560000000
0!
0$
#6570000000
1!
b001 #
1$
b001 &
b001 '
#6580000000
0!
0$
#6590000000
1!
b000 #
1$
b000 &
b000 '
1(
#6600000000
0!
0$
#6610000000
1!
b100 #
1$
b100 &
b100 '
0(
#6620000000
0!
0$
#6630000000
1!
b010 #
1$
b010 &
b010 '
1(
#6640000000
0!
0$
#6650000000
1!
b101 #
1$
b101 &
b101 '
#6660000000
0!
0$
#6670000000
1!
b110 #
1$
b110 &
b110 '
#6680000000
0!
0$
#6690000000
1!
b111 #
1$
b111 &
b111 '
0(
#6700000000
0!
0$
#6710000000
1!
b011 #
1$
b011 &
b011 '
#6720000000
0!
0$
#6730000000
1!
b001 #
1$
b001 &
b001 '
#6740000000
0!
0$
#6750000000
1!
b000 #
1$
b000 &
b000 '
1(
#6760000000
0!
0$
#6770000000
1!
b100 #
1$
b100 &
b100 '
0(
#6780000000
0!
0$
#6790000000
1!
b010 #
1$
b010 &
b010 '
1(
#6800000000
0!
0$
#6810000000
1!
b101 #
1$
b101 &
b101 '
#6820000000
0!
0$
#6830000000
1!
b110 #
1$
b110 &
b110 '
#6840000000
0!
0$
#6850000000
1!
b111 #
1$
b111 &
b111 '
0(
#6860000000
0!
0$
#6870000000
1!
b011 #
1$
b011 &
b011 '
#6880000000
0!
0$
#6890000000
1!
b001 #
1$
b001 &
b001 '
#6900000000
0!
0$
#6910000000
1!
b000 #
1$
b000 &
b000 '
1(
#6920000000
0!
0$
#6930000000
1!
b100 #
1$
b100 &
b100 '
0(
#6940000000
0!
0$
#6950000000
1!
b010 #
1$
b010 &
b010 '
1(
#6960000000
0!
0$
#6970000000
1!
b101 #
1$
b101 &
b101 '
